Workbook

Sheet 0_AI_to_EV_Bridge
B1: AI to EV bridge
B2: One bridge, from the enterprise value you have today to the enterprise value the AI program can carry. Everything is pulled from the tabs behind it — only the two yellow cells are entered here.
B5: INPUTS
B6: ENTER: Basis at entry | C6: ARR | E6: How the deal was struck, not a judgement about today. The basis is fixed for the whole model so before and after stay comparable. Anaplan entered at 18.1x revenue in 2022 while loss-making.
B7: ENTER: Enterprise value today | C7: 11000000000 | E7: Your own valuation, or the entry basis.
B8: ENTER: ARR | C8: 1200000000 | E8: Recurring revenue.
B9: Total revenue | C9: ='4b_Value_Pools_by_Capability'!$D$6 -> 1500000000 | E9: ARR plus professional services. Set on 4b.
B10: ENTER: EBITDA margin on total revenue | C10: 0.42 | E10: Carried for reference and for the Rule of 40 on 4d. Not used in the multiple while the basis is ARR. Verify before quoting.
B11: Valuation metric | C11: =IF($C$6="EBITDA",$C$9*$C$10,$C$8) -> 1200000000 | E11: EBITDA if the basis is EBITDA, ARR if it is ARR.
B12: Current multiple | C12: =IFERROR($C$7/$C$11,0) -> 9.1666667 | E12: Enterprise value divided by the metric. The anchor every scenario works from.
B13: Industry vertical | C13: ='4b_Value_Pools_by_Capability'!$D$4 -> Vertical SaaS | E13: Set on 4b.
B16: POSITION
B18: THE BRIDGE
B19: Closing two capability levels. Capturing the pool does two things: its revenue half lifts ARR, and the whole of it lifts growth, which lifts the multiple. Shown separately so the two effects are visible.
B21: Enterprise value today | C21: =$C$7 -> 11000000000 | E21: ARR $1.2B at 9.17x.
B22: plus ARR uplift | C22: =('8_Enterprise_Value'!$C$35-'8_Enterprise_Value'!$C$25)*'8_Enterprise_Value'!$D$33 -> 2.2130297e+08 | E22: The revenue half of the pool, valued at today’s multiple.
B23: plus multiple uplift | C23: ='8_Enterprise_Value'!$C$35*('8_Enterprise_Value'!$D$35-'8_Enterprise_Value'!$D$33) -> 2.9657974e+08 | E23: The multiple moving from 9.17x to 9.38x, on the new ARR base. | M23: New EV | P23: New EV
B24: less cost of the programme | C24: -16295149 | E24: NPV of build plus operating cost, Barr Eq. 26. | M24: =$C$26 -> 0 | P24: =$C$26 -> 0
B25: NEW ENTERPRISE VALUE | C25: =SUM($C$21:$C$24) -> 1.1501588e+10 | E25: ARR $1.22B at 9.38x, less cost.
B27: Uplift on today | C27: =IFERROR(($C$25-$C$21)/$C$21,0) -> 0.045598869
B28: Value density | C28: ='8_Enterprise_Value'!$C$38 -> 30.781404
B29: Check: ties to 8_Enterprise_Value | C29: =IF(ROUND($C$25,0)=ROUND('8_Enterprise_Value'!$E$35-'8_Enterprise_Value'!$C$29,0),"Ties","CHECK") -> Ties
B39: Chart data — calculated, do not edit
C40: Base | D40: Value
B41: EV today | C41: 0 | D41: =$C$21 -> 11000000000
B42: ARR uplift | C42: =$C$21 -> 11000000000 | D42: =$C$22 -> 2.2130297e+08
B43: Multiple uplift | C43: =$C$21+$C$22 -> 1.1221303e+10 | D43: =$C$23 -> 2.9657974e+08
B44: Cost | C44: =$C$25 -> 1.1501588e+10 | D44: =-$C$24 -> 16295149
B45: New EV | C45: 0 | D45: =$C$25 -> 1.1501588e+10
B47: The vertical axis starts at $10.4B. The two middle bars are about 2% of an $11B base — on a full axis they would not be visible. The base is the story here, not the bridge.

Sheet 1_Industry_Rubric
B2: Frontier rubric AI-enabled applications
B3: The benchmark is the cohort commanding the highest multiples in software, not other SaaS companies. Six dimensions define it. The ceiling on each is what a named company has actually achieved, not a theoretical maximum.
B5: Company | C5: Valuation | D5: ARR | E5: Multiple | F5: Pricing model | G5: What it displaces
B6: Sierra | C6: $10B | D6: ~$100M | E6: 67-100x | F6: Outcome, per resolution | G6: Support agent salary
B7: Harvey | C7: $11B | D7: ~$190M | E7: 55-58x | F7: Seat and licence | G7: Junior associate at $200/hr
B8: Cursor (Anysphere) | C8: $29-50B | D8: $0.5-2B | E8: 25-59x | F8: Seat | G8: Developer time
B9: Glean | C9: $7.2B | D9: $300M | E9: 24x | F9: Seat | G9: Knowledge worker search time
B10: Decagon | C10: $4.5B | D10: ~$35M | E10: high, 200%+ NRR | F10: Outcome | G10: Support agent salary
B11: Growth rate does not explain the spread — the fastest grower priced near the bottom. The premium tracks category position. Harvey trades at 55-58x on seat pricing, which is why outcome pricing is one route to the frontier and not the test itself.
B13: The six dimensions
B14: Code | C14: Dimension | D14: What it asks | E14: Frontier | F14: Held by | G14: Why not 10
B15: BD | C15: Budget Displaced | D15: Does your revenue come out of a labour line or a software line. | E15: 10 | F15: Harvey, Sierra, Cursor | G15: Full marks. Harvey's stated competitor is a junior associate at $200 an hour; Sierra's is a support agent; Cursor's is developer time. None of them competes for a software budget. This is what displacing a labour budget looks like — there is nothing further to reach.
B16: OA | C16: Outcome Attribution | D16: Can the value delivered be measured, isolated and agreed with the customer in advance. | E16: 9 | F16: Sierra, Fin | G16: Sierra bills on a resolved conversation and does not charge when unresolved; Fin publishes $0.99 per resolution. Held just below full marks because the outcome definition is still negotiated per contract and edge cases are contested deal by deal.
B17: AUT | C17: Autonomy | D17: How much of the work completes without a person, and what the person is for. | E17: 9.5 | F17: Sierra, Harvey | G17: Sierra agents process returns and manage cancellations through API connections to systems of record; Harvey customers run more than 25,000 custom agents. Held marginally below full marks because escalation to humans remains routine and is priced for.
B18: DC | C18: Data Compounding | D18: Does the product improve from usage in a way a competitor with the same models cannot replicate. | E18: 9 | F18: Harvey, Glean | G18: Vertical-specific agents with proprietary training data command the highest valuations in the cohort. Harvey holds legal workflow depth across most of the AmLaw 100. Held below full marks because the underlying models are third-party and commoditising, which is the standing bear case.
B19: VEL | C19: Velocity to Scale | D19: How fast the business reaches scale, which is what the market is actually pricing. | E19: 10 | F19: Cursor, Legora | G19: Full marks. Cursor reached $100M ARR in roughly 12 months, Legora in 18, against 36 for Slack. This is the fastest scaling enterprise software has produced.
B20: DE | C20: Delivery Elasticity | D20: Does serving more customers or more volume require proportionally more people. | E20: 8.5 | F20: Fin, Glean | G20: Fin deploys in days with published pricing and no platform fee. Held furthest below full marks because inference is real cost of goods — 18-23% of revenue — and AI gross margins run 50-60% against 70-90% for mature software. Nobody in the cohort has achieved elastic delivery.
C21: FRONTIER POSITION | E21: =AVERAGE(E15:E20) -> 9.3333333
B23: Level anchors by capability
B24: Seventy-two sets of five. Ten value levers and two enablers across the six dimensions. Wording is written per lever — no two blocks repeat.
B26: Capability | C26: Dimension | D26: L1 Laggard | E26: L2 Follower | F26: L3 Practitioner | G26: L4 Leader | H26: L5 Frontier
B27: Product and services differentiation | C27: Budget Displaced | D27: Priced against competing software. The buyer's alternative is another licence. | E27: Priced against software, with a productivity claim attached to justify the premium. | F27: Priced against software but the business case cites a headcount number. | G27: Priced against a named labour line, with the customer's cost per unit of that work known. | H27: The buyer's alternative is hiring. You are compared to a salary, not to a licence.
C28: Outcome Attribution | D28: What the product delivers is asserted in marketing and argued at renewal. | E28: You report adoption and usage to customers, not the value produced. | F28: You report outcomes, but cannot separate your contribution from everything else the customer did. | G28: Baselines are agreed with the customer before deployment and the delta withstands challenge. | H28: The outcome is machine-verifiable and published, not negotiated per contract.
C29: Autonomy | D29: The product records work a person at the customer does. | E29: The product suggests; a customer employee decides and executes every time. | F29: The product executes defined tasks; a customer employee approves before anything commits. | G29: The product completes whole customer workflows end to end, acting in systems of record. | H29: The product runs long-horizon, multi-step processes and escalates only by exception.
C30: Data Compounding | D30: Customer data sits in per-tenant silos. Nothing improves from usage. | E30: Usage is logged but never fed back into the product. | F30: Aggregate usage informs the roadmap, not the product's behaviour. | G30: Usage improves product behaviour across the base, with contractual rights in place to permit it. | H30: The corpus is the moat. A competitor with the same models cannot match the output.
C31: Velocity to Scale | D31: Flat, or too small to measure. | E31: Growing, but slower than the rest of the business. | F31: Growing faster than the rest of the business. | G31: Doubling annually off a base large enough to matter. | H31: The fastest-growing line in the company, and disclosed as such.
C32: Delivery Elasticity | D32: Every new customer needs a services engagement before the product produces anything. | E32: Onboarding is templated but still requires your people. | F32: Standard customers self-configure; your people handle the complex ones. | G32: Most customers reach value in days without your involvement. | H32: The marginal cost of the next customer is compute. No implementation function exists.
B33: Pricing and packaging | C33: Budget Displaced | D33: Priced per seat. Tiers are defined by feature count. | E33: Per seat, with usage add-ons bolted on to capture heavy users. | F33: A hybrid: platform fee plus a usage or volume component the customer can forecast. | G33: Priced on a value metric the customer already measures in their own P&L. | H33: Priced per outcome delivered. Seats are irrelevant to the contract.
C34: Outcome Attribution | D34: No outcome measurement. Discounting is unmanaged and realised price is discovered after the fact. | E34: Outcomes are claimed in marketing; realised price is tracked quarterly. | F34: Outcomes are reported to customers and discount approval follows a policy. | G34: Baselines are agreed before deployment and realised price holds within a narrow band of list. | H34: Outcome measurement is contractual and audited, and price realisation is designed into the metric rather than defended.
C35: Autonomy | D35: Every price is set by a person in a spreadsheet. | E35: Rate cards exist; exceptions are negotiated individually. | F35: Pricing rules are encoded and most quotes follow them. | G35: Price is set by the system from the value metric; humans handle exceptions. | H35: Pricing adjusts continuously to measured value and usage without a person in the loop.
C36: Data Compounding | D36: No record of what customers paid or why. | E36: Pricing history is stored but never analysed. | F36: Win-loss by price point is reviewed periodically. | G36: Realised price and churn data automatically re-tune the rate card. | H36: The pricing corpus is an advantage no competitor can see or replicate.
C37: Velocity to Scale | D37: Pricing changes take a year and a reorganisation. | E37: Changes ship annually, applied to new business only. | F37: Changes reach new business within a quarter. | G37: A new pricing model reaches the whole base within a renewal cycle. | H37: Pricing experiments run continuously across segments at no delivery cost.
C38: Delivery Elasticity | D38: Every non-standard deal needs finance to build a model. | E38: Templates exist but complex deals still consume finance time. | F38: Standard structures self-serve; finance handles the complex minority. | G38: Deal volume can double without adding pricing or finance headcount. | H38: The marginal cost of quoting the next deal is compute.
B39: Sales effectiveness | C39: Budget Displaced | D39: AI tooling is added to the sales stack. Selling capacity is unchanged. | E39: Reps report time saved, but the sales payroll has not moved. | F39: Freed selling time is reinvested in more activity rather than fewer sellers. | G39: Quota coverage has been achieved with fewer sellers than the plan called for. | H39: Selling capacity is set by compute, not by the number of sellers.
C40: Outcome Attribution | D40: Pipeline is attributed to reps by convention. No system contribution is measured. | E40: System usage is measured; its effect on pipeline is not. | F40: System-sourced pipeline is tracked but confounded with rep effort. | G40: System-sourced and rep-sourced pipeline are separated and the split withstands scrutiny. | H40: Contribution per system action is measured and reported continuously.
C41: Autonomy | D41: Reps research, write and follow up manually. | E41: AI drafts outreach and summarises calls; the rep does everything else. | F41: The system prioritises and sequences; a rep approves before anything sends. | G41: Agents run qualification and multi-threaded follow-up without a rep in the loop. | H41: The motion runs unattended to a qualified opportunity and escalates by exception.
C42: Data Compounding | D42: Billing and usage data is not analysed. | E42: Data is reported but never changes pricing. | F42: Pricing is reviewed periodically using historical data. | G42: Billing and usage data automatically improves pricing and packaging decisions. | H42: The pricing and usage record is an asset a competitor could not assemble.
C43: Velocity to Scale | D43: Quote-to-cash cycle time is unchanged or lengthening. | E43: Cycle time falling by a few percent a year. | F43: Cycle time falling by double digits a year. | G43: Cycle time has halved on a multi-year view. | H43: Billing and collection run in near real time.
C44: Delivery Elasticity | D44: Quote-to-cash headcount rises one for one with transaction volume. | E44: Some leverage, but headcount still tracks volume closely. | F44: Headcount grows at roughly half the rate of volume. | G44: Volume can double with little or no added headcount. | H44: The marginal cost of an additional transaction is compute, not people.
B45: Customer retention and expansion | C45: Budget Displaced | D45: Service is a cost you absorb. It appears in no customer business case. | E45: Service quality is a selling point, but nothing in the customer's budget moves because of it. | F45: The customer's business case counts service hours saved on their side. | G45: The customer has retired support headcount because of what you deliver. | H45: You are paid for resolutions the customer would otherwise have staffed.
C46: Outcome Attribution | D46: Neither you nor the customer can say what was resolved and what was deflected. | E46: You report ticket volume and deflection rate as though they were outcomes. | F46: Resolution is tracked, but not separated from customers giving up or self-solving. | G46: Resolution quality is measured against an agreed definition and reported to the customer. | H46: Resolution is binary and machine-verified, and billing depends on it.
C47: Autonomy | D47: Every interaction is queued to a person. | E47: Agents draft replies; a person sends every one. | F47: Common intents resolve automatically with a defined escalation path. | G47: Most interactions close without a person touching them. | H47: The service runs unattended across channels and escalates only by exception.
C48: Data Compounding | D48: Resolved cases are closed and forgotten. | E48: Case history is stored but never used to improve handling. | F48: Case analysis informs periodic training and content updates. | G48: Every resolved case automatically improves how the next one is handled, across all customers. | H48: The resolution corpus is an asset a competitor could not assemble.
C49: Velocity to Scale | D49: Self-service share is flat or falling. | E49: Self-service share improving by a few points a year. | F49: Self-service share improving by double digits a year. | G49: Self-service share doubling on a multi-year view. | H49: Step change — the majority of volume moved to self-service inside two years.
C50: Delivery Elasticity | D50: Support headcount rises one for one with ticket volume. | E50: Some leverage from tooling, but headcount still tracks volume closely. | F50: Support headcount grows at roughly half the rate of volume. | G50: Volume can double with little or no added support headcount. | H50: The marginal cost of additional volume is compute, not people.
B51: Ecosystem strategy | C51: Budget Displaced | D51: Partners resell a licence. Nothing in the end customer’s budget moves. | E51: Partner pitches cite productivity but the business case is software against software. | F51: Partner business cases cite headcount the end customer will not need. | G51: Partners price against a named labour line in the end customer’s operation. | H51: Partners sell against the cost of hiring. The comparison is a salary, not a licence.
C52: Outcome Attribution | D52: Partner-influenced revenue is asserted, not measured. | E52: Partner-sourced deals are tagged in the CRM but the tag is unreliable. | F52: Partner contribution is tracked but confounded with direct effort. | G52: Partner-sourced and direct pipeline are cleanly separated and the split withstands audit. | H52: Value delivered through each partner is measured continuously and settles commercially.
C53: Autonomy | D53: Every integration is built and maintained by your engineers. | E53: Partners submit requirements; your team builds. | F53: A documented API lets partners build without your engineers, with review before release. | G53: Partners build, test and ship on your surface without your involvement. | H53: The ecosystem extends itself. You set policy, not roadmap.
C54: Data Compounding | D54: No visibility into what partners do with the product. | E54: Partner usage is logged but never analysed. | F54: Partner usage informs which integrations get invested in. | G54: Cross-partner data measurably improves the product for every partner. | H54: The ecosystem data is a moat. A competitor starting today could not assemble it.
C55: Velocity to Scale | D55: Partner revenue is flat or immaterial. | E55: Growing, but slower than direct. | F55: Growing faster than direct. | G55: Partner-sourced revenue doubling annually off a base that matters. | H55: The ecosystem is the fastest-growing channel and is disclosed as such.
C56: Delivery Elasticity | D56: Each new partner needs a bespoke engagement. | E56: Onboarding is templated but still consumes your people. | F56: Most partners self-onboard; your team handles the complex ones. | G56: Partner count can double with no added partner-management headcount. | H56: The marginal cost of the next partner is compute.
B57: Product engineering | C57: Budget Displaced | D57: AI tooling is available. Engineering payroll is unchanged and unexamined. | E57: Developers report time saved, but engineering payroll has not moved. | F57: Freed engineering time is reinvested in more work rather than fewer engineers. | G57: Roadmap scope has been delivered with fewer engineers than the plan called for. | H57: Delivery capacity is set by compute, not by headcount.
C58: Outcome Attribution | D58: No measurement of what AI assistance contributes to delivery. | E58: Tool adoption is measured; its effect on throughput is not. | F58: Throughput is tracked but confounded with team changes and scope. | G58: AI-assisted and unassisted throughput are separated and the split withstands scrutiny. | H58: Contribution per assisted commit is measured continuously and reported.
C59: Autonomy | D59: Engineers write, test and review every line by hand. | E59: AI suggests code; an engineer accepts or rejects every suggestion. | F59: AI completes defined tasks; an engineer reviews before merge. | G59: Agents deliver whole tickets end to end; engineers review exceptions. | H59: Agents run multi-step delivery within policy and escalate only by exception.
C60: Data Compounding | D60: Nothing is learned from the codebase or from past delivery. | E60: History exists in the repo but never informs tooling. | F60: Retrospective analysis informs practice periodically. | G60: The codebase and delivery record automatically improve assistance quality. | H60: The accumulated engineering corpus is an advantage a competitor cannot replicate.
C61: Velocity to Scale | D61: Release cadence is flat or lengthening. | E61: Cadence improving slowly. | F61: Cadence improving by double digits year on year. | G61: Throughput doubling on a multi-year view off a base that matters. | H61: Continuous delivery at a rate the peer group cannot match.
C62: Delivery Elasticity | D62: Every increment of scope needs a proportional increment of engineers. | E62: Some leverage from platform work, but headcount tracks scope closely. | F62: Scope grows at roughly twice the rate of headcount. | G62: Scope can double with little added engineering headcount. | H62: The marginal cost of the next feature is compute, not people.
B63: Revenue operations | C63: Budget Displaced | D63: Quote-to-cash is manual and its cost is not examined. | E63: Time savings are reported but the revops payroll is unchanged. | F63: Freed time is reinvested in more deal support rather than fewer people. | G63: Deal volume has grown while revops headcount has not. | H63: Quote-to-cash capacity is set by compute. Headcount is a policy choice.
C64: Outcome Attribution | D64: Forecast accuracy and discount leakage are not measured. | E64: Both are reported after the quarter and explained, not managed. | F64: Both are tracked against a target and reviewed monthly. | G64: Forecast variance and leakage are managed to an agreed baseline that withstands board scrutiny. | H64: Forecast and realised price are machine-verified against contract terms continuously.
C65: Autonomy | D65: Quotes, contracts and invoices are assembled by hand. | E65: Templates exist; approvals and billing remain manual. | F65: CPQ is configured and most standard deals flow through it. | G65: Standard deals quote, contract and bill with no human touch; exceptions are routed. | H65: The whole chain runs unattended within policy, including usage and outcome terms.
C66: Data Compounding | D66: Deal history is not captured in a usable form. | E66: History is stored but never changes how deals are structured. | F66: Deal structure analysis informs policy at QBR. | G66: Closed deal data automatically re-tunes approval thresholds and terms. | H66: The accumulated commercial record is an advantage a competitor cannot buy.
C67: Velocity to Scale | D67: Process changes take a year to reach the field. | E67: Changes ship annually. | F67: Changes reach the field within a quarter. | G67: A new process reaches the whole organisation within one cycle. | H67: Process adapts continuously with no rollout cost.
C68: Delivery Elasticity | D68: Deal volume growth requires proportional revops headcount. | E68: Some leverage from tooling; headcount still tracks volume. | F68: Volume grows at roughly twice the rate of headcount. | G68: Volume can double with no added revops headcount. | H68: The marginal cost of the next transaction is compute.
B69: Supplier and infrastructure cost | C69: Budget Displaced | D69: Third-party AI spend is added on top of existing payroll. | E69: Spend is justified by a productivity claim with no offsetting saving. | F69: Spend displaces some contractor cost but no permanent headcount. | G69: Third-party spend has replaced internal labour, and the saving is visible. | H69: Buying compute is explicitly a substitute for hiring, and priced that way.
C70: Outcome Attribution | D70: No. Vendor invoices are not attributed to anything. | E70: Spend is attributed by vendor, not by customer or feature. | F70: Spend is allocated to teams, but not to individual customers. | G70: Cost to serve is known per customer and per feature, including inference. | H70: Cost to serve per customer is reported continuously and drives pricing decisions.
C71: Autonomy | D71: Usage is discovered at renewal. Nothing is metered. | E71: Usage is visible in dashboards; decisions are manual and periodic. | F71: Usage is metered per workload; commitments are reviewed on data. | G71: Commitments are right-sized automatically at workload level. | H71: Procurement and capacity decisions execute automatically within policy.
C72: Data Compounding | D72: Spend history is not retained in usable form. | E72: Spend data exists but is not analysed. | F72: Spend analysis informs annual negotiation. | G72: Spend and usage data automatically improves architecture and procurement decisions. | H72: The accumulated cost and usage record is a durable negotiating advantage.
C73: Velocity to Scale | D73: The same or more. Spend rises in step with usage. | E73: A few percent less. | F73: Double digits less. | G73: Roughly half what it cost a year ago. | H73: An order of magnitude less, and still falling without renegotiation.
C74: Delivery Elasticity | D74: Down. Each additional customer costs proportionally more to serve. | E74: Flat. Scale brings no margin benefit. | F74: Up slightly, from negotiated volume discounts. | G74: Up materially, because cost to serve falls faster than price. | H74: Up structurally, because the marginal customer costs almost nothing to serve.
B75: Employee experience | C75: Budget Displaced | D75: Internal AI is added spend. No cost has left the P&L. | E75: Time savings are reported but the back-office payroll is unchanged. | F75: Freed capacity is redeployed to new work rather than removed. | G75: Back-office headcount has fallen and the saving is visible in the budget. | H75: The cost of running internal functions is set by compute, not payroll.
C76: Outcome Attribution | D76: Internal AI benefit is asserted, never measured. | E76: Licence counts and logins are measured; effect on work is not. | F76: Time saved is estimated from surveys rather than observed. | G76: A pre-deployment baseline exists and the productivity delta is defensible. | H76: Output per employee is tracked continuously and reported to the board.
C77: Autonomy | D77: People do the work. Systems record it. | E77: Assistants draft; a person completes every task. | F77: Systems complete defined tasks; a person checks before anything commits. | G77: Agents run whole back-office processes end to end. | H77: Processes run unattended and escalate only by exception.
C78: Data Compounding | D78: Institutional knowledge lives in people and cannot be searched. | E78: Documents exist but are stale and unstructured. | F78: Knowledge is searchable but does not improve from use. | G78: The knowledge base improves automatically as people work in it. | H78: Institutional knowledge is a system, not a function of tenure.
C79: Velocity to Scale | D79: Revenue per employee is flat or falling. | E79: Improving a few percent a year. | F79: Improving by double digits a year. | G79: Doubling on a multi-year view. | H79: Step change — the company does materially more with the same headcount.
C80: Delivery Elasticity | D80: Back-office headcount rises with company volume. | E80: Some leverage, but headcount still tracks volume. | F80: Headcount grows at roughly half the rate of volume. | G80: Company volume can double with little or no added back-office headcount. | H80: Back-office capacity is elastic. Volume does not drive headcount.
B81: Capital efficiency | C81: Budget Displaced | D81: Spend grows with headcount and nobody questions the ratio. | E81: Cost per unit of output is reported but does not change decisions. | F81: Cost to serve is understood by segment and discussed at QBR. | G81: Growth is funded by displaced cost rather than new headcount. | H81: Capacity scales on compute. Headcount is a deliberate choice, not a consequence of growth.
C82: Outcome Attribution | D82: CAC payback and cost to serve are not calculated. | E82: Blended figures exist; no segment view and no owner. | F82: Both are calculated by segment and reviewed quarterly. | G82: Segment economics drive where the company invests, against an agreed baseline. | H82: Unit economics are proven per segment and survive a buyer’s own diligence.
C83: Autonomy | D83: Spend approvals are ad hoc and reconstructed after the quarter. | E83: Thresholds exist; enforcement depends on who approves. | F83: Policy is applied through the finance system with a clean audit trail. | G83: Standard spend clears automatically; humans review exceptions only. | H83: Governance is encoded end to end. Out-of-policy spend cannot be committed.
C84: Data Compounding | D84: No history of what spend produced what return. | E84: Spend and outcome data exist in separate systems. | F84: Return on spend is analysed periodically by category. | G84: Historic return automatically re-weights the allocation model. | H84: The allocation record compounds into an advantage in where the company places capital.
C85: Velocity to Scale | D85: Budget reallocation happens once a year, if at all. | E85: Reallocation is possible mid-year but politically expensive. | F85: Quarterly reallocation against performance is routine. | G85: Capital moves to the best-returning segment within a quarter, without escalation. | H85: Allocation adjusts continuously against measured return.
C86: Delivery Elasticity | D86: Every point of growth costs a proportional point of opex. | E86: Some operating leverage, but Rule of 40 is flat. | F86: Rule of 40 improving, driven mostly by growth. | G86: Rule of 40 above 40 and improving on the margin side. | H86: Volume can grow substantially with no material step in cost. Rule of 40 above 50.
B87: Data foundation | C87: Budget Displaced | D87: The data estate supports reporting only. It enables no commercial claim. | E87: Data supports a productivity story but not a pricing change. | F87: Data supports a business case that cites customer headcount. | G87: The data asset lets you price against a named labour line. | H87: The data asset is why the buyer's alternative is hiring rather than buying.
C88: Outcome Attribution | D88: Outcomes cannot be measured from the data you hold. | E88: Activity can be measured; outcomes require a project. | F88: Outcomes can be measured with manual assembly each time. | G88: Outcomes can be measured from data you already hold, without a project. | H88: Outcome measurement is instrumented and continuous.
C89: Autonomy | D89: Data must be extracted and moved by a person before anything can use it. | E89: Pipelines exist but break and need manual intervention. | F89: Pipelines run reliably; models read but do not write. | G89: Models read and act on the data without a person moving it first. | H89: The data layer serves autonomous agents directly, with governance enforced in place.
C90: Velocity to Scale | D90: Not growing. Rights and quality block most of it. | E90: Growing only in line with customer count. | F90: Growing faster than customer count as rights are cleared. | G90: Doubling on a multi-year view. | H90: Depth increased an order of magnitude, and the rights are settled.
C91: Delivery Elasticity | D91: Every new data source is an engineering project. | E91: Onboarding a source is templated but still bespoke. | F91: Standard sources onboard through configuration. | G91: A new source can be onboarded without an engineering project. | H91: Sources onboard automatically with governance applied in place.
B92: Governance & funding | C92: Budget Displaced | D92: AI is funded from the technology budget as a technology project. | E92: AI is funded centrally with a productivity narrative attached. | F92: Funding requires a headcount case but the headcount is rarely released. | G92: There is a funding route for work that changes how revenue is earned. | H92: Investment decisions are made against the labour cost the work displaces.
C93: Outcome Attribution | D93: Investment is approved on delivery milestones alone. | E93: Benefits are stated at approval and never revisited. | F93: Benefits are reviewed but not measured against a baseline. | G93: Investment is approved against outcome targets and reviewed against them. | H93: Funding continues only where measured outcomes are delivered.
C94: Autonomy | D94: Every decision needs a committee and a meeting. | E94: Decisions are logged in a tool, but each one waits on a person. | F94: Routine decisions follow a defined path; anything new goes to committee. | G94: Policy is enforced automatically; people handle exceptions only. | H94: Governance runs continuously in the background and surfaces only what breaches policy.
C95: Data Compounding | D95: No legal position exists on learning from customer data. | E95: The default position is no, with no route to change it. | F95: Case-by-case approval, negotiated per customer. | G95: A legal position permits learning across accounts, agreed and documented. | H95: Data rights are standard in the contract and treated as an asset.
C96: Velocity to Scale | D96: More than a year. | E96: Six to twelve months. | F96: Three to six months. | G96: Under three months. | H96: Weeks, with funding and approval routed automatically.
C97: Delivery Elasticity | D97: It stays where it is. Nothing changes. | E97: Redeployment is discussed but rarely happens. | F97: Redeployment is decided once a year, at planning. | G97: Freed capacity is redeployed or removed within the year. | H97: Capacity moves continuously to wherever it is worth most.
B99: Lever weights and ceilings
B100: Value lever | C100: Budget Displaced | D100: Outcome Attribution | E100: Autonomy | F100: Data Compounding | G100: Velocity to Scale | H100: Delivery Elasticity | I100: Check | J100: Ceiling
B101: Product and services differentiation | C101: 0.3 | D101: 0.15 | E101: 0.15 | F101: 0.2 | G101: 0.15 | H101: 0.05 | I101: =SUM(C101:H101) -> 1 | J101: =C101*$E$15+D101*$E$16+E101*$E$17+F101*$E$18+G101*$E$19+H101*$E$20 -> 9.5
B102: Pricing and packaging | C102: 0.35 | D102: 0.35 | E102: 0.05 | F102: 0.1 | G102: 0.1 | H102: 0.05 | I102: =SUM(C102:H102) -> 1 | J102: =C102*$E$15+D102*$E$16+E102*$E$17+F102*$E$18+G102*$E$19+H102*$E$20 -> 9.45
B103: Sales effectiveness | C103: 0.15 | D103: 0.1 | E103: 0.25 | F103: 0.1 | G103: 0.3 | H103: 0.1 | I103: =SUM(C103:H103) -> 1 | J103: =C103*$E$15+D103*$E$16+E103*$E$17+F103*$E$18+G103*$E$19+H103*$E$20 -> 9.525
B104: Customer retention and expansion | C104: 0.1 | D104: 0.25 | E104: 0.25 | F104: 0.2 | G104: 0.05 | H104: 0.15 | I104: =SUM(C104:H104) -> 1 | J104: =C104*$E$15+D104*$E$16+E104*$E$17+F104*$E$18+G104*$E$19+H104*$E$20 -> 9.2
B105: Ecosystem strategy | C105: 0.1 | D105: 0.1 | E105: 0.15 | F105: 0.35 | G105: 0.2 | H105: 0.1 | I105: =SUM(C105:H105) -> 1 | J105: =C105*$E$15+D105*$E$16+E105*$E$17+F105*$E$18+G105*$E$19+H105*$E$20 -> 9.325
B106: Product engineering | C106: 0.2 | D106: 0.05 | E106: 0.3 | F106: 0.1 | G106: 0.15 | H106: 0.2 | I106: =SUM(C106:H106) -> 1 | J106: =C106*$E$15+D106*$E$16+E106*$E$17+F106*$E$18+G106*$E$19+H106*$E$20 -> 9.4
...

Sheet 2_Capability_Assessment
AB1: level map
B2: Capability assessment | AB2: L1 | AC2: 0.2
B3: 36 capabilities across ten value levers. Each carries one rating; its frontier dimension is fixed. Read across the five descriptions and pick what the company can evidence today. Levels 4 and 5 need evidence a third party could verify — without it, score 3. Lever scores roll up on the machine block below and feed 4b. | AB3: L2 | AC3: 0.4
AB4: L3 | AC4: 0.6
B5: Lever | C5: Capability | D5: Dim | E5: L1 Absent | F5: L2 Emerging | G5: L3 Defined | H5: L4 Advanced | I5: L5 Frontier | J5: LEVEL | K5: Ceiling | L5: Metric impacted | M5: wt | N5: lvl# | O5: pts | AB5: L4 | AC5: 0.8
B6: Product and services differentiation | C6: Proprietary data advantage | D6: DC | E6: No usage or outcome data is retained beyond logs. | F6: Data is retained but sits in systems nobody queries. | G6: A usable dataset exists; it informs roadmap decisions periodically. | H6: The dataset measurably improves the product and a competitor could not assemble it quickly. | I6: The dataset is the product's core defence. Replicating it requires the same install base and the same years. | J6: L3 | K6: =IFERROR(INDEX('1_Industry_Rubric'!$E$15:$E$20,MATCH($D6,{"BD","OA","AUT","DC","VEL","DE"},0)),"") -> 9 | L6: Gross margin, NRR | M6: =IFERROR(INDEX('1_Industry_Rubric'!$C$101:$H$110,MATCH($B6,'1_Industry_Rubric'!$B$101:$B$110,0),MATCH($D6,{"BD","OA","AUT","DC","VEL","DE"},0)),"") -> 0.2 | N6: =IFERROR(VLOOKUP($J6,$AB$2:$AC$6,2,FALSE()),"") -> 0.6 | O6: =IFERROR($K6*$M6*$N6,"") -> 1.08 | AB6: L5 | AC6: 1
B7: Product and services differentiation | C7: AI-native product architecture | D7: AUT | E7: AI is absent, or bolted on as a separate feature. | F7: AI features exist alongside the core product but share no architecture with it. | G7: Core functions are exposed as callable actions; some agents operate on them. | H7: The product is API-first end to end; agents can execute any core function without touching the UI. | I7: The product was rebuilt around agent execution. The UI is one client among several. | J7: L4 | K7: =IFERROR(INDEX('1_Industry_Rubric'!$E$15:$E$20,MATCH($D7,{"BD","OA","AUT","DC","VEL","DE"},0)),"") -> 9.5 | L7: Gross margin, ARR growth | M7: =IFERROR(INDEX('1_Industry_Rubric'!$C$101:$H$110,MATCH($B7,'1_Industry_Rubric'!$B$101:$B$110,0),MATCH($D7,{"BD","OA","AUT","DC","VEL","DE"},0)),"") -> 0.15 | N7: =IFERROR(VLOOKUP($J7,$AB$2:$AC$6,2,FALSE()),"") -> 0.8 | O7: =IFERROR($K7*$M7*$N7,"") -> 1.14
B8: Product and services differentiation | C8: Workflow depth and embeddedness | D8: BD | E8: Used occasionally, easily replaced, no dependency. | F8: Used regularly but sits alongside the customer's real workflow. | G8: Embedded in a workflow the customer runs weekly. | H8: Embedded in a workflow that would break if the product were removed. | I8: The customer's process was redesigned around the product. Removal means rehiring. | J8: L3 | K8: =IFERROR(INDEX('1_Industry_Rubric'!$E$15:$E$20,MATCH($D8,{"BD","OA","AUT","DC","VEL","DE"},0)),"") -> 10 | L8: GRR, NRR | M8: =IFERROR(INDEX('1_Industry_Rubric'!$C$101:$H$110,MATCH($B8,'1_Industry_Rubric'!$B$101:$B$110,0),MATCH($D8,{"BD","OA","AUT","DC","VEL","DE"},0)),"") -> 0.3 | N8: =IFERROR(VLOOKUP($J8,$AB$2:$AC$6,2,FALSE()),"") -> 0.6 | O8: =IFERROR($K8*$M8*$N8,"") -> 1.8
B9: Product and services differentiation | C9: Release velocity | D9: VEL | E9: Releases are irregular and each one is a project. | F9: Scheduled releases, but new functionality reaches customers slowly. | G9: Regular release cadence; most customers are within a version or two. | H9: New functionality reaches the whole install base within a release cycle. | I9: Continuous delivery to the whole install base at no incremental cost per customer. | J9: L3 | K9: =IFERROR(INDEX('1_Industry_Rubric'!$E$15:$E$20,MATCH($D9,{"BD","OA","AUT","DC","VEL","DE"},0)),"") -> 10 | L9: ARR growth, NRR | M9: =IFERROR(INDEX('1_Industry_Rubric'!$C$101:$H$110,MATCH($B9,'1_Industry_Rubric'!$B$101:$B$110,0),MATCH($D9,{"BD","OA","AUT","DC","VEL","DE"},0)),"") -> 0.15 | N9: =IFERROR(VLOOKUP($J9,$AB$2:$AC$6,2,FALSE()),"") -> 0.6 | O9: =IFERROR($K9*$M9*$N9,"") -> 0.9
B10: Product and services differentiation | C10: Model portability | D10: DE | E10: Built against one provider's API. Swapping means a rewrite. | F10: One provider, but calls are wrapped behind an internal interface. | G10: An abstraction layer exists; a second provider has been tested but not run in production. | H10: Two or more providers run in production and traffic can be shifted without a release. | I10: Requests route by cost and task across providers automatically. No single provider has pricing leverage over you. | J10: L2 | K10: =IFERROR(INDEX('1_Industry_Rubric'!$E$15:$E$20,MATCH($D10,{"BD","OA","AUT","DC","VEL","DE"},0)),"") -> 8.5 | L10: Gross margin, COGS per transaction | M10: =IFERROR(INDEX('1_Industry_Rubric'!$C$101:$H$110,MATCH($B10,'1_Industry_Rubric'!$B$101:$B$110,0),MATCH($D10,{"BD","OA","AUT","DC","VEL","DE"},0)),"") -> 0.05 | N10: =IFERROR(VLOOKUP($J10,$AB$2:$AC$6,2,FALSE()),"") -> 0.4 | O10: =IFERROR($K10*$M10*$N10,"") -> 0.17
B11: Pricing and packaging | C11: Value metric and packaging design | D11: BD | E11: Priced per seat, with tiers defined by feature count. | F11: Per seat with usage add-ons bolted on top. | G11: A hybrid exists: platform fee plus a usage or volume component. | H11: Priced on a value metric the customer already measures in their own P&L. | I11: Priced per outcome delivered. Seats are irrelevant to the contract. | J11: L3 | K11: =IFERROR(INDEX('1_Industry_Rubric'!$E$15:$E$20,MATCH($D11,{"BD","OA","AUT","DC","VEL","DE"},0)),"") -> 10 | L11: ASP, NRR | M11: =IFERROR(INDEX('1_Industry_Rubric'!$C$101:$H$110,MATCH($B11,'1_Industry_Rubric'!$B$101:$B$110,0),MATCH($D11,{"BD","OA","AUT","DC","VEL","DE"},0)),"") -> 0.35 | N11: =IFERROR(VLOOKUP($J11,$AB$2:$AC$6,2,FALSE()),"") -> 0.6 | O11: =IFERROR($K11*$M11*$N11,"") -> 2.1
B12: Pricing and packaging | C12: Outcome measurement and price realisation | D12: OA | E12: No outcome measurement. Discounting is unmanaged. | F12: Outcomes are claimed in marketing; realised price is tracked after the fact. | G12: Outcomes are reported to customers; discount approval has a policy. | H12: Baseline agreed before deployment and the delta measured against it; realised price holds within a narrow band of list. | I12: Outcome measurement is contractual and audited, and price realisation is designed into the metric rather than defended. | J12: L3 | K12: =IFERROR(INDEX('1_Industry_Rubric'!$E$15:$E$20,MATCH($D12,{"BD","OA","AUT","DC","VEL","DE"},0)),"") -> 9 | L12: Realised price, NRR | M12: =IFERROR(INDEX('1_Industry_Rubric'!$C$101:$H$110,MATCH($B12,'1_Industry_Rubric'!$B$101:$B$110,0),MATCH($D12,{"BD","OA","AUT","DC","VEL","DE"},0)),"") -> 0.35 | N12: =IFERROR(VLOOKUP($J12,$AB$2:$AC$6,2,FALSE()),"") -> 0.6 | O12: =IFERROR($K12*$M12*$N12,"") -> 1.89
B13: Sales effectiveness | C13: Buyer-value discovery | D13: BD | E13: Discovery covers requirements and features only. | F13: Discovery asks about pain but not about cost of the work. | G13: Reps ask what the current process costs, though the answer rarely reaches the proposal. | H13: Every enterprise deal is scoped against a quantified labour line the buyer confirms. | I13: The buyer's own finance team supplies the baseline. The deal is priced against their number, not yours. | J13: L4 | K13: =IFERROR(INDEX('1_Industry_Rubric'!$E$15:$E$20,MATCH($D13,{"BD","OA","AUT","DC","VEL","DE"},0)),"") -> 10 | L13: Win rate, ASP | M13: =IFERROR(INDEX('1_Industry_Rubric'!$C$101:$H$110,MATCH($B13,'1_Industry_Rubric'!$B$101:$B$110,0),MATCH($D13,{"BD","OA","AUT","DC","VEL","DE"},0)),"") -> 0.15 | N13: =IFERROR(VLOOKUP($J13,$AB$2:$AC$6,2,FALSE()),"") -> 0.8 | O13: =IFERROR($K13*$M13*$N13,"") -> 1.2
B14: Sales effectiveness | C14: Pipeline intelligence | D14: DC | E14: Pipeline is whatever reps type into the CRM. | F14: Stage definitions exist; hygiene is enforced manually. | G14: Scoring exists and is roughly trusted; forecasts are still adjusted by judgement. | H14: Signals from product and engagement data drive scoring, and the model is measurably calibrated. | I14: Pipeline quality improves continuously from closed-loop outcome data no competitor holds. | J14: L3 | K14: =IFERROR(INDEX('1_Industry_Rubric'!$E$15:$E$20,MATCH($D14,{"BD","OA","AUT","DC","VEL","DE"},0)),"") -> 9 | L14: Forecast accuracy, win rate | M14: =IFERROR(INDEX('1_Industry_Rubric'!$C$101:$H$110,MATCH($B14,'1_Industry_Rubric'!$B$101:$B$110,0),MATCH($D14,{"BD","OA","AUT","DC","VEL","DE"},0)),"") -> 0.1 | N14: =IFERROR(VLOOKUP($J14,$AB$2:$AC$6,2,FALSE()),"") -> 0.6 | O14: =IFERROR($K14*$M14*$N14,"") -> 0.54
B15: Sales effectiveness | C15: Deal desk and approval design | D15: AUT | E15: Approvals are ad hoc, routed by email. | F15: A policy exists; exceptions are frequent and manual. | G15: Deal desk reviews non-standard terms within a defined SLA. | H15: Standard deals clear approval automatically; humans see exceptions only. | I15: Approval logic is encoded end to end. Terms outside policy cannot be quoted. | J15: L2 | K15: =IFERROR(INDEX('1_Industry_Rubric'!$E$15:$E$20,MATCH($D15,{"BD","OA","AUT","DC","VEL","DE"},0)),"") -> 9.5 | L15: Sales cycle time, discount leakage | M15: =IFERROR(INDEX('1_Industry_Rubric'!$C$101:$H$110,MATCH($B15,'1_Industry_Rubric'!$B$101:$B$110,0),MATCH($D15,{"BD","OA","AUT","DC","VEL","DE"},0)),"") -> 0.25 | N15: =IFERROR(VLOOKUP($J15,$AB$2:$AC$6,2,FALSE()),"") -> 0.4 | O15: =IFERROR($K15*$M15*$N15,"") -> 0.95
B16: Sales effectiveness | C16: Rep enablement and ramp | D16: DE | E16: New reps learn by shadowing. Ramp is undefined. | F16: Onboarding content exists but is static and rarely updated. | G16: Structured ramp with defined milestones; time to quota is measured. | H16: Enablement adapts to the rep, and ramp time has measurably shortened. | I16: Adding a rep costs a fraction of what it did two years ago, and quota attainment holds. | J16: L3 | K16: =IFERROR(INDEX('1_Industry_Rubric'!$E$15:$E$20,MATCH($D16,{"BD","OA","AUT","DC","VEL","DE"},0)),"") -> 8.5 | L16: Time to quota, sales efficiency | M16: =IFERROR(INDEX('1_Industry_Rubric'!$C$101:$H$110,MATCH($B16,'1_Industry_Rubric'!$B$101:$B$110,0),MATCH($D16,{"BD","OA","AUT","DC","VEL","DE"},0)),"") -> 0.1 | N16: =IFERROR(VLOOKUP($J16,$AB$2:$AC$6,2,FALSE()),"") -> 0.6 | O16: =IFERROR($K16*$M16*$N16,"") -> 0.51
B17: Sales effectiveness | C17: Sales methodology consistency | D17: VEL | E17: No common methodology. Every rep sells their own way. | F17: A methodology is named in training but not used in the CRM or in deal reviews. | G17: Methodology is applied in pre-sales; qualification fields are completed on most deals. | H17: The same methodology runs pre-sales and post-sales, and handover carries the qualification and the value case intact. | I17: One methodology governs discovery through renewal across the whole organisation, and every deal review uses its language. | J17: L3 | K17: =IFERROR(INDEX('1_Industry_Rubric'!$E$15:$E$20,MATCH($D17,{"BD","OA","AUT","DC","VEL","DE"},0)),"") -> 10 | L17: Win rate, forecast accuracy | M17: =IFERROR(INDEX('1_Industry_Rubric'!$C$101:$H$110,MATCH($B17,'1_Industry_Rubric'!$B$101:$B$110,0),MATCH($D17,{"BD","OA","AUT","DC","VEL","DE"},0)),"") -> 0.3 | N17: =IFERROR(VLOOKUP($J17,$AB$2:$AC$6,2,FALSE()),"") -> 0.6 | O17: =IFERROR($K17*$M17*$N17,"") -> 1.8
B18: Customer retention and expansion | C18: Health signal detection | D18: DC | E18: Churn is discovered at renewal. | F18: Usage is reported but not connected to renewal risk. | G18: A health score exists and is broadly believed. | H18: Risk is predicted early enough to act, and the prediction is measurably accurate. | I18: Detection improves continuously from every renewal outcome, across the whole base. | J18: L3 | K18: =IFERROR(INDEX('1_Industry_Rubric'!$E$15:$E$20,MATCH($D18,{"BD","OA","AUT","DC","VEL","DE"},0)),"") -> 9 | L18: GRR, churn rate | M18: =IFERROR(INDEX('1_Industry_Rubric'!$C$101:$H$110,MATCH($B18,'1_Industry_Rubric'!$B$101:$B$110,0),MATCH($D18,{"BD","OA","AUT","DC","VEL","DE"},0)),"") -> 0.2 | N18: =IFERROR(VLOOKUP($J18,$AB$2:$AC$6,2,FALSE()),"") -> 0.6 | O18: =IFERROR($K18*$M18*$N18,"") -> 1.08
... B41: Capital efficiency | C41: Burn discipline | D41: DE | E41: Burn is reported but not managed against a plan. | F41: A plan exists; variance is explained after the quarter. | G41: Burn is managed to plan with monthly accountability by owner. | H41: Growth is funded without a proportional increase in burn; Rule of 40 is measurably improving. | I41: The company can grow volume substantially without a material step in cost. | J41: L3 | K41: =IFERROR(INDEX('1_Industry_Rubric'!$E$15:$E$20,MATCH($D41,{"BD","OA","AUT","DC","VEL","DE"},0)),"") -> 8.5 | L41: Rule of 40, burn multiple | M41: =IFERROR(INDEX('1_Industry_Rubric'!$C$101:$H$110,MATCH($B41,'1_Industry_Rubric'!$B$101:$B$110,0),MATCH($D41,{"BD","OA","AUT","DC","VEL","DE"},0)),"") -> 0.25 | N41: =IFERROR(VLOOKUP($J41,$AB$2:$AC$6,2,FALSE()),"") -> 0.6 | O41: =IFERROR($K41*$M41*$N41,"") -> 1.275
B44: Machine block — lever rollup. Barr dimension weighting, normalised for the dimensions each lever actually touches.
B45: Lever | C45: Score | D45: Ceiling | E45: Gap | F45: % of frontier | G45: Capabilities
B46: Product and services differentiation | C46: =IFERROR(SUMIFS($O$6:$O$41,$B$6:$B$41,$B46)/SUMIFS($M$6:$M$41,$B$6:$B$41,$B46),"") -> 5.9882353 | D46: =IFERROR(VLOOKUP($B46,'1_Industry_Rubric'!$B$101:$J$110,9,FALSE()),"") -> 9.5 | E46: =IFERROR($D46-$C46,"") -> 3.5117647 | F46: =IFERROR($C46/$D46,"") -> 0.63034056 | G46: =COUNTIFS($B$6:$B$41,$B46) -> 5
B47: Pricing and packaging | C47: =IFERROR(SUMIFS($O$6:$O$41,$B$6:$B$41,$B47)/SUMIFS($M$6:$M$41,$B$6:$B$41,$B47),"") -> 5.7 | D47: =IFERROR(VLOOKUP($B47,'1_Industry_Rubric'!$B$101:$J$110,9,FALSE()),"") -> 9.45 | E47: =IFERROR($D47-$C47,"") -> 3.75 | F47: =IFERROR($C47/$D47,"") -> 0.6031746 | G47: =COUNTIFS($B$6:$B$41,$B47) -> 2
B48: Sales effectiveness | C48: =IFERROR(SUMIFS($O$6:$O$41,$B$6:$B$41,$B48)/SUMIFS($M$6:$M$41,$B$6:$B$41,$B48),"") -> 5.5555556 | D48: =IFERROR(VLOOKUP($B48,'1_Industry_Rubric'!$B$101:$J$110,9,FALSE()),"") -> 9.525 | E48: =IFERROR($D48-$C48,"") -> 3.9694444 | F48: =IFERROR($C48/$D48,"") -> 0.58326043 | G48: =COUNTIFS($B$6:$B$41,$B48) -> 5
B49: Customer retention and expansion | C49: =IFERROR(SUMIFS($O$6:$O$41,$B$6:$B$41,$B49)/SUMIFS($M$6:$M$41,$B$6:$B$41,$B49),"") -> 6.0352941 | D49: =IFERROR(VLOOKUP($B49,'1_Industry_Rubric'!$B$101:$J$110,9,FALSE()),"") -> 9.2 | E49: =IFERROR($D49-$C49,"") -> 3.1647059 | F49: =IFERROR($C49/$D49,"") -> 0.65601023 | G49: =COUNTIFS($B$6:$B$41,$B49) -> 4
B50: Ecosystem strategy | C50: =IFERROR(SUMIFS($O$6:$O$41,$B$6:$B$41,$B50)/SUMIFS($M$6:$M$41,$B$6:$B$41,$B50),"") -> 5.2769231 | D50: =IFERROR(VLOOKUP($B50,'1_Industry_Rubric'!$B$101:$J$110,9,FALSE()),"") -> 9.325 | E50: =IFERROR($D50-$C50,"") -> 4.0480769 | F50: =IFERROR($C50/$D50,"") -> 0.56588987 | G50: =COUNTIFS($B$6:$B$41,$B50) -> 3
B51: Product engineering | C51: =IFERROR(SUMIFS($O$6:$O$41,$B$6:$B$41,$B51)/SUMIFS($M$6:$M$41,$B$6:$B$41,$B51),"") -> 7.1529412 | D51: =IFERROR(VLOOKUP($B51,'1_Industry_Rubric'!$B$101:$J$110,9,FALSE()),"") -> 9.4 | E51: =IFERROR($D51-$C51,"") -> 2.2470588 | F51: =IFERROR($C51/$D51,"") -> 0.76095119 | G51: =COUNTIFS($B$6:$B$41,$B51) -> 4
B52: Revenue operations | C52: =IFERROR(SUMIFS($O$6:$O$41,$B$6:$B$41,$B52)/SUMIFS($M$6:$M$41,$B$6:$B$41,$B52),"") -> 6.0714286 | D52: =IFERROR(VLOOKUP($B52,'1_Industry_Rubric'!$B$101:$J$110,9,FALSE()),"") -> 9.3 | E52: =IFERROR($D52-$C52,"") -> 3.2285714 | F52: =IFERROR($C52/$D52,"") -> 0.65284178 | G52: =COUNTIFS($B$6:$B$41,$B52) -> 3
B53: Supplier and infrastructure cost | C53: =IFERROR(SUMIFS($O$6:$O$41,$B$6:$B$41,$B53)/SUMIFS($M$6:$M$41,$B$6:$B$41,$B53),"") -> 3.3866667 | D53: =IFERROR(VLOOKUP($B53,'1_Industry_Rubric'!$B$101:$J$110,9,FALSE()),"") -> 9.025 | E53: =IFERROR($D53-$C53,"") -> 5.6383333 | F53: =IFERROR($C53/$D53,"") -> 0.37525392 | G53: =COUNTIFS($B$6:$B$41,$B53) -> 3
B54: Employee experience | C54: =IFERROR(SUMIFS($O$6:$O$41,$B$6:$B$41,$B54)/SUMIFS($M$6:$M$41,$B$6:$B$41,$B54),"") -> 5.26875 | D54: =IFERROR(VLOOKUP($B54,'1_Industry_Rubric'!$B$101:$J$110,9,FALSE()),"") -> 9.225 | E54: =IFERROR($D54-$C54,"") -> 3.95625 | F54: =IFERROR($C54/$D54,"") -> 0.57113821 | G54: =COUNTIFS($B$6:$B$41,$B54) -> 4
B55: Capital efficiency | C55: =IFERROR(SUMIFS($O$6:$O$41,$B$6:$B$41,$B55)/SUMIFS($M$6:$M$41,$B$6:$B$41,$B55),"") -> 4.8357143 | D55: =IFERROR(VLOOKUP($B55,'1_Industry_Rubric'!$B$101:$J$110,9,FALSE()),"") -> 9.175 | E55: =IFERROR($D55-$C55,"") -> 4.3392857 | F55: =IFERROR($C55/$D55,"") -> 0.52705333 | G55: =COUNTIFS($B$6:$B$41,$B55) -> 3
B58: Frontier dimensions
B59: Dimension | C59: Mean level | D59: Ceiling | E59: Readiness
B60: BD | C60: =IFERROR(AVERAGEIFS($N$6:$N$41,$D$6:$D$41,"BD"),"") -> 0.56 | D60: ='1_Industry_Rubric'!$E$15 -> 10 | E60: =IFERROR($C60*$D60,"") -> 5.6
B61: OA | C61: =IFERROR(AVERAGEIFS($N$6:$N$41,$D$6:$D$41,"OA"),"") -> 0.64 | D61: ='1_Industry_Rubric'!$E$16 -> 9 | E61: =IFERROR($C61*$D61,"") -> 5.76
B62: AUT | C62: =IFERROR(AVERAGEIFS($N$6:$N$41,$D$6:$D$41,"AUT"),"") -> 0.6 | D62: ='1_Industry_Rubric'!$E$17 -> 9.5 | E62: =IFERROR($C62*$D62,"") -> 5.7
B63: DC | C63: =IFERROR(AVERAGEIFS($N$6:$N$41,$D$6:$D$41,"DC"),"") -> 0.63333333 | D63: ='1_Industry_Rubric'!$E$18 -> 9 | E63: =IFERROR($C63*$D63,"") -> 5.7
B64: VEL | C64: =IFERROR(AVERAGEIFS($N$6:$N$41,$D$6:$D$41,"VEL"),"") -> 0.6 | D64: ='1_Industry_Rubric'!$E$19 -> 10 | E64: =IFERROR($C64*$D64,"") -> 6
B65: DE | C65: =IFERROR(AVERAGEIFS($N$6:$N$41,$D$6:$D$41,"DE"),"") -> 0.6 | D65: ='1_Industry_Rubric'!$E$20 -> 8.5 | E65: =IFERROR($C65*$D65,"") -> 5.1
B68: Weighted capability score | C68: =IFERROR(SUM($O$6:$O$41)/SUM($M$6:$M$41),"") -> 5.5625806
B69: Frontier ceiling | C69: =IFERROR(SUMPRODUCT($K$6:$K$41*$M$6:$M$41)/SUM($M$6:$M$41),"") -> 9.2548387
B70: Distance to frontier | C70: =IFERROR($C$69-$C$68,"") -> 3.6922581
B71: Normalised capability maturity | C71: =IFERROR($C$68/$C$69*10,"") -> 6.0104566
B72: Budget Displaced, weighted mean | C72: =IFERROR($E$60,"") -> 5.6
B73: Outcome Attribution, weighted mean | C73: =IFERROR($E$61,"") -> 5.76
B74: Frontier maturity (lower of BD and OA) | C74: =IFERROR(MIN($C$72,$C$73),"") -> 5.6
B75: Capabilities scored | C75: =COUNTA($J$6:$J$41)&" of 36" -> 36 of 36
B77: Read by 4b_Value_Pools_by_Capability and 8_Enterprise_Value.
B78: Enablers
B79: Enabler | C79: Score | D79: Threshold | E79: Gate
B80: Data foundation | C80: 6.6666667 | D80: 7 | E80: =MIN(1,$C80/$D80) -> 0.95238095
B81: Governance and funding | C81: 7.2 | D81: 7 | E81: =MIN(1,$C81/$D81) -> 1
B82: Combined enabler gate | C82: =MIN($E$80,$E$81) -> 0.95238095
B83: Enter the two enabler scores out of 10. Below the 7.0 threshold the gate bites and caps conversion on every lever.
B86: Maturity matrix
B87: Lever against frontier dimension, mean level of the capabilities tagged to it. Blank means the lever has no capability on that dimension.
B88: LEVER | C88: BD | D88: OA | E88: AUT | F88: DC | G88: VEL | H88: DE | I88: LEVEL
B89: Product and services differentiation | C89: =IFERROR(IF(COUNTIFS($B$6:$B$41,$B89,$D$6:$D$41,"BD",$N$6:$N$41,">0")=0,"",AVERAGEIFS($N$6:$N$41,$B$6:$B$41,$B89,$D$6:$D$41,"BD")*5),"") -> 3 | D89: =IFERROR(IF(COUNTIFS($B$6:$B$41,$B89,$D$6:$D$41,"OA",$N$6:$N$41,">0")=0,"",AVERAGEIFS($N$6:$N$41,$B$6:$B$41,$B89,$D$6:$D$41,"OA")*5),"") | E89: =IFERROR(IF(COUNTIFS($B$6:$B$41,$B89,$D$6:$D$41,"AUT",$N$6:$N$41,">0")=0,"",AVERAGEIFS($N$6:$N$41,$B$6:$B$41,$B89,$D$6:$D$41,"AUT")*5),"") -> 4 | F89: =IFERROR(IF(COUNTIFS($B$6:$B$41,$B89,$D$6:$D$41,"DC",$N$6:$N$41,">0")=0,"",AVERAGEIFS($N$6:$N$41,$B$6:$B$41,$B89,$D$6:$D$41,"DC")*5),"") -> 3 | G89: =IFERROR(IF(COUNTIFS($B$6:$B$41,$B89,$D$6:$D$41,"VEL",$N$6:$N$41,">0")=0,"",AVERAGEIFS($N$6:$N$41,$B$6:$B$41,$B89,$D$6:$D$41,"VEL")*5),"") -> 3 | H89: =IFERROR(IF(COUNTIFS($B$6:$B$41,$B89,$D$6:$D$41,"DE",$N$6:$N$41,">0")=0,"",AVERAGEIFS($N$6:$N$41,$B$6:$B$41,$B89,$D$6:$D$41,"DE")*5),"") -> 2 | I89: =IFERROR(AVERAGEIFS($N$6:$N$41,$B$6:$B$41,$B89)*5,"") -> 3
B90: Pricing and packaging | C90: =IFERROR(IF(COUNTIFS($B$6:$B$41,$B90,$D$6:$D$41,"BD",$N$6:$N$41,">0")=0,"",AVERAGEIFS($N$6:$N$41,$B$6:$B$41,$B90,$D$6:$D$41,"BD")*5),"") -> 3 | D90: =IFERROR(IF(COUNTIFS($B$6:$B$41,$B90,$D$6:$D$41,"OA",$N$6:$N$41,">0")=0,"",AVERAGEIFS($N$6:$N$41,$B$6:$B$41,$B90,$D$6:$D$41,"OA")*5),"") -> 3 | E90: =IFERROR(IF(COUNTIFS($B$6:$B$41,$B90,$D$6:$D$41,"AUT",$N$6:$N$41,">0")=0,"",AVERAGEIFS($N$6:$N$41,$B$6:$B$41,$B90,$D$6:$D$41,"AUT")*5),"") | F90: =IFERROR(IF(COUNTIFS($B$6:$B$41,$B90,$D$6:$D$41,"DC",$N$6:$N$41,">0")=0,"",AVERAGEIFS($N$6:$N$41,$B$6:$B$41,$B90,$D$6:$D$41,"DC")*5),"") | G90: =IFERROR(IF(COUNTIFS($B$6:$B$41,$B90,$D$6:$D$41,"VEL",$N$6:$N$41,">0")=0,"",AVERAGEIFS($N$6:$N$41,$B$6:$B$41,$B90,$D$6:$D$41,"VEL")*5),"") | H90: =IFERROR(IF(COUNTIFS($B$6:$B$41,$B90,$D$6:$D$41,"DE",$N$6:$N$41,">0")=0,"",AVERAGEIFS($N$6:$N$41,$B$6:$B$41,$B90,$D$6:$D$41,"DE")*5),"") | I90: =IFERROR(AVERAGEIFS($N$6:$N$41,$B$6:$B$41,$B90)*5,"") -> 3
B91: Sales effectiveness | C91: =IFERROR(IF(COUNTIFS($B$6:$B$41,$B91,$D$6:$D$41,"BD",$N$6:$N$41,">0")=0,"",AVERAGEIFS($N$6:$N$41,$B$6:$B$41,$B91,$D$6:$D$41,"BD")*5),"") -> 4 | D91: =IFERROR(IF(COUNTIFS($B$6:$B$41,$B91,$D$6:$D$41,"OA",$N$6:$N$41,">0")=0,"",AVERAGEIFS($N$6:$N$41,$B$6:$B$41,$B91,$D$6:$D$41,"OA")*5),"") | E91: =IFERROR(IF(COUNTIFS($B$6:$B$41,$B91,$D$6:$D$41,"AUT",$N$6:$N$41,">0")=0,"",AVERAGEIFS($N$6:$N$41,$B$6:$B$41,$B91,$D$6:$D$41,"AUT")*5),"") -> 2 | F91: =IFERROR(IF(COUNTIFS($B$6:$B$41,$B91,$D$6:$D$41,"DC",$N$6:$N$41,">0")=0,"",AVERAGEIFS($N$6:$N$41,$B$6:$B$41,$B91,$D$6:$D$41,"DC")*5),"") -> 3 | G91: =IFERROR(IF(COUNTIFS($B$6:$B$41,$B91,$D$6:$D$41,"VEL",$N$6:$N$41,">0")=0,"",AVERAGEIFS($N$6:$N$41,$B$6:$B$41,$B91,$D$6:$D$41,"VEL")*5),"") -> 3 | H91: =IFERROR(IF(COUNTIFS($B$6:$B$41,$B91,$D$6:$D$41,"DE",$N$6:$N$41,">0")=0,"",AVERAGEIFS($N$6:$N$41,$B$6:$B$41,$B91,$D$6:$D$41,"DE")*5),"") -> 3 | I91: =IFERROR(AVERAGEIFS($N$6:$N$41,$B$6:$B$41,$B91)*5,"") -> 3
B92: Customer retention and expansion | C92: =IFERROR(IF(COUNTIFS($B$6:$B$41,$B92,$D$6:$D$41,"BD",$N$6:$N$41,">0")=0,"",AVERAGEIFS($N$6:$N$41,$B$6:$B$41,$B92,$D$6:$D$41,"BD")*5),"") | D92: =IFERROR(IF(COUNTIFS($B$6:$B$41,$B92,$D$6:$D$41,"OA",$N$6:$N$41,">0")=0,"",AVERAGEIFS($N$6:$N$41,$B$6:$B$41,$B92,$D$6:$D$41,"OA")*5),"") -> 3 | E92: =IFERROR(IF(COUNTIFS($B$6:$B$41,$B92,$D$6:$D$41,"AUT",$N$6:$N$41,">0")=0,"",AVERAGEIFS($N$6:$N$41,$B$6:$B$41,$B92,$D$6:$D$41,"AUT")*5),"") -> 3 | F92: =IFERROR(IF(COUNTIFS($B$6:$B$41,$B92,$D$6:$D$41,"DC",$N$6:$N$41,">0")=0,"",AVERAGEIFS($N$6:$N$41,$B$6:$B$41,$B92,$D$6:$D$41,"DC")*5),"") -> 3 | G92: =IFERROR(IF(COUNTIFS($B$6:$B$41,$B92,$D$6:$D$41,"VEL",$N$6:$N$41,">0")=0,"",AVERAGEIFS($N$6:$N$41,$B$6:$B$41,$B92,$D$6:$D$41,"VEL")*5),"") | H92: =IFERROR(IF(COUNTIFS($B$6:$B$41,$B92,$D$6:$D$41,"DE",$N$6:$N$41,">0")=0,"",AVERAGEIFS($N$6:$N$41,$B$6:$B$41,$B92,$D$6:$D$41,"DE")*5),"") -> 5 | I92: =IFERROR(AVERAGEIFS($N$6:$N$41,$B$6:$B$41,$B92)*5,"") -> 3.5
B93: Ecosystem strategy | C93: =IFERROR(IF(COUNTIFS($B$6:$B$41,$B93,$D$6:$D$41,"BD",$N$6:$N$41,">0")=0,"",AVERAGEIFS($N$6:$N$41,$B$6:$B$41,$B93,$D$6:$D$41,"BD")*5),"") | D93: =IFERROR(IF(COUNTIFS($B$6:$B$41,$B93,$D$6:$D$41,"OA",$N$6:$N$41,">0")=0,"",AVERAGEIFS($N$6:$N$41,$B$6:$B$41,$B93,$D$6:$D$41,"OA")*5),"") | E93: =IFERROR(IF(COUNTIFS($B$6:$B$41,$B93,$D$6:$D$41,"AUT",$N$6:$N$41,">0")=0,"",AVERAGEIFS($N$6:$N$41,$B$6:$B$41,$B93,$D$6:$D$41,"AUT")*5),"") | F93: =IFERROR(IF(COUNTIFS($B$6:$B$41,$B93,$D$6:$D$41,"DC",$N$6:$N$41,">0")=0,"",AVERAGEIFS($N$6:$N$41,$B$6:$B$41,$B93,$D$6:$D$41,"DC")*5),"") -> 3 | G93: =IFERROR(IF(COUNTIFS($B$6:$B$41,$B93,$D$6:$D$41,"VEL",$N$6:$N$41,">0")=0,"",AVERAGEIFS($N$6:$N$41,$B$6:$B$41,$B93,$D$6:$D$41,"VEL")*5),"") -> 3 | H93: =IFERROR(IF(COUNTIFS($B$6:$B$41,$B93,$D$6:$D$41,"DE",$N$6:$N$41,">0")=0,"",AVERAGEIFS($N$6:$N$41,$B$6:$B$41,$B93,$D$6:$D$41,"DE")*5),"") -> 2 | I93: =IFERROR(AVERAGEIFS($N$6:$N$41,$B$6:$B$41,$B93)*5,"") -> 2.6666667
B94: Product engineering | C94: =IFERROR(IF(COUNTIFS($B$6:$B$41,$B94,$D$6:$D$41,"BD",$N$6:$N$41,">0")=0,"",AVERAGEIFS($N$6:$N$41,$B$6:$B$41,$B94,$D$6:$D$41,"BD")*5),"") -> 3 | D94: =IFERROR(IF(COUNTIFS($B$6:$B$41,$B94,$D$6:$D$41,"OA",$N$6:$N$41,">0")=0,"",AVERAGEIFS($N$6:$N$41,$B$6:$B$41,$B94,$D$6:$D$41,"OA")*5),"") | E94: =IFERROR(IF(COUNTIFS($B$6:$B$41,$B94,$D$6:$D$41,"AUT",$N$6:$N$41,">0")=0,"",AVERAGEIFS($N$6:$N$41,$B$6:$B$41,$B94,$D$6:$D$41,"AUT")*5),"") -> 4 | F94: =IFERROR(IF(COUNTIFS($B$6:$B$41,$B94,$D$6:$D$41,"DC",$N$6:$N$41,">0")=0,"",AVERAGEIFS($N$6:$N$41,$B$6:$B$41,$B94,$D$6:$D$41,"DC")*5),"") | G94: =IFERROR(IF(COUNTIFS($B$6:$B$41,$B94,$D$6:$D$41,"VEL",$N$6:$N$41,">0")=0,"",AVERAGEIFS($N$6:$N$41,$B$6:$B$41,$B94,$D$6:$D$41,"VEL")*5),"") -> 3 | H94: =IFERROR(IF(COUNTIFS($B$6:$B$41,$B94,$D$6:$D$41,"DE",$N$6:$N$41,">0")=0,"",AVERAGEIFS($N$6:$N$41,$B$6:$B$41,$B94,$D$6:$D$41,"DE")*5),"") -> 5 | I94: =IFERROR(AVERAGEIFS($N$6:$N$41,$B$6:$B$41,$B94)*5,"") -> 3.75
B95: Revenue operations | C95: =IFERROR(IF(COUNTIFS($B$6:$B$41,$B95,$D$6:$D$41,"BD",$N$6:$N$41,">0")=0,"",AVERAGEIFS($N$6:$N$41,$B$6:$B$41,$B95,$D$6:$D$41,"BD")*5),"") | D95: =IFERROR(IF(COUNTIFS($B$6:$B$41,$B95,$D$6:$D$41,"OA",$N$6:$N$41,">0")=0,"",AVERAGEIFS($N$6:$N$41,$B$6:$B$41,$B95,$D$6:$D$41,"OA")*5),"") -> 3 | E95: =IFERROR(IF(COUNTIFS($B$6:$B$41,$B95,$D$6:$D$41,"AUT",$N$6:$N$41,">0")=0,"",AVERAGEIFS($N$6:$N$41,$B$6:$B$41,$B95,$D$6:$D$41,"AUT")*5),"") -> 4 | F95: =IFERROR(IF(COUNTIFS($B$6:$B$41,$B95,$D$6:$D$41,"DC",$N$6:$N$41,">0")=0,"",AVERAGEIFS($N$6:$N$41,$B$6:$B$41,$B95,$D$6:$D$41,"DC")*5),"") | G95: =IFERROR(IF(COUNTIFS($B$6:$B$41,$B95,$D$6:$D$41,"VEL",$N$6:$N$41,">0")=0,"",AVERAGEIFS($N$6:$N$41,$B$6:$B$41,$B95,$D$6:$D$41,"VEL")*5),"") | H95: =IFERROR(IF(COUNTIFS($B$6:$B$41,$B95,$D$6:$D$41,"DE",$N$6:$N$41,">0")=0,"",AVERAGEIFS($N$6:$N$41,$B$6:$B$41,$B95,$D$6:$D$41,"DE")*5),"") -> 2 | I95: =IFERROR(AVERAGEIFS($N$6:$N$41,$B$6:$B$41,$B95)*5,"") -> 3
B96: Supplier and infrastructure cost | C96: =IFERROR(IF(COUNTIFS($B$6:$B$41,$B96,$D$6:$D$41,"BD",$N$6:$N$41,">0")=0,"",AVERAGEIFS($N$6:$N$41,$B$6:$B$41,$B96,$D$6:$D$41,"BD")*5),"") -> 1 | D96: =IFERROR(IF(COUNTIFS($B$6:$B$41,$B96,$D$6:$D$41,"OA",$N$6:$N$41,">0")=0,"",AVERAGEIFS($N$6:$N$41,$B$6:$B$41,$B96,$D$6:$D$41,"OA")*5),"") | E96: =IFERROR(IF(COUNTIFS($B$6:$B$41,$B96,$D$6:$D$41,"AUT",$N$6:$N$41,">0")=0,"",AVERAGEIFS($N$6:$N$41,$B$6:$B$41,$B96,$D$6:$D$41,"AUT")*5),"") | F96: =IFERROR(IF(COUNTIFS($B$6:$B$41,$B96,$D$6:$D$41,"DC",$N$6:$N$41,">0")=0,"",AVERAGEIFS($N$6:$N$41,$B$6:$B$41,$B96,$D$6:$D$41,"DC")*5),"") -> 3 | G96: =IFERROR(IF(COUNTIFS($B$6:$B$41,$B96,$D$6:$D$41,"VEL",$N$6:$N$41,">0")=0,"",AVERAGEIFS($N$6:$N$41,$B$6:$B$41,$B96,$D$6:$D$41,"VEL")*5),"") | H96: =IFERROR(IF(COUNTIFS($B$6:$B$41,$B96,$D$6:$D$41,"DE",$N$6:$N$41,">0")=0,"",AVERAGEIFS($N$6:$N$41,$B$6:$B$41,$B96,$D$6:$D$41,"DE")*5),"") -> 2 | I96: =IFERROR(AVERAGEIFS($N$6:$N$41,$B$6:$B$41,$B96)*5,"") -> 2
B97: Employee experience | C97: =IFERROR(IF(COUNTIFS($B$6:$B$41,$B97,$D$6:$D$41,"BD",$N$6:$N$41,">0")=0,"",AVERAGEIFS($N$6:$N$41,$B$6:$B$41,$B97,$D$6:$D$41,"BD")*5),"") | D97: =IFERROR(IF(COUNTIFS($B$6:$B$41,$B97,$D$6:$D$41,"OA",$N$6:$N$41,">0")=0,"",AVERAGEIFS($N$6:$N$41,$B$6:$B$41,$B97,$D$6:$D$41,"OA")*5),"") -> 4 | E97: =IFERROR(IF(COUNTIFS($B$6:$B$41,$B97,$D$6:$D$41,"AUT",$N$6:$N$41,">0")=0,"",AVERAGEIFS($N$6:$N$41,$B$6:$B$41,$B97,$D$6:$D$41,"AUT")*5),"") -> 2 | F97: =IFERROR(IF(COUNTIFS($B$6:$B$41,$B97,$D$6:$D$41,"DC",$N$6:$N$41,">0")=0,"",AVERAGEIFS($N$6:$N$41,$B$6:$B$41,$B97,$D$6:$D$41,"DC")*5),"") -> 4 | G97: =IFERROR(IF(COUNTIFS($B$6:$B$41,$B97,$D$6:$D$41,"VEL",$N$6:$N$41,">0")=0,"",AVERAGEIFS($N$6:$N$41,$B$6:$B$41,$B97,$D$6:$D$41,"VEL")*5),"") | H97: =IFERROR(IF(COUNTIFS($B$6:$B$41,$B97,$D$6:$D$41,"DE",$N$6:$N$41,">0")=0,"",AVERAGEIFS($N$6:$N$41,$B$6:$B$41,$B97,$D$6:$D$41,"DE")*5),"") -> 3 | I97: =IFERROR(AVERAGEIFS($N$6:$N$41,$B$6:$B$41,$B97)*5,"") -> 3.25
B98: Capital efficiency | C98: =IFERROR(IF(COUNTIFS($B$6:$B$41,$B98,$D$6:$D$41,"BD",$N$6:$N$41,">0")=0,"",AVERAGEIFS($N$6:$N$41,$B$6:$B$41,$B98,$D$6:$D$41,"BD")*5),"") | D98: =IFERROR(IF(COUNTIFS($B$6:$B$41,$B98,$D$6:$D$41,"OA",$N$6:$N$41,">0")=0,"",AVERAGEIFS($N$6:$N$41,$B$6:$B$41,$B98,$D$6:$D$41,"OA")*5),"") -> 3 | E98: =IFERROR(IF(COUNTIFS($B$6:$B$41,$B98,$D$6:$D$41,"AUT",$N$6:$N$41,">0")=0,"",AVERAGEIFS($N$6:$N$41,$B$6:$B$41,$B98,$D$6:$D$41,"AUT")*5),"") -> 2 | F98: =IFERROR(IF(COUNTIFS($B$6:$B$41,$B98,$D$6:$D$41,"DC",$N$6:$N$41,">0")=0,"",AVERAGEIFS($N$6:$N$41,$B$6:$B$41,$B98,$D$6:$D$41,"DC")*5),"") | G98: =IFERROR(IF(COUNTIFS($B$6:$B$41,$B98,$D$6:$D$41,"VEL",$N$6:$N$41,">0")=0,"",AVERAGEIFS($N$6:$N$41,$B$6:$B$41,$B98,$D$6:$D$41,"VEL")*5),"") | H98: =IFERROR(IF(COUNTIFS($B$6:$B$41,$B98,$D$6:$D$41,"DE",$N$6:$N$41,">0")=0,"",AVERAGEIFS($N$6:$N$41,$B$6:$B$41,$B98,$D$6:$D$41,"DE")*5),"") -> 3 | I98: =IFERROR(AVERAGEIFS($N$6:$N$41,$B$6:$B$41,$B98)*5,"") -> 2.6666667
B99: DIMENSION | C99: =IFERROR(AVERAGEIFS($N$6:$N$41,$D$6:$D$41,"BD")*5,"") -> 2.8 | D99: =IFERROR(AVERAGEIFS($N$6:$N$41,$D$6:$D$41,"OA")*5,"") -> 3.2 | E99: =IFERROR(AVERAGEIFS($N$6:$N$41,$D$6:$D$41,"AUT")*5,"") -> 3 | F99: =IFERROR(AVERAGEIFS($N$6:$N$41,$D$6:$D$41,"DC")*5,"") -> 3.1666667 | G99: =IFERROR(AVERAGEIFS($N$6:$N$41,$D$6:$D$41,"VEL")*5,"") -> 3 | H99: =IFERROR(AVERAGEIFS($N$6:$N$41,$D$6:$D$41,"DE")*5,"") -> 3 | I99: =IFERROR(AVERAGE($N$6:$N$41)*5,"") -> 3.0277778

Sheet 3_Distance_to_Frontier
B2: Distance to frontier
B3: Live from 2_Capability_Assessment. Distance is measured against each capability's own ceiling, derived from the six dimensions weighted for that capability. The value column is what closing the gap is worth before feasibility and timing.
B5: Value lever | C5: Score | D5: Ceiling | E5: Gap | F5: % of frontier | G5: Closed | H5: Reachable | I5: Gross pool | J5: Adjusted pool | K5: At stake
B6: ='2_Capability_Assessment'!$B$46 -> Product and services differentiation | C6: ='2_Capability_Assessment'!$C$46 -> 5.9882353 | D6: ='2_Capability_Assessment'!$D$46 -> 9.5 | E6: =IFERROR($D6-$C6,"") -> 3.5117647 | F6: =IFERROR($C6/$D6,"") -> 0.63034056 | G6: =IFERROR($C6/$D6,"") -> 0.63034056 | H6: =IFERROR('4b_Value_Pools_by_Capability'!$L$15,"") -> 0.72535895 | I6: =IFERROR('4b_Value_Pools_by_Capability'!$E$15,"") -> 187500000 | J6: =IFERROR('4b_Value_Pools_by_Capability'!$O$15,"") -> 21893199 | K6: =IFERROR($I6-$J6,"") -> 1.656068e+08
B7: ='2_Capability_Assessment'!$B$47 -> Pricing and packaging | C7: ='2_Capability_Assessment'!$C$47 -> 5.7 | D7: ='2_Capability_Assessment'!$D$47 -> 9.45 | E7: =IFERROR($D7-$C7,"") -> 3.75 | F7: =IFERROR($C7/$D7,"") -> 0.6031746 | G7: =IFERROR($C7/$D7,"") -> 0.6031746 | H7: =IFERROR('4b_Value_Pools_by_Capability'!$L$16,"") -> 0.72535895 | I7: =IFERROR('4b_Value_Pools_by_Capability'!$E$16,"") -> 1.0125e+08 | J7: =IFERROR('4b_Value_Pools_by_Capability'!$O$16,"") -> 7070511 | K7: =IFERROR($I7-$J7,"") -> 94179489
B8: ='2_Capability_Assessment'!$B$48 -> Sales effectiveness | C8: ='2_Capability_Assessment'!$C$48 -> 5.5555556 | D8: ='2_Capability_Assessment'!$D$48 -> 9.525 | E8: =IFERROR($D8-$C8,"") -> 3.9694444 | F8: =IFERROR($C8/$D8,"") -> 0.58326043 | G8: =IFERROR($C8/$D8,"") -> 0.58326043 | H8: =IFERROR('4b_Value_Pools_by_Capability'!$L$17,"") -> 0.72535895 | I8: =IFERROR('4b_Value_Pools_by_Capability'!$E$17,"") -> 41400000 | J8: =IFERROR('4b_Value_Pools_by_Capability'!$O$17,"") -> 3913844.9 | K8: =IFERROR($I8-$J8,"") -> 37486155
B9: ='2_Capability_Assessment'!$B$49 -> Customer retention and expansion | C9: ='2_Capability_Assessment'!$C$49 -> 6.0352941 | D9: ='2_Capability_Assessment'!$D$49 -> 9.2 | E9: =IFERROR($D9-$C9,"") -> 3.1647059 | F9: =IFERROR($C9/$D9,"") -> 0.65601023 | G9: =IFERROR($C9/$D9,"") -> 0.65601023 | H9: =IFERROR('4b_Value_Pools_by_Capability'!$L$18,"") -> 0.72535895 | I9: =IFERROR('4b_Value_Pools_by_Capability'!$E$18,"") -> 28500000 | J9: =IFERROR('4b_Value_Pools_by_Capability'!$O$18,"") -> 2597463.4 | K9: =IFERROR($I9-$J9,"") -> 25902537
B10: ='2_Capability_Assessment'!$B$50 -> Ecosystem strategy | C10: ='2_Capability_Assessment'!$C$50 -> 5.2769231 | D10: ='2_Capability_Assessment'!$D$50 -> 9.325 | E10: =IFERROR($D10-$C10,"") -> 4.0480769 | F10: =IFERROR($C10/$D10,"") -> 0.56588987 | G10: =IFERROR($C10/$D10,"") -> 0.56588987 | H10: =IFERROR('4b_Value_Pools_by_Capability'!$L$19,"") -> 0.72535895 | I10: =IFERROR('4b_Value_Pools_by_Capability'!$E$19,"") -> 9000000 | J10: =IFERROR('4b_Value_Pools_by_Capability'!$O$19,"") -> 530676.26 | K10: =IFERROR($I10-$J10,"") -> 8469323.7
B11: ='2_Capability_Assessment'!$B$51 -> Product engineering | C11: ='2_Capability_Assessment'!$C$51 -> 7.1529412 | D11: ='2_Capability_Assessment'!$D$51 -> 9.4 | E11: =IFERROR($D11-$C11,"") -> 2.2470588 | F11: =IFERROR($C11/$D11,"") -> 0.76095119 | G11: =IFERROR($C11/$D11,"") -> 0.76095119 | H11: =IFERROR('4b_Value_Pools_by_Capability'!$L$20,"") -> 0.72535895 | I11: =IFERROR('4b_Value_Pools_by_Capability'!$E$20,"") -> 68640000 | J11: =IFERROR('4b_Value_Pools_by_Capability'!$O$20,"") -> 10280062 | K11: =IFERROR($I11-$J11,"") -> 58359938
B12: ='2_Capability_Assessment'!$B$52 -> Revenue operations | C12: ='2_Capability_Assessment'!$C$52 -> 6.0714286 | D12: ='2_Capability_Assessment'!$D$52 -> 9.3 | E12: =IFERROR($D12-$C12,"") -> 3.2285714 | F12: =IFERROR($C12/$D12,"") -> 0.65284178 | G12: =IFERROR($C12/$D12,"") -> 0.65284178 | H12: =IFERROR('4b_Value_Pools_by_Capability'!$L$21,"") -> 0.72535895 | I12: =IFERROR('4b_Value_Pools_by_Capability'!$E$21,"") -> 10800000 | J12: =IFERROR('4b_Value_Pools_by_Capability'!$O$21,"") -> 1061176.9 | K12: =IFERROR($I12-$J12,"") -> 9738823.1
B13: ='2_Capability_Assessment'!$B$53 -> Supplier and infrastructure cost | C13: ='2_Capability_Assessment'!$C$53 -> 3.3866667 | D13: ='2_Capability_Assessment'!$D$53 -> 9.025 | E13: =IFERROR($D13-$C13,"") -> 5.6383333 | F13: =IFERROR($C13/$D13,"") -> 0.37525392 | G13: =IFERROR($C13/$D13,"") -> 0.37525392 | H13: =IFERROR('4b_Value_Pools_by_Capability'!$L$22,"") -> 0.72535895 | I13: =IFERROR('4b_Value_Pools_by_Capability'!$E$22,"") -> 16200000 | J13: =IFERROR('4b_Value_Pools_by_Capability'!$O$22,"") -> 281522.41 | K13: =IFERROR($I13-$J13,"") -> 15918478
B14: ='2_Capability_Assessment'!$B$54 -> Employee experience | C14: ='2_Capability_Assessment'!$C$54 -> 5.26875 | D14: ='2_Capability_Assessment'!$D$54 -> 9.225 | E14: =IFERROR($D14-$C14,"") -> 3.95625 | F14: =IFERROR($C14/$D14,"") -> 0.57113821 | G14: =IFERROR($C14/$D14,"") -> 0.57113821 | H14: =IFERROR('4b_Value_Pools_by_Capability'!$L$23,"") -> 0.72535895 | I14: =IFERROR('4b_Value_Pools_by_Capability'!$E$23,"") -> 21600000 | J14: =IFERROR('4b_Value_Pools_by_Capability'!$O$23,"") -> 1999565.9 | K14: =IFERROR($I14-$J14,"") -> 19600434
B15: ='2_Capability_Assessment'!$B$55 -> Capital efficiency | C15: ='2_Capability_Assessment'!$C$55 -> 4.8357143 | D15: ='2_Capability_Assessment'!$D$55 -> 9.175 | E15: =IFERROR($D15-$C15,"") -> 4.3392857 | F15: =IFERROR($C15/$D15,"") -> 0.52705333 | G15: =IFERROR($C15/$D15,"") -> 0.52705333 | H15: =IFERROR('4b_Value_Pools_by_Capability'!$L$24,"") -> 0.72535895 | I15: =IFERROR('4b_Value_Pools_by_Capability'!$E$24,"") -> 0 | J15: =IFERROR('4b_Value_Pools_by_Capability'!$O$24,"") -> 0 | K15: =IFERROR($I15-$J15,"") -> 0
B17: Binding dimension | C17: =IFERROR(INDEX('2_Capability_Assessment'!$B$60:$B$65,MATCH(MIN('2_Capability_Assessment'!$E$60:$E$65),'2_Capability_Assessment'!$E$60:$E$65,0)),"") -> DE
B19: Data foundation | C19: ='2_Capability_Assessment'!$C$80 -> 6.6666667 | D19: 10 | E19: =IFERROR($C19/$D19,0) -> 0.66666667 | F19: =IF($C19=0,"not scored",IF($C19<7,"CAPPING","clear")) -> CAPPING
B20: Governance & funding | C20: ='2_Capability_Assessment'!$C$81 -> 7.2 | D20: 10 | E20: =IFERROR($C20/$D20,0) -> 0.72 | F20: =IF($C20=0,"not scored",IF($C20<7,"CAPPING","clear")) -> clear
B21: Gate applied to capture | C21: ='2_Capability_Assessment'!$C$82 -> 0.95238095 | E21: Multiplies every capability's maturity on 4b. An enabler at or above 70% of the frontier does not cap; below that it suppresses capture proportionally.
B24: Closed is the share of the ceiling already reached. Reachable is Barr's gap scaling function eta(g), pulled from 4b — the further from the frontier, the more of the pool is still unclaimed, so reachability rises with distance and is floored at 15%. Read the two together: a capability that is far behind has more headroom but converts it less well, which is why readiness and reachability pull against each other. At stake is the gross pool less what is currently adjustable, which is what closing the capability gap is worth before feasibility and timing are applied.

Sheet 4b_Value_Pools_by_Capability
B1: Value pools by value lever
B2: The prize is set by the company’s own cost and revenue lines, not by its scores. For each lever: revenue × base % (the line it touches) × uplift % (a published benchmark for what AI does to that line) = GROSS. Only then do the scores apply, through capture ceiling, reachability and capability maturity = ADJUSTED.
B3: INPUTS
B4: Industry vertical | D4: Vertical SaaS | E4: Sets the frontier cohort. Read by tabs 5 and 6.
B5: Industry critical scale S* | D5: 3300000000 | E5: Barr’s critical-scale threshold. Drives the firm scale factor.
B6: Total revenue | D6: 1500000000 | E6: ARR plus professional services.
B7: Capture adjustment | D7: 1 | E7: Leave at 1.00 unless deliberately scaling every pool.
B8: Reachability curve steepness | D8: 3.5 | E8: Lambda in Barr Eq. 25. Judgemental constant, not calibrated.
B9: Vendor AI only? (Yes / No) | D9: No | E9: Barr caps Phi at 0.65 where a firm deploys only off-the-shelf vendor AI.
B10: Firm scale factor (Phi) | D10: =IF($D$5=0,1,MIN(1/(1+EXP(-2*LOG10($D$6/$D$5))),1)) -> 0.33518073 | E10: Barr Eq. 21. Logistic on revenue against S*.
B11: Enabler gate | D11: =MIN(1,MIN('2_Capability_Assessment'!$C$80,'2_Capability_Assessment'!$C$81)/7) -> 0.95238095 | E11: Data foundation and governance. Below 7.0 it caps conversion on every lever.
B12: Share of accounts on an AI tier | D12: 0.5 | E12: Sizes Product and services differentiation. Pricing and packaging takes the remainder plus a residual.
B13: Residual pricing headroom on tiered accounts | D13: 0.35 | E13: How much of the 10% discount gap is still open where the AI premium already applies. At 0% the two levers partition the revenue base cleanly.
I14: SCORE | J14: CEILING | L14: REACH | M14: MATURITY | N14: CAPTURE CEILING | O14: ADJUSTED POOL | P14: REV SHARE | Q14: REVENUE EFFECT | R14: COST EFFECT | W14: CASH EBITDA | AE14: METRIC IMPACTED | AF14: UPLIFT SOURCE | AG14: STATUS | AH14: SAAS BAND
B15: Product and services differentiation | C15: =$D$12 -> 0.5 | D15: 0.25 | E15: =$D$6*C15*D15 -> 187500000 | F15: ="GROSS: $"&TEXT($D$6/1000000,"#,##0")&"M x "&TEXT(C15,"0.0%")&" x "&TEXT(D15,"0.0%")&" = $"&TEXT(E15/1000000,"#,##0.0")&"M"&CHAR(10)&"ADJUSTED: x "&TEXT(N15,"0.00")&" capture x "&TEXT(L15,"0.000")&" reach x "&TEXT(M15,"0.000")&" maturity = $"&TEXT(O15/1000000,"#,##0.0")&"M" -> GROSS: $1,500M x 50.0% x 25.0% = $187.5M ADJUSTED: x 0.80 capture x 0.725 reach x 0.600 maturity = $21.9M | G15: Accounts on an AI tier, from the shared input above. The AI premium lifts revenue per account by 25%. Company figure. | I15: ='2_Capability_Assessment'!$C$46 -> 5.9882353 | J15: ='2_Capability_Assessment'!$D$46 -> 9.5 | L15: =MAX(0.15,1-EXP(-$D$8*'2_Capability_Assessment'!$C$70/10)) -> 0.72535895 | M15: =IFERROR(I15/J15,0)*$D$11 -> 0.60032434 | N15: 0.8 | O15: =E15*N15*L15*M15*$D$7*$D$10 -> 21893199 | P15: 1 | Q15: =O15*P15 -> 21893199 | R15: =O15*(1-P15) -> 0 | V15: 1 | W15: =R15*V15 -> 0 | X15: =R15*(1-V15) -> 0 | Z15: ='7_Value_Timing'!$C$25 -> 0.95977741 | AA15: =IFERROR(Z15,"") -> 0.95977741 | AB15: =O15*AA15*'5_Implementation_Feasibility'!$E$13 -> 19168732 | AE15: ARR growth, NRR | AF15: SaaS-specific. AI-native SaaS enables pricing models that were not viable before — per-AI-query billing, premium AI tiers and MCP access fees for partners wanting structured data access (Qrvey, 2026). No published median for the premium itself, so 25% remains a Contoso figure. | AG15: COMPANY | AH15: —
B16: Pricing and packaging | C16: =(1-$D$12)+$D$12*$D$13 -> 0.675 | D16: 0.1 | E16: =$D$6*C16*D16 -> 1.0125e+08 | F16: ="GROSS: $"&TEXT($D$6/1000000,"#,##0")&"M x "&TEXT(C16,"0.0%")&" x "&TEXT(D16,"0.0%")&" = $"&TEXT(E16/1000000,"#,##0.0")&"M"&CHAR(10)&"ADJUSTED: x "&TEXT(N16,"0.00")&" capture x "&TEXT(L16,"0.000")&" reach x "&TEXT(M16,"0.000")&" maturity = $"&TEXT(O16/1000000,"#,##0.0")&"M" -> GROSS: $1,500M x 67.5% x 10.0% = $101.3M ADJUSTED: x 0.50 capture x 0.725 reach x 0.574 maturity = $7.1M | G16: Accounts not on an AI tier carry the full 10% discount gap. Accounts already on a tier have had part of that gap closed by the premium, so only the residual share below applies to them. This is what stops Pricing and Product double-counting the same dollar. | I16: ='2_Capability_Assessment'!$C$47 -> 5.7 | J16: ='2_Capability_Assessment'!$D$47 -> 9.45 | L16: =MAX(0.15,1-EXP(-$D$8*'2_Capability_Assessment'!$C$70/10)) -> 0.72535895 | M16: =IFERROR(I16/J16,0)*$D$11 -> 0.574452 | N16: 0.5 | O16: =E16*N16*L16*M16*$D$7*$D$10 -> 7070511 | P16: 0.55 | Q16: =O16*P16 -> 3888781 | R16: =O16*(1-P16) -> 3181729.9 | V16: 1 | W16: =R16*V16 -> 3181729.9 | X16: =R16*(1-V16) -> 0 | Z16: ='7_Value_Timing'!$C$25 -> 0.95977741 | AA16: =IFERROR(Z16,"") -> 0.95977741 | AB16: =O16*AA16*'5_Implementation_Feasibility'!$E$13 -> 6190631.4 | AE16: ASP, realised price, NRR | AF16: SaaS-specific. Per-seat pricing is breaking as customers reduce seats rather than add them; Workday attributed an 8.5% workforce reduction to AI efficiency. Hybrid models are the bridge. The 10% realised discount is a Contoso figure. | AG16: COMPANY | AH16: —
B17: Sales effectiveness | C17: 0.184 | D17: 0.15 | E17: =$D$6*C17*D17 -> 41400000 | F17: ="GROSS: $"&TEXT($D$6/1000000,"#,##0")&"M x "&TEXT(C17,"0.0%")&" x "&TEXT(D17,"0.0%")&" = $"&TEXT(E17/1000000,"#,##0.0")&"M"&CHAR(10)&"ADJUSTED: x "&TEXT(N17,"0.00")&" capture x "&TEXT(L17,"0.000")&" reach x "&TEXT(M17,"0.000")&" maturity = $"&TEXT(O17/1000000,"#,##0.0")&"M" -> GROSS: $1,500M x 18.4% x 15.0% = $41.4M ADJUSTED: x 0.70 capture x 0.725 reach x 0.555 maturity = $3.9M | G17: Sales 15% plus marketing 8% of ARR, the 2026 SaaS Capital medians, converted to 18.4% of total revenue. Fifteen percent of that comes back. Split 40% to revenue won and 60% to cost saved — AI selling capacity can be taken as fewer sellers or as more pipeline. | I17: ='2_Capability_Assessment'!$C$48 -> 5.5555556 | J17: ='2_Capability_Assessment'!$D$48 -> 9.525 | L17: =MAX(0.15,1-EXP(-$D$8*'2_Capability_Assessment'!$C$70/10)) -> 0.72535895 | M17: =IFERROR(I17/J17,0)*$D$11 -> 0.55548612 | N17: 0.7 | O17: =E17*N17*L17*M17*$D$7*$D$10 -> 3913844.9 | P17: 0.4 | Q17: =O17*P17 -> 1565538 | R17: =O17*(1-P17) -> 2348306.9 | V17: 1 | W17: =R17*V17 -> 2348306.9 | X17: =R17*(1-V17) -> 0 | Z17: ='7_Value_Timing'!$C$25 -> 0.95977741 | AA17: =IFERROR(Z17,"") -> 0.95977741 | AB17: =O17*AA17*'5_Implementation_Feasibility'!$E$13 -> 3426792.1 | AE17: Win rate, sales efficiency | AF17: SaaS-specific. State of B2B SaaS Sales 2026, 500+ companies: firms that rebuilt the SDR motion around AI see 3–5x better results than those running 2020-era manual prospecting. Cross-industry anchor: Brynjolfsson, Li and Raymond, QJE 2025, 14% average productivity gain across 5,179 agents. | AG17: PUBLISHED | AH17: 15–25%
B18: Customer retention and expansion | C18: 1 | D18: 0.019 | E18: =$D$6*C18*D18 -> 28500000 | F18: ="GROSS: $"&TEXT($D$6/1000000,"#,##0")&"M x "&TEXT(C18,"0.0%")&" x "&TEXT(D18,"0.0%")&" = $"&TEXT(E18/1000000,"#,##0.0")&"M"&CHAR(10)&"ADJUSTED: x "&TEXT(N18,"0.00")&" capture x "&TEXT(L18,"0.000")&" reach x "&TEXT(M18,"0.000")&" maturity = $"&TEXT(O18/1000000,"#,##0.0")&"M" -> GROSS: $1,500M x 100.0% x 1.9% = $28.5M ADJUSTED: x 0.60 capture x 0.725 reach x 0.625 maturity = $2.6M | G18: AI churn prediction moves SaaS churn from 6.8% to 4.9% after twelve months — 1.9 points of revenue retained. | I18: ='2_Capability_Assessment'!$C$49 -> 6.0352941 | J18: ='2_Capability_Assessment'!$D$49 -> 9.2 | L18: =MAX(0.15,1-EXP(-$D$8*'2_Capability_Assessment'!$C$70/10)) -> 0.72535895 | M18: =IFERROR(I18/J18,0)*$D$11 -> 0.62477165 | N18: 0.6 | O18: =E18*N18*L18*M18*$D$7*$D$10 -> 2597463.4 | P18: 0.6 | Q18: =O18*P18 -> 1558478 | R18: =O18*(1-P18) -> 1038985.4 | V18: 1 | W18: =R18*V18 -> 1038985.4 | X18: =R18*(1-V18) -> 0 | Z18: ='7_Value_Timing'!$C$25 -> 0.95977741 | AA18: =IFERROR(Z18,"") -> 0.95977741 | AB18: =O18*AA18*'5_Implementation_Feasibility'!$E$13 -> 2274225.8 | AE18: GRR, NRR | AF18: SaaS-specific. AI resolves 50–60% of tier-1 support queries and reduces customer service costs by roughly 30% (industry reporting, 2026). Churn falls from 6.8% to 4.9% after twelve months of AI churn prediction — 1.9 points of revenue retained. | AG18: PUBLISHED | AH18: —
B19: Ecosystem strategy | C19: 0.3 | D19: 0.02 | E19: =$D$6*C19*D19 -> 9000000 | F19: ="GROSS: $"&TEXT($D$6/1000000,"#,##0")&"M x "&TEXT(C19,"0.0%")&" x "&TEXT(D19,"0.0%")&" = $"&TEXT(E19/1000000,"#,##0.0")&"M"&CHAR(10)&"ADJUSTED: x "&TEXT(N19,"0.00")&" capture x "&TEXT(L19,"0.000")&" reach x "&TEXT(M19,"0.000")&" maturity = $"&TEXT(O19/1000000,"#,##0.0")&"M" -> GROSS: $1,500M x 30.0% x 2.0% = $9.0M ADJUSTED: x 0.45 capture x 0.725 reach x 0.539 maturity = $0.5M | G19: 30% of revenue comes through partners. AI lifts that by 2%. Company figure. | I19: ='2_Capability_Assessment'!$C$50 -> 5.2769231 | J19: ='2_Capability_Assessment'!$D$50 -> 9.325 | L19: =MAX(0.15,1-EXP(-$D$8*'2_Capability_Assessment'!$C$70/10)) -> 0.72535895 | M19: =IFERROR(I19/J19,0)*$D$11 -> 0.53894274 | N19: 0.45 | O19: =E19*N19*L19*M19*$D$7*$D$10 -> 530676.26 | P19: 1 | Q19: =O19*P19 -> 530676.26 | R19: =O19*(1-P19) -> 0 | V19: 1 | W19: =R19*V19 -> 0 | X19: =R19*(1-V19) -> 0 | Z19: ='7_Value_Timing'!$C$25 -> 0.95977741 | AA19: =IFERROR(Z19,"") -> 0.95977741 | AB19: =O19*AA19*'5_Implementation_Feasibility'!$E$13 -> 464637.02 | AE19: Partner-sourced ARR, CAC | AF19: SaaS-specific but thin. MCP access fees for partners wanting structured data access are an emerging revenue line (Qrvey, 2026). No published uplift figure. 2% is judgemental. | AG19: UNSOURCED | AH19: —
B20: Product engineering | C20: 0.176 | D20: 0.26 | E20: =$D$6*C20*D20 -> 68640000 | F20: ="GROSS: $"&TEXT($D$6/1000000,"#,##0")&"M x "&TEXT(C20,"0.0%")&" x "&TEXT(D20,"0.0%")&" = $"&TEXT(E20/1000000,"#,##0.0")&"M"&CHAR(10)&"ADJUSTED: x "&TEXT(N20,"0.00")&" capture x "&TEXT(L20,"0.000")&" reach x "&TEXT(M20,"0.000")&" maturity = $"&TEXT(O20/1000000,"#,##0.0")&"M" -> GROSS: $1,500M x 17.6% x 26.0% = $68.6M ADJUSTED: x 0.85 capture x 0.725 reach x 0.725 maturity = $10.3M | G20: R&D at the 2026 median of 22% of ARR, converted to 17.6% of total revenue. AI makes engineers 26% faster. | I20: ='2_Capability_Assessment'!$C$51 -> 7.1529412 | J20: ='2_Capability_Assessment'!$D$51 -> 9.4 | L20: =MAX(0.15,1-EXP(-$D$8*'2_Capability_Assessment'!$C$70/10)) -> 0.72535895 | M20: =IFERROR(I20/J20,0)*$D$11 -> 0.72471542 | N20: 0.85 | O20: =E20*N20*L20*M20*$D$7*$D$10 -> 10280062 | P20: 0 | Q20: =O20*P20 -> 0 | R20: =O20*(1-P20) -> 10280062 | V20: 1 | W20: =R20*V20 -> 10280062 | X20: =R20*(1-V20) -> 0 | Z20: ='7_Value_Timing'!$C$25 -> 0.95977741 | AA20: =IFERROR(Z20,"") -> 0.95977741 | AB20: =O20*AA20*'5_Implementation_Feasibility'!$E$13 -> 9000774.2 | AE20: R&D as % of revenue | AF20: SaaS-specific. GitHub reports its AI coding assistant automates roughly 30% of developers’ code writing. Cross-industry RCT: Cui et al. 2025, 4,867 developers at Microsoft, Accenture and a Fortune 100 firm, 26.08% more completed pull requests. | AG20: PUBLISHED | AH20: 26–30%
B21: Revenue operations | C21: 0.024 | D21: 0.3 | E21: =$D$6*C21*D21 -> 10800000 | F21: ="GROSS: $"&TEXT($D$6/1000000,"#,##0")&"M x "&TEXT(C21,"0.0%")&" x "&TEXT(D21,"0.0%")&" = $"&TEXT(E21/1000000,"#,##0.0")&"M"&CHAR(10)&"ADJUSTED: x "&TEXT(N21,"0.00")&" capture x "&TEXT(L21,"0.000")&" reach x "&TEXT(M21,"0.000")&" maturity = $"&TEXT(O21/1000000,"#,##0.0")&"M" -> GROSS: $1,500M x 2.4% x 30.0% = $10.8M ADJUSTED: x 0.65 capture x 0.725 reach x 0.622 maturity = $1.1M | G21: 3% of ARR, the revops share of the 15% G&A benchmark, converted to 2.4% of revenue. Quote-to-cash automation removes 30% of it. | I21: ='2_Capability_Assessment'!$C$52 -> 6.0714286 | J21: ='2_Capability_Assessment'!$D$52 -> 9.3 | L21: =MAX(0.15,1-EXP(-$D$8*'2_Capability_Assessment'!$C$70/10)) -> 0.72535895 | M21: =IFERROR(I21/J21,0)*$D$11 -> 0.62175408 | N21: 0.65 | O21: =E21*N21*L21*M21*$D$7*$D$10 -> 1061176.9 | P21: 0.2 | Q21: =O21*P21 -> 212235.37 | R21: =O21*(1-P21) -> 848941.49 | V21: 1 | W21: =R21*V21 -> 848941.49 | X21: =R21*(1-V21) -> 0 | Z21: ='7_Value_Timing'!$C$25 -> 0.95977741 | AA21: =IFERROR(Z21,"") -> 0.95977741 | AB21: =O21*AA21*'5_Implementation_Feasibility'!$E$13 -> 929120.23 | AE21: Sales cycle time, G&A as % of revenue | AF21: SaaS-specific. EvenFlow AI, an automotive scheduling SaaS, reduced operational capacity inefficiencies by up to 30% automating workflows that previously required manual analysis. Single case, not a median. | AG21: PARTIAL | AH21: ~30%
B22: Supplier and infrastructure cost | C22: 0.072 | D22: 0.15 | E22: =$D$6*C22*D22 -> 16200000 | F22: ="GROSS: $"&TEXT($D$6/1000000,"#,##0")&"M x "&TEXT(C22,"0.0%")&" x "&TEXT(D22,"0.0%")&" = $"&TEXT(E22/1000000,"#,##0.0")&"M"&CHAR(10)&"ADJUSTED: x "&TEXT(N22,"0.00")&" capture x "&TEXT(L22,"0.000")&" reach x "&TEXT(M22,"0.000")&" maturity = $"&TEXT(O22/1000000,"#,##0.0")&"M" -> GROSS: $1,500M x 7.2% x 15.0% = $16.2M ADJUSTED: x 0.20 capture x 0.725 reach x 0.357 maturity = $0.3M | G22: Hosting 5% plus DevOps 4% of ARR at the 2026 medians, converted to 7.2% of revenue. Cut 15% by buying better and routing inference by cost. | I22: ='2_Capability_Assessment'!$C$53 -> 3.3866667 | J22: ='2_Capability_Assessment'!$D$53 -> 9.025 | L22: =MAX(0.15,1-EXP(-$D$8*'2_Capability_Assessment'!$C$70/10)) -> 0.72535895 | M22: =IFERROR(I22/J22,0)*$D$11 -> 0.35738469 | N22: 0.2 | O22: =E22*N22*L22*M22*$D$7*$D$10 -> 281522.41 | P22: 0 | Q22: =O22*P22 -> 0 | R22: =O22*(1-P22) -> 281522.41 | V22: 1 | W22: =R22*V22 -> 281522.41 | X22: =R22*(1-V22) -> 0 | Z22: ='7_Value_Timing'!$C$25 -> 0.95977741 | AA22: =IFERROR(Z22,"") -> 0.95977741 | AB22: =O22*AA22*'5_Implementation_Feasibility'!$E$13 -> 246488.76 | AE22: Gross margin, COGS per transaction | AF22: SaaS-specific and pointing the other way. Scaling AI to production routinely reveals 500–1,000% cost underestimation; companies underestimate total AI cost by 30% or more (Herbatschek, 2026). Inference, storage, fine-tuning and in-production maintenance compound. Treat 15% as optimistic. | AG22: CONTESTED | AH22: negative risk
B23: Employee experience | C23: 0.096 | D23: 0.15 | E23: =$D$6*C23*D23 -> 21600000 | F23: ="GROSS: $"&TEXT($D$6/1000000,"#,##0")&"M x "&TEXT(C23,"0.0%")&" x "&TEXT(D23,"0.0%")&" = $"&TEXT(E23/1000000,"#,##0.0")&"M"&CHAR(10)&"ADJUSTED: x "&TEXT(N23,"0.00")&" capture x "&TEXT(L23,"0.000")&" reach x "&TEXT(M23,"0.000")&" maturity = $"&TEXT(O23/1000000,"#,##0.0")&"M" -> GROSS: $1,500M x 9.6% x 15.0% = $21.6M ADJUSTED: x 0.70 capture x 0.725 reach x 0.544 maturity = $2.0M | G23: The remaining 12% of the G&A benchmark, converted to 9.6% of revenue. Back office works 15% faster. | I23: ='2_Capability_Assessment'!$C$54 -> 5.26875 | J23: ='2_Capability_Assessment'!$D$54 -> 9.225 | L23: =MAX(0.15,1-EXP(-$D$8*'2_Capability_Assessment'!$C$70/10)) -> 0.72535895 | M23: =IFERROR(I23/J23,0)*$D$11 -> 0.54394115 | N23: 0.7 | O23: =E23*N23*L23*M23*$D$7*$D$10 -> 1999565.9 | P23: 0 | Q23: =O23*P23 -> 0 | R23: =O23*(1-P23) -> 1999565.9 | V23: 1 | W23: =R23*V23 -> 1999565.9 | X23: =R23*(1-V23) -> 0 | Z23: ='7_Value_Timing'!$C$25 -> 0.95977741 | AA23: =IFERROR(Z23,"") -> 0.95977741 | AB23: =O23*AA23*'5_Implementation_Feasibility'!$E$13 -> 1750732.8 | AE23: G&A as % of revenue | AF23: SaaS-specific. Companies consolidating their SaaS stack see 20–35% cost reductions and 3.2x ROI within twelve months; platform AI now replaces 25–35% of point solutions out of the box. AI point tools have the lowest utilisation of any category at 38%. | AG23: PUBLISHED | AH23: 20–35%
B24: Capital efficiency | C24: 0 | D24: 0 | E24: =$D$6*C24*D24 -> 0 | F24: ="GROSS: $"&TEXT($D$6/1000000,"#,##0")&"M x "&TEXT(C24,"0.0%")&" x "&TEXT(D24,"0.0%")&" = $"&TEXT(E24/1000000,"#,##0.0")&"M"&CHAR(10)&"ADJUSTED: x "&TEXT(N24,"0.00")&" capture x "&TEXT(L24,"0.000")&" reach x "&TEXT(M24,"0.000")&" maturity = $"&TEXT(O24/1000000,"#,##0.0")&"M" -> GROSS: $1,500M x 0.0% x 0.0% = $0.0M ADJUSTED: x 0.00 capture x 0.725 reach x 0.502 maturity = $0.0M | G24: No independent pool. CAC payback and cost to serve are realisations of the other levers — sizing them here would double-count Sales effectiveness and Employee experience. | I24: ='2_Capability_Assessment'!$C$55 -> 4.8357143 | J24: ='2_Capability_Assessment'!$D$55 -> 9.175 | L24: =MAX(0.15,1-EXP(-$D$8*'2_Capability_Assessment'!$C$70/10)) -> 0.72535895 | M24: =IFERROR(I24/J24,0)*$D$11 -> 0.50195555 | N24: 0 | O24: =E24*N24*L24*M24*$D$7*$D$10 -> 0 | P24: 0 | Q24: =O24*P24 -> 0 | R24: =O24*(1-P24) -> 0 | V24: 1 | W24: =R24*V24 -> 0 | X24: =R24*(1-V24) -> 0 | Z24: ='7_Value_Timing'!$C$25 -> 0.95977741 | AA24: =IFERROR(Z24,"") -> 0.95977741 | AB24: =O24*AA24*'5_Implementation_Feasibility'!$E$13 -> 0 | AE24: Rule of 40, CAC payback | AF24: Not sized. CAC payback and cost to serve are realisations of the other levers; a pool here would double-count. | AG24: N/A | AH24: —
B25: TOTAL | E25: =SUM(E15:E24) -> 484890000 | O25: =SUM(O15:O24) -> 49628021 | Q25: =SUM(Q15:Q24) -> 29648908 | R25: =SUM(R15:R24) -> 19979114 | W25: =SUM(W15:W24) -> 19979114 | X25: =SUM(X15:X24) -> 0
B27: SUMMARY — read by the downstream tabs
B28: Gross pool | E28: =E25 -> 484890000
B29: Adjusted pool at current capability | E29: =O25 -> 49628021
B30: Share of gross captured | E30: =IFERROR(O25/E25,0) -> 0.10234903
B31: Left on the table | E31: =E25-O25 -> 4.3526198e+08
B32: Revenue effect | E32: =Q25 -> 29648908
B33: Cost effect | E33: =R25 -> 19979114
B34: Cash EBITDA effect | E34: =W25 -> 19979114
B35: Largest adjusted pool | E35: =INDEX($B$15:$B$24,MATCH(MAX($O$15:$O$24),$O$15:$O$24,0)) -> Product and services differentiation
B36: Aggregate capture check | E36: =SUMPRODUCT($N$15:$N$24,$L$15:$L$24,$M$15:$M$24) -> 2.3545855
B37: Adjusted pool after feasibility | E37: =O25*'5_Implementation_Feasibility'!$E$13 -> 45273137
B38: Realised in window, timed | E38: =SUM(AB15:AB24) -> 43452134
B39: Lost to timing | E39: =O25*'5_Implementation_Feasibility'!$E$13-$E$38 -> 1821003
B40: Revenue effect, timed | E40: =SUMPRODUCT($Q$15:$Q$24,$AA$15:$AA$24)*'5_Implementation_Feasibility'!$E$13 -> 25959292
B41: Cash EBITDA effect, timed | E41: =SUMPRODUCT($W$15:$W$24,$AA$15:$AA$24)*'5_Implementation_Feasibility'!$E$13 -> 17492842
B44: NOTES
B45: 1. Scores come from 2_Capability_Assessment, where 36 capabilities are rated once each against the frontier dimension they primarily advance.
B46: 2. Lever score uses Barr dimension weighting, normalised for the dimensions each lever actually touches.
B47: 3. Capital efficiency is scored but carries no pool — sizing it would double-count Sales effectiveness and Employee experience.
B48: 4. Pricing and packaging carries the discount-recovery pool that previously sat under Revenue operations.
B49: 5. Customer retention uplift of 1.9% is sourced: AI churn prediction moves SaaS churn from 6.8% to 4.9% after twelve months.
B50: 6. Revenue operations base of 3.0% of revenue is a PLACEHOLDER. Confirm the actual revops cost base with management.
B51: 7. The enabler gates are applied once, in D12. They are not re-applied on tab 5.
B52: 8. Column AE names the operating metric each lever moves.
B54: BREAKDOWN BY CAPABILITY
B55: Each lever’s pool split across its capabilities in proportion to the dimension weight that capability carries. A capability sitting on a dimension the lever depends on takes more of the pool.
B56: VALUE LEVER | C56: CAPABILITY | D56: DIM | E56: WEIGHT in lever | F56: GROSS | G56: ADJUSTED | H56: LEVEL | I56: METRIC IMPACTED
B57: Product and services differentiation | C57: Proprietary data advantage | D57: DC | E57: =IFERROR('2_Capability_Assessment'!$M$6/SUMIF('2_Capability_Assessment'!$B$6:$B$41,$B$15,'2_Capability_Assessment'!$M$6:$M$41),0) -> 0.23529412 | F57: =$E$15*$E57 -> 44117647 | G57: =$O$15*$E57 -> 5151341 | H57: ='2_Capability_Assessment'!$J$6 -> L3 | I57: Gross margin, NRR
C58: AI-native product architecture | D58: AUT | E58: =IFERROR('2_Capability_Assessment'!$M$7/SUMIF('2_Capability_Assessment'!$B$6:$B$41,$B$15,'2_Capability_Assessment'!$M$6:$M$41),0) -> 0.17647059 | F58: =$E$15*$E58 -> 33088235 | G58: =$O$15*$E58 -> 3863505.7 | H58: ='2_Capability_Assessment'!$J$7 -> L4 | I58: Gross margin, ARR growth
C59: Workflow depth and embeddedness | D59: BD | E59: =IFERROR('2_Capability_Assessment'!$M$8/SUMIF('2_Capability_Assessment'!$B$6:$B$41,$B$15,'2_Capability_Assessment'!$M$6:$M$41),0) -> 0.35294118 | F59: =$E$15*$E59 -> 66176471 | G59: =$O$15*$E59 -> 7727011.5 | H59: ='2_Capability_Assessment'!$J$8 -> L3 | I59: GRR, NRR
C60: Release velocity | D60: VEL | E60: =IFERROR('2_Capability_Assessment'!$M$9/SUMIF('2_Capability_Assessment'!$B$6:$B$41,$B$15,'2_Capability_Assessment'!$M$6:$M$41),0) -> 0.17647059 | F60: =$E$15*$E60 -> 33088235 | G60: =$O$15*$E60 -> 3863505.7 | H60: ='2_Capability_Assessment'!$J$9 -> L3 | I60: ARR growth, NRR
C61: Model portability | D61: DE | E61: =IFERROR('2_Capability_Assessment'!$M$10/SUMIF('2_Capability_Assessment'!$B$6:$B$41,$B$15,'2_Capability_Assessment'!$M$6:$M$41),0) -> 0.058823529 | F61: =$E$15*$E61 -> 11029412 | G61: =$O$15*$E61 -> 1287835.2 | H61: ='2_Capability_Assessment'!$J$10 -> L2 | I61: Gross margin, COGS per transaction
B62: Pricing and packaging | C62: Value metric and packaging design | D62: BD | E62: =IFERROR('2_Capability_Assessment'!$M$11/SUMIF('2_Capability_Assessment'!$B$6:$B$41,$B$16,'2_Capability_Assessment'!$M$6:$M$41),0) -> 0.5 | F62: =$E$16*$E62 -> 50625000 | G62: =$O$16*$E62 -> 3535255.5 | H62: ='2_Capability_Assessment'!$J$11 -> L3 | I62: ASP, NRR
C63: Outcome measurement and price realisation | D63: OA | E63: =IFERROR('2_Capability_Assessment'!$M$12/SUMIF('2_Capability_Assessment'!$B$6:$B$41,$B$16,'2_Capability_Assessment'!$M$6:$M$41),0) -> 0.5 | F63: =$E$16*$E63 -> 50625000 | G63: =$O$16*$E63 -> 3535255.5 | H63: ='2_Capability_Assessment'!$J$12 -> L3 | I63: Realised price, NRR
B64: UPLIFT SOURCES — SaaS industry | C64: Buyer-value discovery | D64: BD | E64: =IFERROR('2_Capability_Assessment'!$M$13/SUMIF('2_Capability_Assessment'!$B$6:$B$41,$B$17,'2_Capability_Assessment'!$M$6:$M$41),0) -> 0.16666667 | F64: =$E$17*$E64 -> 6900000 | G64: =$O$17*$E64 -> 652307.48 | H64: ='2_Capability_Assessment'!$J$13 -> L4 | I64: Win rate, ASP
B65: State of B2B SaaS Sales 2026 | C65: Pipeline intelligence | D65: DC | E65: =IFERROR('2_Capability_Assessment'!$M$14/SUMIF('2_Capability_Assessment'!$B$6:$B$41,$B$17,'2_Capability_Assessment'!$M$6:$M$41),0) -> 0.11111111 | F65: =$E$17*$E65 -> 4600000 | G65: =$O$17*$E65 -> 434871.65 | H65: ='2_Capability_Assessment'!$J$14 -> L3 | I65: Forecast accuracy, win rate
B66: Survey of 500+ B2B SaaS companies. Firms that rebuilt the SDR motion around AI report 3–5x better results than those running manual prospecting and template outreach. Used for Sales effectiveness. | C66: Deal desk and approval design | D66: AUT | E66: =IFERROR('2_Capability_Assessment'!$M$15/SUMIF('2_Capability_Assessment'!$B$6:$B$41,$B$17,'2_Capability_Assessment'!$M$6:$M$41),0) -> 0.27777778 | F66: =$E$17*$E66 -> 11500000 | G66: =$O$17*$E66 -> 1087179.1 | H66: ='2_Capability_Assessment'!$J$15 -> L2 | I66: Sales cycle time, discount leakage
B67: SaaS platform consolidation, 2026 | C67: Rep enablement and ramp | D67: DE | E67: =IFERROR('2_Capability_Assessment'!$M$16/SUMIF('2_Capability_Assessment'!$B$6:$B$41,$B$17,'2_Capability_Assessment'!$M$6:$M$41),0) -> 0.11111111 | F67: =$E$17*$E67 -> 4600000 | G67: =$O$17*$E67 -> 434871.65 | H67: ='2_Capability_Assessment'!$J$16 -> L3 | I67: Time to quota, sales efficiency
B68: Companies consolidating their SaaS stack see 20–35% cost reductions and 3.2x ROI within twelve months. Platform AI replaces 25–35% of point solutions out of the box. AI point tools show 38% utilisation, the lowest of any category. Used for Employee experience. | C68: Sales methodology consistency | D68: VEL | E68: =IFERROR('2_Capability_Assessment'!$M$17/SUMIF('2_Capability_Assessment'!$B$6:$B$41,$B$17,'2_Capability_Assessment'!$M$6:$M$41),0) -> 0.33333333 | F68: =$E$17*$E68 -> 13800000 | G68: =$O$17*$E68 -> 1304615 | H68: ='2_Capability_Assessment'!$J$17 -> L3 | I68: Win rate, forecast accuracy
B69: SaaS support automation, 2026 | C69: Health signal detection | D69: DC | E69: =IFERROR('2_Capability_Assessment'!$M$18/SUMIF('2_Capability_Assessment'!$B$6:$B$41,$B$18,'2_Capability_Assessment'!$M$6:$M$41),0) -> 0.23529412 | F69: =$E$18*$E69 -> 6705882.4 | G69: =$O$18*$E69 -> 611167.86 | H69: ='2_Capability_Assessment'!$J$18 -> L3 | I69: GRR, churn rate
B70: AI resolves 50–60% of tier-1 support queries; chatbots reduce customer service costs by around 30%. Gartner: 85% of service leaders piloting conversational AI. Used alongside the churn figure for Customer retention. | C70: Proactive intervention capacity | D70: AUT | E70: =IFERROR('2_Capability_Assessment'!$M$19/SUMIF('2_Capability_Assessment'!$B$6:$B$41,$B$18,'2_Capability_Assessment'!$M$6:$M$41),0) -> 0.29411765 | F70: =$E$18*$E70 -> 8382352.9 | G70: =$O$18*$E70 -> 763959.83 | H70: ='2_Capability_Assessment'!$J$19 -> L3 | I70: GRR, cost to serve
B71: GitHub and Cui et al. 2025 | C71: Expansion motion design | D71: DE | E71: =IFERROR('2_Capability_Assessment'!$M$20/SUMIF('2_Capability_Assessment'!$B$6:$B$41,$B$18,'2_Capability_Assessment'!$M$6:$M$41),0) -> 0.17647059 | F71: =$E$18*$E71 -> 5029411.8 | G71: =$O$18*$E71 -> 458375.9 | H71: ='2_Capability_Assessment'!$J$20 -> L5 | I71: NRR, expansion ARR
B72: GitHub reports its coding assistant automates roughly 30% of code writing. Cui et al. RCT across 4,867 developers found 26.08% more completed pull requests. Used for Product engineering. | C72: Renewal value case | D72: OA | E72: =IFERROR('2_Capability_Assessment'!$M$21/SUMIF('2_Capability_Assessment'!$B$6:$B$41,$B$18,'2_Capability_Assessment'!$M$6:$M$41),0) -> 0.29411765 | F72: =$E$18*$E72 -> 8382352.9 | G72: =$O$18*$E72 -> 763959.83 | H72: ='2_Capability_Assessment'!$J$21 -> L3 | I72: NRR, renewal rate
B73: Herbatschek 2026 / BetterCloud 2026 | C73: Partner distribution and API surface | D73: VEL | E73: =IFERROR('2_Capability_Assessment'!$M$22/SUMIF('2_Capability_Assessment'!$B$6:$B$41,$B$19,'2_Capability_Assessment'!$M$6:$M$41),0) -> 0.30769231 | F73: =$E$19*$E73 -> 2769230.8 | G73: =$O$19*$E73 -> 163285 | H73: ='2_Capability_Assessment'!$J$22 -> L3 | I73: Partner-sourced ARR, CAC
B74: Scaling AI to production routinely reveals 500–1,000% cost underestimation; total AI cost underestimated by 30% or more. Inference, storage, fine-tuning and in-production maintenance compound faster than roadmap planning accounts for. This works against the Supplier and infrastructure uplift. | C74: Data network effects | D74: DC | E74: =IFERROR('2_Capability_Assessment'!$M$23/SUMIF('2_Capability_Assessment'!$B$6:$B$41,$B$19,'2_Capability_Assessment'!$M$6:$M$41),0) -> 0.53846154 | F74: =$E$19*$E74 -> 4846153.8 | G74: =$O$19*$E74 -> 285748.76 | H74: ='2_Capability_Assessment'!$J$23 -> L3 | I74: NRR, win rate
B75: Gartner, via BetterCloud 2026 | C75: Marketplace presence | D75: DE | E75: =IFERROR('2_Capability_Assessment'!$M$24/SUMIF('2_Capability_Assessment'!$B$6:$B$41,$B$19,'2_Capability_Assessment'!$M$6:$M$41),0) -> 0.15384615 | F75: =$E$19*$E75 -> 1384615.4 | G75: =$O$19*$E75 -> 81642.502 | H75: ='2_Capability_Assessment'!$J$24 -> L2 | I75: CAC, pipeline coverage
B76: Enterprise software spend rising 14.7% in 2026 to more than $1.4 trillion, with generative AI the primary accelerant. 40% of enterprise apps will carry task-specific AI agents by 2026. 35% of point-product SaaS tools replaced by AI agents by 2030. | C76: Engineering productivity | D76: BD | E76: =IFERROR('2_Capability_Assessment'!$M$25/SUMIF('2_Capability_Assessment'!$B$6:$B$41,$B$20,'2_Capability_Assessment'!$M$6:$M$41),0) -> 0.23529412 | F76: =$E$20*$E76 -> 16150588 | G76: =$O$20*$E76 -> 2418838 | H76: ='2_Capability_Assessment'!$J$25 -> L3 | I76: R&D as % of revenue, release throughput
B77: Unsourced | C77: Platform and reuse architecture | D77: VEL | E77: =IFERROR('2_Capability_Assessment'!$M$26/SUMIF('2_Capability_Assessment'!$B$6:$B$41,$B$20,'2_Capability_Assessment'!$M$6:$M$41),0) -> 0.17647059 | F77: =$E$20*$E77 -> 12112941 | G77: =$O$20*$E77 -> 1814128.5 | H77: ='2_Capability_Assessment'!$J$26 -> L3 | I77: R&D as % of revenue, gross margin
B78: Ecosystem strategy at 2% has no published SaaS uplift figure. Revenue operations at 30% rests on a single case study, not a median. Together $19.8M of gross pool. | C78: Quality and test automation | D78: AUT | E78: =IFERROR('2_Capability_Assessment'!$M$27/SUMIF('2_Capability_Assessment'!$B$6:$B$41,$B$20,'2_Capability_Assessment'!$M$6:$M$41),0) -> 0.35294118 | F78: =$E$20*$E78 -> 24225882 | G78: =$O$20*$E78 -> 3628257 | H78: ='2_Capability_Assessment'!$J$27 -> L4 | I78: R&D as % of revenue, escaped defects
C79: Technical debt management | D79: DE | E79: =IFERROR('2_Capability_Assessment'!$M$28/SUMIF('2_Capability_Assessment'!$B$6:$B$41,$B$20,'2_Capability_Assessment'!$M$6:$M$41),0) -> 0.23529412 | F79: =$E$20*$E79 -> 16150588 | G79: =$O$20*$E79 -> 2418838 | H79: ='2_Capability_Assessment'!$J$28 -> L5 | I79: Release throughput, maintenance cost
B80: Revenue operations | C80: Quote, contract and billing automation | D80: AUT | E80: =IFERROR('2_Capability_Assessment'!$M$29/SUMIF('2_Capability_Assessment'!$B$6:$B$41,$B$21,'2_Capability_Assessment'!$M$6:$M$41),0) -> 0.5 | F80: =$E$21*$E80 -> 5400000 | G80: =$O$21*$E80 -> 530588.43 | H80: ='2_Capability_Assessment'!$J$29 -> L4 | I80: Sales cycle time, G&A as % of revenue
C81: Revenue recognition integrity | D81: OA | E81: =IFERROR('2_Capability_Assessment'!$M$30/SUMIF('2_Capability_Assessment'!$B$6:$B$41,$B$21,'2_Capability_Assessment'!$M$6:$M$41),0) -> 0.28571429 | F81: =$E$21*$E81 -> 3085714.3 | G81: =$O$21*$E81 -> 303193.39 | H81: ='2_Capability_Assessment'!$J$30 -> L3 | I81: Audit cost, close cycle time
C82: Collections and DSO management | D82: DE | E82: =IFERROR('2_Capability_Assessment'!$M$31/SUMIF('2_Capability_Assessment'!$B$6:$B$41,$B$21,'2_Capability_Assessment'!$M$6:$M$41),0) -> 0.21428571 | F82: =$E$21*$E82 -> 2314285.7 | G82: =$O$21*$E82 -> 227395.04 | H82: ='2_Capability_Assessment'!$J$31 -> L2 | I82: DSO, working capital
B83: Supplier and infrastructure cost | C83: Cloud, compute and inference cost | D83: DE | E83: =IFERROR('2_Capability_Assessment'!$M$32/SUMIF('2_Capability_Assessment'!$B$6:$B$41,$B$22,'2_Capability_Assessment'!$M$6:$M$41),0) -> 0.66666667 | F83: =$E$22*$E83 -> 10800000 | G83: =$O$22*$E83 -> 187681.61 | H83: ='2_Capability_Assessment'!$J$32 -> L2 | I83: Gross margin, COGS per transaction
C84: Vendor portfolio rationalisation | D84: BD | E84: =IFERROR('2_Capability_Assessment'!$M$33/SUMIF('2_Capability_Assessment'!$B$6:$B$41,$B$22,'2_Capability_Assessment'!$M$6:$M$41),0) -> 0.2 | F84: =$E$22*$E84 -> 3240000 | G84: =$O$22*$E84 -> 56304.482 | H84: ='2_Capability_Assessment'!$J$33 -> L1 | I84: G&A as % of revenue, vendor spend
C85: Contract negotiation leverage | D85: DC | E85: =IFERROR('2_Capability_Assessment'!$M$34/SUMIF('2_Capability_Assessment'!$B$6:$B$41,$B$22,'2_Capability_Assessment'!$M$6:$M$41),0) -> 0.13333333 | F85: =$E$22*$E85 -> 2160000 | G85: =$O$22*$E85 -> 37536.321 | H85: ='2_Capability_Assessment'!$J$34 -> L3 | I85: Gross margin, vendor spend
B86: Employee experience | C86: Knowledge retrieval and reuse | D86: DC | E86: =IFERROR('2_Capability_Assessment'!$M$35/SUMIF('2_Capability_Assessment'!$B$6:$B$41,$B$23,'2_Capability_Assessment'!$M$6:$M$41),0) -> 0.1875 | F86: =$E$23*$E86 -> 4050000 | G86: =$O$23*$E86 -> 374918.61 | H86: ='2_Capability_Assessment'!$J$35 -> L4 | I86: G&A as % of revenue, time to resolution
C87: Process automation in back office | D87: AUT | E87: =IFERROR('2_Capability_Assessment'!$M$36/SUMIF('2_Capability_Assessment'!$B$6:$B$41,$B$23,'2_Capability_Assessment'!$M$6:$M$41),0) -> 0.375 | F87: =$E$23*$E87 -> 8100000 | G87: =$O$23*$E87 -> 749837.22 | H87: ='2_Capability_Assessment'!$J$36 -> L2 | I87: G&A as % of revenue, cost to serve
C88: Talent acquisition and ramp | D88: DE | E88: =IFERROR('2_Capability_Assessment'!$M$37/SUMIF('2_Capability_Assessment'!$B$6:$B$41,$B$23,'2_Capability_Assessment'!$M$6:$M$41),0) -> 0.3125 | F88: =$E$23*$E88 -> 6750000 | G88: =$O$23*$E88 -> 624864.35 | H88: ='2_Capability_Assessment'!$J$37 -> L3 | I88: Time to productivity, G&A as % of revenue
C89: Workforce planning | D89: OA | E89: =IFERROR('2_Capability_Assessment'!$M$38/SUMIF('2_Capability_Assessment'!$B$6:$B$41,$B$23,'2_Capability_Assessment'!$M$6:$M$41),0) -> 0.125 | F89: =$E$23*$E89 -> 2700000 | G89: =$O$23*$E89 -> 249945.74 | H89: ='2_Capability_Assessment'!$J$38 -> L4 | I89: Headcount per $M ARR, cost to serve
B90: Capital efficiency | C90: Unit economics by segment | D90: OA | E90: =IFERROR('2_Capability_Assessment'!$M$39/SUMIF('2_Capability_Assessment'!$B$6:$B$41,$B$24,'2_Capability_Assessment'!$M$6:$M$41),0) -> 0.35714286 | F90: =$E$24*$E90 -> 0 | G90: =$O$24*$E90 -> 0 | H90: ='2_Capability_Assessment'!$J$39 -> L3 | I90: CAC payback, cost to serve
C91: Spend governance | D91: AUT | E91: =IFERROR('2_Capability_Assessment'!$M$40/SUMIF('2_Capability_Assessment'!$B$6:$B$41,$B$24,'2_Capability_Assessment'!$M$6:$M$41),0) -> 0.28571429 | F91: =$E$24*$E91 -> 0 | G91: =$O$24*$E91 -> 0 | H91: ='2_Capability_Assessment'!$J$40 -> L2 | I91: Rule of 40, opex variance
C92: Burn discipline | D92: DE | E92: =IFERROR('2_Capability_Assessment'!$M$41/SUMIF('2_Capability_Assessment'!$B$6:$B$41,$B$24,'2_Capability_Assessment'!$M$6:$M$41),0) -> 0.35714286 | F92: =$E$24*$E92 -> 0 | G92: =$O$24*$E92 -> 0 | H92: ='2_Capability_Assessment'!$J$41 -> L3 | I92: Rule of 40, burn multiple
B93: TOTAL | F93: =SUM(F57:F92) -> 484890000 | G93: =SUM(G57:G92) -> 49628021

Sheet 4d_Metric_Impact
B2: Metric impact
B3: Each operating metric starts from a stated baseline. The value pools that feed it are converted into an uplift and a target. Pools here are after feasibility and timing — the run rate a sponsor can underwrite, not the gross prize.
B5: INPUTS
B6: ARR | C6: 1200000000
B7: Total revenue | C7: ='4b_Value_Pools_by_Capability'!$D$6 -> 1500000000
B10: METRIC | C10: BASELINE | D10: UPLIFT | E10: TARGET | F10: POOL BEHIND THIS METRIC | G10: SHARE OF THE DISTINCT POOL | H10: HOW IT CONVERTS
B11: NRR | C11: 1.01 | D11: =(SUMIF('4b_Value_Pools_by_Capability'!$B$15:$B$24,$B$33,'4b_Value_Pools_by_Capability'!$O$15:$O$24)*$C$33+SUMIF('4b_Value_Pools_by_Capability'!$B$15:$B$24,$B$34,'4b_Value_Pools_by_Capability'!$O$15:$O$24)*$C$34+SUMIF('4b_Value_Pools_by_Capability'!$B$15:$B$24,$B$35,'4b_Value_Pools_by_Capability'!$O$15:$O$24)*$C$35+SUMIF('4b_Value_Pools_by_Capability'!$B$15:$B$24,$B$36,'4b_Value_Pools_by_Capability'!$O$15:$O$24)*$C$36+SUMIF('4b_Value_Pools_by_Capability'!$B$15:$B$24,$B$37,'4b_Value_Pools_by_Capability'!$O$15:$O$24)*$C$37+SUMIF('4b_Value_Pools_by_Capability'!$B$15:$B$24,$B$38,'4b_Value_Pools_by_Capability'!$O$15:$O$24)*$C$38+SUMIF('4b_Value_Pools_by_Capability'!$B$15:$B$24,$B$39,'4b_Value_Pools_by_Capability'!$O$15:$O$24)*$C$39+SUMIF('4b_Value_Pools_by_Capability'!$B$15:$B$24,$B$40,'4b_Value_Pools_by_Capability'!$O$15:$O$24)*$C$40+SUMIF('4b_Value_Pools_by_Capability'!$B$15:$B$24,$B$41,'4b_Value_Pools_by_Capability'!$O$15:$O$24)*$C$41+SUMIF('4b_Value_Pools_by_Capability'!$B$15:$B$24,$B$42,'4b_Value_Pools_by_Capability'!$O$15:$O$24)*$C$42)*'5_Implementation_Feasibility'!$E$13*'7_Value_Timing'!$C$25/$C$6 -> 0.0097270822 | E11: =$C11+$D11 -> 1.0197271 | F11: =(SUMIF('4b_Value_Pools_by_Capability'!$B$15:$B$24,$B$33,'4b_Value_Pools_by_Capability'!$O$15:$O$24)*$C$33+SUMIF('4b_Value_Pools_by_Capability'!$B$15:$B$24,$B$34,'4b_Value_Pools_by_Capability'!$O$15:$O$24)*$C$34+SUMIF('4b_Value_Pools_by_Capability'!$B$15:$B$24,$B$35,'4b_Value_Pools_by_Capability'!$O$15:$O$24)*$C$35+SUMIF('4b_Value_Pools_by_Capability'!$B$15:$B$24,$B$36,'4b_Value_Pools_by_Capability'!$O$15:$O$24)*$C$36+SUMIF('4b_Value_Pools_by_Capability'!$B$15:$B$24,$B$37,'4b_Value_Pools_by_Capability'!$O$15:$O$24)*$C$37+SUMIF('4b_Value_Pools_by_Capability'!$B$15:$B$24,$B$38,'4b_Value_Pools_by_Capability'!$O$15:$O$24)*$C$38+SUMIF('4b_Value_Pools_by_Capability'!$B$15:$B$24,$B$39,'4b_Value_Pools_by_Capability'!$O$15:$O$24)*$C$39+SUMIF('4b_Value_Pools_by_Capability'!$B$15:$B$24,$B$40,'4b_Value_Pools_by_Capability'!$O$15:$O$24)*$C$40+SUMIF('4b_Value_Pools_by_Capability'!$B$15:$B$24,$B$41,'4b_Value_Pools_by_Capability'!$O$15:$O$24)*$C$41+SUMIF('4b_Value_Pools_by_Capability'!$B$15:$B$24,$B$42,'4b_Value_Pools_by_Capability'!$O$15:$O$24)*$C$42)*'5_Implementation_Feasibility'!$E$13*'7_Value_Timing'!$C$25 -> 11672499 | G11: =IFERROR($F11/$C$24,"") -> 0.26862889 | H11: Revenue-side pools divided by ARR, added to baseline.
B12: GRR | C12: 0.9 | D12: =(SUMIF('4b_Value_Pools_by_Capability'!$B$15:$B$24,$B$33,'4b_Value_Pools_by_Capability'!$O$15:$O$24)*$D$33+SUMIF('4b_Value_Pools_by_Capability'!$B$15:$B$24,$B$34,'4b_Value_Pools_by_Capability'!$O$15:$O$24)*$D$34+SUMIF('4b_Value_Pools_by_Capability'!$B$15:$B$24,$B$35,'4b_Value_Pools_by_Capability'!$O$15:$O$24)*$D$35+SUMIF('4b_Value_Pools_by_Capability'!$B$15:$B$24,$B$36,'4b_Value_Pools_by_Capability'!$O$15:$O$24)*$D$36+SUMIF('4b_Value_Pools_by_Capability'!$B$15:$B$24,$B$37,'4b_Value_Pools_by_Capability'!$O$15:$O$24)*$D$37+SUMIF('4b_Value_Pools_by_Capability'!$B$15:$B$24,$B$38,'4b_Value_Pools_by_Capability'!$O$15:$O$24)*$D$38+SUMIF('4b_Value_Pools_by_Capability'!$B$15:$B$24,$B$39,'4b_Value_Pools_by_Capability'!$O$15:$O$24)*$D$39+SUMIF('4b_Value_Pools_by_Capability'!$B$15:$B$24,$B$40,'4b_Value_Pools_by_Capability'!$O$15:$O$24)*$D$40+SUMIF('4b_Value_Pools_by_Capability'!$B$15:$B$24,$B$41,'4b_Value_Pools_by_Capability'!$O$15:$O$24)*$D$41+SUMIF('4b_Value_Pools_by_Capability'!$B$15:$B$24,$B$42,'4b_Value_Pools_by_Capability'!$O$15:$O$24)*$D$42)*'5_Implementation_Feasibility'!$E$13*'7_Value_Timing'!$C$25/$C$6 -> 0.0011371129 | E12: =$C12+$D12 -> 0.90113711 | F12: =(SUMIF('4b_Value_Pools_by_Capability'!$B$15:$B$24,$B$33,'4b_Value_Pools_by_Capability'!$O$15:$O$24)*$D$33+SUMIF('4b_Value_Pools_by_Capability'!$B$15:$B$24,$B$34,'4b_Value_Pools_by_Capability'!$O$15:$O$24)*$D$34+SUMIF('4b_Value_Pools_by_Capability'!$B$15:$B$24,$B$35,'4b_Value_Pools_by_Capability'!$O$15:$O$24)*$D$35+SUMIF('4b_Value_Pools_by_Capability'!$B$15:$B$24,$B$36,'4b_Value_Pools_by_Capability'!$O$15:$O$24)*$D$36+SUMIF('4b_Value_Pools_by_Capability'!$B$15:$B$24,$B$37,'4b_Value_Pools_by_Capability'!$O$15:$O$24)*$D$37+SUMIF('4b_Value_Pools_by_Capability'!$B$15:$B$24,$B$38,'4b_Value_Pools_by_Capability'!$O$15:$O$24)*$D$38+SUMIF('4b_Value_Pools_by_Capability'!$B$15:$B$24,$B$39,'4b_Value_Pools_by_Capability'!$O$15:$O$24)*$D$39+SUMIF('4b_Value_Pools_by_Capability'!$B$15:$B$24,$B$40,'4b_Value_Pools_by_Capability'!$O$15:$O$24)*$D$40+SUMIF('4b_Value_Pools_by_Capability'!$B$15:$B$24,$B$41,'4b_Value_Pools_by_Capability'!$O$15:$O$24)*$D$41+SUMIF('4b_Value_Pools_by_Capability'!$B$15:$B$24,$B$42,'4b_Value_Pools_by_Capability'!$O$15:$O$24)*$D$42)*'5_Implementation_Feasibility'!$E$13*'7_Value_Timing'!$C$25 -> 1364535.5 | G12: =IFERROR($F12/$C$24,"") -> 0.031403187 | H12: Retention pool, revenue share only, divided by ARR.
B13: Gross margin | C13: 0.73 | D13: =(SUMIF('4b_Value_Pools_by_Capability'!$B$15:$B$24,$B$33,'4b_Value_Pools_by_Capability'!$O$15:$O$24)*$E$33+SUMIF('4b_Value_Pools_by_Capability'!$B$15:$B$24,$B$34,'4b_Value_Pools_by_Capability'!$O$15:$O$24)*$E$34+SUMIF('4b_Value_Pools_by_Capability'!$B$15:$B$24,$B$35,'4b_Value_Pools_by_Capability'!$O$15:$O$24)*$E$35+SUMIF('4b_Value_Pools_by_Capability'!$B$15:$B$24,$B$36,'4b_Value_Pools_by_Capability'!$O$15:$O$24)*$E$36+SUMIF('4b_Value_Pools_by_Capability'!$B$15:$B$24,$B$37,'4b_Value_Pools_by_Capability'!$O$15:$O$24)*$E$37+SUMIF('4b_Value_Pools_by_Capability'!$B$15:$B$24,$B$38,'4b_Value_Pools_by_Capability'!$O$15:$O$24)*$E$38+SUMIF('4b_Value_Pools_by_Capability'!$B$15:$B$24,$B$39,'4b_Value_Pools_by_Capability'!$O$15:$O$24)*$E$39+SUMIF('4b_Value_Pools_by_Capability'!$B$15:$B$24,$B$40,'4b_Value_Pools_by_Capability'!$O$15:$O$24)*$E$40+SUMIF('4b_Value_Pools_by_Capability'!$B$15:$B$24,$B$41,'4b_Value_Pools_by_Capability'!$O$15:$O$24)*$E$41+SUMIF('4b_Value_Pools_by_Capability'!$B$15:$B$24,$B$42,'4b_Value_Pools_by_Capability'!$O$15:$O$24)*$E$42)*'5_Implementation_Feasibility'!$E$13*'7_Value_Timing'!$C$25/$C$7 -> 0.00016432584 | E13: =$C13+$D13 -> 0.73016433 | F13: =(SUMIF('4b_Value_Pools_by_Capability'!$B$15:$B$24,$B$33,'4b_Value_Pools_by_Capability'!$O$15:$O$24)*$E$33+SUMIF('4b_Value_Pools_by_Capability'!$B$15:$B$24,$B$34,'4b_Value_Pools_by_Capability'!$O$15:$O$24)*$E$34+SUMIF('4b_Value_Pools_by_Capability'!$B$15:$B$24,$B$35,'4b_Value_Pools_by_Capability'!$O$15:$O$24)*$E$35+SUMIF('4b_Value_Pools_by_Capability'!$B$15:$B$24,$B$36,'4b_Value_Pools_by_Capability'!$O$15:$O$24)*$E$36+SUMIF('4b_Value_Pools_by_Capability'!$B$15:$B$24,$B$37,'4b_Value_Pools_by_Capability'!$O$15:$O$24)*$E$37+SUMIF('4b_Value_Pools_by_Capability'!$B$15:$B$24,$B$38,'4b_Value_Pools_by_Capability'!$O$15:$O$24)*$E$38+SUMIF('4b_Value_Pools_by_Capability'!$B$15:$B$24,$B$39,'4b_Value_Pools_by_Capability'!$O$15:$O$24)*$E$39+SUMIF('4b_Value_Pools_by_Capability'!$B$15:$B$24,$B$40,'4b_Value_Pools_by_Capability'!$O$15:$O$24)*$E$40+SUMIF('4b_Value_Pools_by_Capability'!$B$15:$B$24,$B$41,'4b_Value_Pools_by_Capability'!$O$15:$O$24)*$E$41+SUMIF('4b_Value_Pools_by_Capability'!$B$15:$B$24,$B$42,'4b_Value_Pools_by_Capability'!$O$15:$O$24)*$E$42)*'5_Implementation_Feasibility'!$E$13*'7_Value_Timing'!$C$25 -> 246488.76 | G13: =IFERROR($F13/$C$24,"") -> 0.0056726503 | H13: Infrastructure and inference cost removed, divided by revenue.
B14: R&D as % of revenue | C14: 0.203 | D14: =-(SUMIF('4b_Value_Pools_by_Capability'!$B$15:$B$24,$B$33,'4b_Value_Pools_by_Capability'!$O$15:$O$24)*$F$33+SUMIF('4b_Value_Pools_by_Capability'!$B$15:$B$24,$B$34,'4b_Value_Pools_by_Capability'!$O$15:$O$24)*$F$34+SUMIF('4b_Value_Pools_by_Capability'!$B$15:$B$24,$B$35,'4b_Value_Pools_by_Capability'!$O$15:$O$24)*$F$35+SUMIF('4b_Value_Pools_by_Capability'!$B$15:$B$24,$B$36,'4b_Value_Pools_by_Capability'!$O$15:$O$24)*$F$36+SUMIF('4b_Value_Pools_by_Capability'!$B$15:$B$24,$B$37,'4b_Value_Pools_by_Capability'!$O$15:$O$24)*$F$37+SUMIF('4b_Value_Pools_by_Capability'!$B$15:$B$24,$B$38,'4b_Value_Pools_by_Capability'!$O$15:$O$24)*$F$38+SUMIF('4b_Value_Pools_by_Capability'!$B$15:$B$24,$B$39,'4b_Value_Pools_by_Capability'!$O$15:$O$24)*$F$39+SUMIF('4b_Value_Pools_by_Capability'!$B$15:$B$24,$B$40,'4b_Value_Pools_by_Capability'!$O$15:$O$24)*$F$40+SUMIF('4b_Value_Pools_by_Capability'!$B$15:$B$24,$B$41,'4b_Value_Pools_by_Capability'!$O$15:$O$24)*$F$41+SUMIF('4b_Value_Pools_by_Capability'!$B$15:$B$24,$B$42,'4b_Value_Pools_by_Capability'!$O$15:$O$24)*$F$42)*'5_Implementation_Feasibility'!$E$13*'7_Value_Timing'!$C$25/$C$7 -> -0.0060005161 | E14: =$C14+$D14 -> 0.19699948 | F14: =(SUMIF('4b_Value_Pools_by_Capability'!$B$15:$B$24,$B$33,'4b_Value_Pools_by_Capability'!$O$15:$O$24)*$F$33+SUMIF('4b_Value_Pools_by_Capability'!$B$15:$B$24,$B$34,'4b_Value_Pools_by_Capability'!$O$15:$O$24)*$F$34+SUMIF('4b_Value_Pools_by_Capability'!$B$15:$B$24,$B$35,'4b_Value_Pools_by_Capability'!$O$15:$O$24)*$F$35+SUMIF('4b_Value_Pools_by_Capability'!$B$15:$B$24,$B$36,'4b_Value_Pools_by_Capability'!$O$15:$O$24)*$F$36+SUMIF('4b_Value_Pools_by_Capability'!$B$15:$B$24,$B$37,'4b_Value_Pools_by_Capability'!$O$15:$O$24)*$F$37+SUMIF('4b_Value_Pools_by_Capability'!$B$15:$B$24,$B$38,'4b_Value_Pools_by_Capability'!$O$15:$O$24)*$F$38+SUMIF('4b_Value_Pools_by_Capability'!$B$15:$B$24,$B$39,'4b_Value_Pools_by_Capability'!$O$15:$O$24)*$F$39+SUMIF('4b_Value_Pools_by_Capability'!$B$15:$B$24,$B$40,'4b_Value_Pools_by_Capability'!$O$15:$O$24)*$F$40+SUMIF('4b_Value_Pools_by_Capability'!$B$15:$B$24,$B$41,'4b_Value_Pools_by_Capability'!$O$15:$O$24)*$F$41+SUMIF('4b_Value_Pools_by_Capability'!$B$15:$B$24,$B$42,'4b_Value_Pools_by_Capability'!$O$15:$O$24)*$F$42)*'5_Implementation_Feasibility'!$E$13*'7_Value_Timing'!$C$25 -> 9000774.2 | G14: =IFERROR($F14/$C$24,"") -> 0.20714228 | H14: Engineering cost removed, divided by revenue. Lower is better.
B15: G&A as % of revenue | C15: 0.058 | D15: =-(SUMIF('4b_Value_Pools_by_Capability'!$B$15:$B$24,$B$33,'4b_Value_Pools_by_Capability'!$O$15:$O$24)*$G$33+SUMIF('4b_Value_Pools_by_Capability'!$B$15:$B$24,$B$34,'4b_Value_Pools_by_Capability'!$O$15:$O$24)*$G$34+SUMIF('4b_Value_Pools_by_Capability'!$B$15:$B$24,$B$35,'4b_Value_Pools_by_Capability'!$O$15:$O$24)*$G$35+SUMIF('4b_Value_Pools_by_Capability'!$B$15:$B$24,$B$36,'4b_Value_Pools_by_Capability'!$O$15:$O$24)*$G$36+SUMIF('4b_Value_Pools_by_Capability'!$B$15:$B$24,$B$37,'4b_Value_Pools_by_Capability'!$O$15:$O$24)*$G$37+SUMIF('4b_Value_Pools_by_Capability'!$B$15:$B$24,$B$38,'4b_Value_Pools_by_Capability'!$O$15:$O$24)*$G$38+SUMIF('4b_Value_Pools_by_Capability'!$B$15:$B$24,$B$39,'4b_Value_Pools_by_Capability'!$O$15:$O$24)*$G$39+SUMIF('4b_Value_Pools_by_Capability'!$B$15:$B$24,$B$40,'4b_Value_Pools_by_Capability'!$O$15:$O$24)*$G$40+SUMIF('4b_Value_Pools_by_Capability'!$B$15:$B$24,$B$41,'4b_Value_Pools_by_Capability'!$O$15:$O$24)*$G$41+SUMIF('4b_Value_Pools_by_Capability'!$B$15:$B$24,$B$42,'4b_Value_Pools_by_Capability'!$O$15:$O$24)*$G$42)*'5_Implementation_Feasibility'!$E$13*'7_Value_Timing'!$C$25/$C$7 -> -0.0017865687 | E15: =$C15+$D15 -> 0.056213431 | F15: =(SUMIF('4b_Value_Pools_by_Capability'!$B$15:$B$24,$B$33,'4b_Value_Pools_by_Capability'!$O$15:$O$24)*$G$33+SUMIF('4b_Value_Pools_by_Capability'!$B$15:$B$24,$B$34,'4b_Value_Pools_by_Capability'!$O$15:$O$24)*$G$34+SUMIF('4b_Value_Pools_by_Capability'!$B$15:$B$24,$B$35,'4b_Value_Pools_by_Capability'!$O$15:$O$24)*$G$35+SUMIF('4b_Value_Pools_by_Capability'!$B$15:$B$24,$B$36,'4b_Value_Pools_by_Capability'!$O$15:$O$24)*$G$36+SUMIF('4b_Value_Pools_by_Capability'!$B$15:$B$24,$B$37,'4b_Value_Pools_by_Capability'!$O$15:$O$24)*$G$37+SUMIF('4b_Value_Pools_by_Capability'!$B$15:$B$24,$B$38,'4b_Value_Pools_by_Capability'!$O$15:$O$24)*$G$38+SUMIF('4b_Value_Pools_by_Capability'!$B$15:$B$24,$B$39,'4b_Value_Pools_by_Capability'!$O$15:$O$24)*$G$39+SUMIF('4b_Value_Pools_by_Capability'!$B$15:$B$24,$B$40,'4b_Value_Pools_by_Capability'!$O$15:$O$24)*$G$40+SUMIF('4b_Value_Pools_by_Capability'!$B$15:$B$24,$B$41,'4b_Value_Pools_by_Capability'!$O$15:$O$24)*$G$41+SUMIF('4b_Value_Pools_by_Capability'!$B$15:$B$24,$B$42,'4b_Value_Pools_by_Capability'!$O$15:$O$24)*$G$42)*'5_Implementation_Feasibility'!$E$13*'7_Value_Timing'!$C$25 -> 2679853.1 | G15: =IFERROR($F15/$C$24,"") -> 0.061673681 | H15: Back-office and revops cost removed. Lower is better.
B16: S&M as % of revenue | C16: 0.116 | D16: =-(SUMIF('4b_Value_Pools_by_Capability'!$B$15:$B$24,$B$33,'4b_Value_Pools_by_Capability'!$O$15:$O$24)*$H$33+SUMIF('4b_Value_Pools_by_Capability'!$B$15:$B$24,$B$34,'4b_Value_Pools_by_Capability'!$O$15:$O$24)*$H$34+SUMIF('4b_Value_Pools_by_Capability'!$B$15:$B$24,$B$35,'4b_Value_Pools_by_Capability'!$O$15:$O$24)*$H$35+SUMIF('4b_Value_Pools_by_Capability'!$B$15:$B$24,$B$36,'4b_Value_Pools_by_Capability'!$O$15:$O$24)*$H$36+SUMIF('4b_Value_Pools_by_Capability'!$B$15:$B$24,$B$37,'4b_Value_Pools_by_Capability'!$O$15:$O$24)*$H$37+SUMIF('4b_Value_Pools_by_Capability'!$B$15:$B$24,$B$38,'4b_Value_Pools_by_Capability'!$O$15:$O$24)*$H$38+SUMIF('4b_Value_Pools_by_Capability'!$B$15:$B$24,$B$39,'4b_Value_Pools_by_Capability'!$O$15:$O$24)*$H$39+SUMIF('4b_Value_Pools_by_Capability'!$B$15:$B$24,$B$40,'4b_Value_Pools_by_Capability'!$O$15:$O$24)*$H$40+SUMIF('4b_Value_Pools_by_Capability'!$B$15:$B$24,$B$41,'4b_Value_Pools_by_Capability'!$O$15:$O$24)*$H$41+SUMIF('4b_Value_Pools_by_Capability'!$B$15:$B$24,$B$42,'4b_Value_Pools_by_Capability'!$O$15:$O$24)*$H$42)*'5_Implementation_Feasibility'!$E$13*'7_Value_Timing'!$C$25/$C$7 -> -0.0013707168 | E16: =$C16+$D16 -> 0.11462928 | F16: =(SUMIF('4b_Value_Pools_by_Capability'!$B$15:$B$24,$B$33,'4b_Value_Pools_by_Capability'!$O$15:$O$24)*$H$33+SUMIF('4b_Value_Pools_by_Capability'!$B$15:$B$24,$B$34,'4b_Value_Pools_by_Capability'!$O$15:$O$24)*$H$34+SUMIF('4b_Value_Pools_by_Capability'!$B$15:$B$24,$B$35,'4b_Value_Pools_by_Capability'!$O$15:$O$24)*$H$35+SUMIF('4b_Value_Pools_by_Capability'!$B$15:$B$24,$B$36,'4b_Value_Pools_by_Capability'!$O$15:$O$24)*$H$36+SUMIF('4b_Value_Pools_by_Capability'!$B$15:$B$24,$B$37,'4b_Value_Pools_by_Capability'!$O$15:$O$24)*$H$37+SUMIF('4b_Value_Pools_by_Capability'!$B$15:$B$24,$B$38,'4b_Value_Pools_by_Capability'!$O$15:$O$24)*$H$38+SUMIF('4b_Value_Pools_by_Capability'!$B$15:$B$24,$B$39,'4b_Value_Pools_by_Capability'!$O$15:$O$24)*$H$39+SUMIF('4b_Value_Pools_by_Capability'!$B$15:$B$24,$B$40,'4b_Value_Pools_by_Capability'!$O$15:$O$24)*$H$40+SUMIF('4b_Value_Pools_by_Capability'!$B$15:$B$24,$B$41,'4b_Value_Pools_by_Capability'!$O$15:$O$24)*$H$41+SUMIF('4b_Value_Pools_by_Capability'!$B$15:$B$24,$B$42,'4b_Value_Pools_by_Capability'!$O$15:$O$24)*$H$42)*'5_Implementation_Feasibility'!$E$13*'7_Value_Timing'!$C$25 -> 2056075.3 | G16: =IFERROR($F16/$C$24,"") -> 0.047318165 | H16: Selling cost removed, divided by revenue. Lower is better.
B17: New logo growth | C17: 0.12 | D17: =(SUMIF('4b_Value_Pools_by_Capability'!$B$15:$B$24,$B$33,'4b_Value_Pools_by_Capability'!$O$15:$O$24)*$K$33+SUMIF('4b_Value_Pools_by_Capability'!$B$15:$B$24,$B$34,'4b_Value_Pools_by_Capability'!$O$15:$O$24)*$K$34+SUMIF('4b_Value_Pools_by_Capability'!$B$15:$B$24,$B$35,'4b_Value_Pools_by_Capability'!$O$15:$O$24)*$K$35+SUMIF('4b_Value_Pools_by_Capability'!$B$15:$B$24,$B$36,'4b_Value_Pools_by_Capability'!$O$15:$O$24)*$K$36+SUMIF('4b_Value_Pools_by_Capability'!$B$15:$B$24,$B$37,'4b_Value_Pools_by_Capability'!$O$15:$O$24)*$K$37+SUMIF('4b_Value_Pools_by_Capability'!$B$15:$B$24,$B$38,'4b_Value_Pools_by_Capability'!$O$15:$O$24)*$K$38+SUMIF('4b_Value_Pools_by_Capability'!$B$15:$B$24,$B$39,'4b_Value_Pools_by_Capability'!$O$15:$O$24)*$K$39+SUMIF('4b_Value_Pools_by_Capability'!$B$15:$B$24,$B$40,'4b_Value_Pools_by_Capability'!$O$15:$O$24)*$K$40+SUMIF('4b_Value_Pools_by_Capability'!$B$15:$B$24,$B$41,'4b_Value_Pools_by_Capability'!$O$15:$O$24)*$K$41+SUMIF('4b_Value_Pools_by_Capability'!$B$15:$B$24,$B$42,'4b_Value_Pools_by_Capability'!$O$15:$O$24)*$K$42)*'5_Implementation_Feasibility'!$E$13*'7_Value_Timing'!$C$25/$C$6 -> 0.011113827 | E17: =$C17+$D17 -> 0.13111383 | F17: =(SUMIF('4b_Value_Pools_by_Capability'!$B$15:$B$24,$B$33,'4b_Value_Pools_by_Capability'!$O$15:$O$24)*$K$33+SUMIF('4b_Value_Pools_by_Capability'!$B$15:$B$24,$B$34,'4b_Value_Pools_by_Capability'!$O$15:$O$24)*$K$34+SUMIF('4b_Value_Pools_by_Capability'!$B$15:$B$24,$B$35,'4b_Value_Pools_by_Capability'!$O$15:$O$24)*$K$35+SUMIF('4b_Value_Pools_by_Capability'!$B$15:$B$24,$B$36,'4b_Value_Pools_by_Capability'!$O$15:$O$24)*$K$36+SUMIF('4b_Value_Pools_by_Capability'!$B$15:$B$24,$B$37,'4b_Value_Pools_by_Capability'!$O$15:$O$24)*$K$37+SUMIF('4b_Value_Pools_by_Capability'!$B$15:$B$24,$B$38,'4b_Value_Pools_by_Capability'!$O$15:$O$24)*$K$38+SUMIF('4b_Value_Pools_by_Capability'!$B$15:$B$24,$B$39,'4b_Value_Pools_by_Capability'!$O$15:$O$24)*$K$39+SUMIF('4b_Value_Pools_by_Capability'!$B$15:$B$24,$B$40,'4b_Value_Pools_by_Capability'!$O$15:$O$24)*$K$40+SUMIF('4b_Value_Pools_by_Capability'!$B$15:$B$24,$B$41,'4b_Value_Pools_by_Capability'!$O$15:$O$24)*$K$41+SUMIF('4b_Value_Pools_by_Capability'!$B$15:$B$24,$B$42,'4b_Value_Pools_by_Capability'!$O$15:$O$24)*$K$42)*'5_Implementation_Feasibility'!$E$13*'7_Value_Timing'!$C$25 -> 13336593 | G17: =IFERROR($F17/$C$24,"") -> 0.30692607 | H17: New customers won. Feeds ARR growth alongside expansion.
B18: Realised price vs list | C18: 0.9 | D18: =(SUMIF('4b_Value_Pools_by_Capability'!$B$15:$B$24,$B$33,'4b_Value_Pools_by_Capability'!$O$15:$O$24)*$J$33+SUMIF('4b_Value_Pools_by_Capability'!$B$15:$B$24,$B$34,'4b_Value_Pools_by_Capability'!$O$15:$O$24)*$J$34+SUMIF('4b_Value_Pools_by_Capability'!$B$15:$B$24,$B$35,'4b_Value_Pools_by_Capability'!$O$15:$O$24)*$J$35+SUMIF('4b_Value_Pools_by_Capability'!$B$15:$B$24,$B$36,'4b_Value_Pools_by_Capability'!$O$15:$O$24)*$J$36+SUMIF('4b_Value_Pools_by_Capability'!$B$15:$B$24,$B$37,'4b_Value_Pools_by_Capability'!$O$15:$O$24)*$J$37+SUMIF('4b_Value_Pools_by_Capability'!$B$15:$B$24,$B$38,'4b_Value_Pools_by_Capability'!$O$15:$O$24)*$J$38+SUMIF('4b_Value_Pools_by_Capability'!$B$15:$B$24,$B$39,'4b_Value_Pools_by_Capability'!$O$15:$O$24)*$J$39+SUMIF('4b_Value_Pools_by_Capability'!$B$15:$B$24,$B$40,'4b_Value_Pools_by_Capability'!$O$15:$O$24)*$J$40+SUMIF('4b_Value_Pools_by_Capability'!$B$15:$B$24,$B$41,'4b_Value_Pools_by_Capability'!$O$15:$O$24)*$J$41+SUMIF('4b_Value_Pools_by_Capability'!$B$15:$B$24,$B$42,'4b_Value_Pools_by_Capability'!$O$15:$O$24)*$J$42)*'5_Implementation_Feasibility'!$E$13*'7_Value_Timing'!$C$25/$C$7 -> 0.0020635438 | E18: =$C18+$D18 -> 0.90206354 | F18: =(SUMIF('4b_Value_Pools_by_Capability'!$B$15:$B$24,$B$33,'4b_Value_Pools_by_Capability'!$O$15:$O$24)*$J$33+SUMIF('4b_Value_Pools_by_Capability'!$B$15:$B$24,$B$34,'4b_Value_Pools_by_Capability'!$O$15:$O$24)*$J$34+SUMIF('4b_Value_Pools_by_Capability'!$B$15:$B$24,$B$35,'4b_Value_Pools_by_Capability'!$O$15:$O$24)*$J$35+SUMIF('4b_Value_Pools_by_Capability'!$B$15:$B$24,$B$36,'4b_Value_Pools_by_Capability'!$O$15:$O$24)*$J$36+SUMIF('4b_Value_Pools_by_Capability'!$B$15:$B$24,$B$37,'4b_Value_Pools_by_Capability'!$O$15:$O$24)*$J$37+SUMIF('4b_Value_Pools_by_Capability'!$B$15:$B$24,$B$38,'4b_Value_Pools_by_Capability'!$O$15:$O$24)*$J$38+SUMIF('4b_Value_Pools_by_Capability'!$B$15:$B$24,$B$39,'4b_Value_Pools_by_Capability'!$O$15:$O$24)*$J$39+SUMIF('4b_Value_Pools_by_Capability'!$B$15:$B$24,$B$40,'4b_Value_Pools_by_Capability'!$O$15:$O$24)*$J$40+SUMIF('4b_Value_Pools_by_Capability'!$B$15:$B$24,$B$41,'4b_Value_Pools_by_Capability'!$O$15:$O$24)*$J$41+SUMIF('4b_Value_Pools_by_Capability'!$B$15:$B$24,$B$42,'4b_Value_Pools_by_Capability'!$O$15:$O$24)*$J$42)*'5_Implementation_Feasibility'!$E$13*'7_Value_Timing'!$C$25 -> 3095315.7 | G18: =IFERROR($F18/$C$24,"") -> 0.071235068 | H18: Discount recovered, divided by revenue.
B19: EBITDA margin | C19: 0.42 | D19: =-$D$14-$D$15-$D$16+$D$13 -> 0.0093221275 | E19: =$C19+$D19 -> 0.42932213 | F19: ="derived" -> derived | H19: Derived from the four cost-side rows above. No pool of its own.
B20: Rule of 40 | C20: =$C$21+$C$19 -> 0.55 | D20: =$D$21+$D$19 -> 0.030163037 | E20: =$C$20+$D$20 -> 0.58016304 | F20: ="derived" -> derived | H20: Derived, not a separate pool. The strongest single predictor of the SaaS multiple.
B21: ARR growth | C21: =$C$17+($C$11-1) -> 0.13 | D21: =$D$17+$D$11 -> 0.02084091 | E21: =$C$21+$D$21 -> 0.15084091 | F21: ="derived" -> derived | H21: New logo growth plus expansion from NRR above 100%. Derived, no pool of its own.
B22: Every lever is allocated once. The pool column now sums to the distinct annual pool.
B24: Sum of the pool column | C24: =SUM($F$11:$F$18) -> 43452134 | E24: Ties to the after-timing pool on tab 8. This is the only additive number on this tab.
B25: Distinct annual pool, after feasibility and timing | C25: ='4b_Value_Pools_by_Capability'!$O$25*'5_Implementation_Feasibility'!$E$13*'7_Value_Timing'!$C$25 -> 43452134
B26: Difference | C26: =$C$24-$C$25 -> 0 | E26: Should be zero. Anything else means a lever’s allocation row does not sum to 100%.
B27: 4. Pricing is split 55 / 45 between revenue and cost effect, matching the revenue share on 4b.
B28: NOTES
B29: 1. Baselines in the amber column are entries. Replace them with the company’s actual reported figures before quoting anything.
B30: ALLOCATION — how each lever’s pool is split across the metrics it moves
B31: Each row sums to 100%. Change a weight and the metric pools above move with it. This is what stops a lever being counted twice.
B32: VALUE LEVER | C32: NRR | D32: GRR | E32: Gross margin | F32: R&D as % of revenue | G32: G&A as % of revenue | H32: S&M as % of revenue | I32: ARR growth | J32: Realised price vs list | K32: New logo growth | L32: CHECK
B33: Product and services differentiation | C33: 0.4 | D33: 0 | E33: 0 | F33: 0 | G33: 0 | H33: 0 | I33: 0 | J33: 0 | K33: 0.6 | L33: =SUM(C33:K33) -> 1
B34: Pricing and packaging | C34: 0.5 | D34: 0 | E34: 0 | F34: 0 | G34: 0 | H34: 0 | I34: 0 | J34: 0.5 | K34: 0 | L34: =SUM(C34:K34) -> 1
B35: Sales effectiveness | C35: 0 | D35: 0 | E35: 0 | F35: 0 | G35: 0 | H35: 0.6 | I35: 0 | J35: 0 | K35: 0.4 | L35: =SUM(C35:K35) -> 1
B36: Customer retention and expansion | C36: 0.4 | D36: 0.6 | E36: 0 | F36: 0 | G36: 0 | H36: 0 | I36: 0 | J36: 0 | K36: 0 | L36: =SUM(C36:K36) -> 1
B37: Ecosystem strategy | C37: 0 | D37: 0 | E37: 0 | F37: 0 | G37: 0 | H37: 0 | I37: 0 | J37: 0 | K37: 1 | L37: =SUM(C37:K37) -> 1
B38: Product engineering | C38: 0 | D38: 0 | E38: 0 | F38: 1 | G38: 0 | H38: 0 | I38: 0 | J38: 0 | K38: 0 | L38: =SUM(C38:K38) -> 1
B39: Revenue operations | C39: 0 | D39: 0 | E39: 0 | F39: 0 | G39: 1 | H39: 0 | I39: 0 | J39: 0 | K39: 0 | L39: =SUM(C39:K39) -> 1
B40: Supplier and infrastructure cost | C40: 0 | D40: 0 | E40: 1 | F40: 0 | G40: 0 | H40: 0 | I40: 0 | J40: 0 | K40: 0 | L40: =SUM(C40:K40) -> 1
B41: Employee experience | C41: 0 | D41: 0 | E41: 0 | F41: 0 | G41: 1 | H41: 0 | I41: 0 | J41: 0 | K41: 0 | L41: =SUM(C41:K41) -> 1
B42: Capital efficiency | C42: 0 | D42: 0 | E42: 0 | F42: 0 | G42: 0 | H42: 0 | I42: 0 | J42: 0 | K42: 0 | L42: =SUM(C42:K42) -> 0

Sheet 4m_Exit_Multiple
B2: Exit multiple
B3: ARR growth — expansion from existing customers plus new logo — is the single largest predictor of where a SaaS company sits in the multiple distribution. The cohort medians below are observed, not modelled.
B5: A. OBSERVED GROWTH COHORTS
B6: ARR growth | C6: EV / ARR median | D6: band top | E6: n | G6: Source
B7: Under 10% | C7: 1.9 | D7: 0.1 | E7: 18 | G7: SaaS Capital Index, 30 June 2026.
B8: 10 to 20% | C8: 3.1 | D8: 0.2 | E8: 23 | G8: The cohort Contoso sits in today.
B9: 20 to 30% | C9: 5.5 | D9: 0.3 | E9: 11 | G9: Only 6 of 58 constituents grew faster than 30% in the year to June 2026.
B10: Above 30% | C10: 10 | D10: 9.99 | E10: 6 | G10: High-growth SaaS commands two to three times the multiple of slow-growth peers.
B12: B. WITHIN-BAND MOVEMENT
B13: Uplift per 10 points of growth | C13: 1.25 | G13: Published range is +1.0x to +1.5x per 10 points. Midpoint used. Applies inside a band; crossing a band uses the cohort step.
B17: C. EXIT MULTIPLE AND ENTERPRISE VALUE
B18: Two growth paths. The pool path uses the ARR growth the value pools actually produce. The frontier path assumes the company reaches frontier growth. The gap between them is the honest uncertainty.
B19: All growth comes from the value pools on 4b, via ARR growth on 4d. No assumed trajectory.
B20: CAPABILITY POSITION | C20: ARR GROWTH | D20: COHORT | E20: MULTIPLE | F20: ENTERPRISE VALUE
B21: POOL PATH — growth the value pools produce
B22: Today | C22: ='4d_Metric_Impact'!$C$21 -> 0.13 | D22: =IFERROR(INDEX($C$7:$C$10,MATCH($C22,$D$7:$D$10,1)+1),$C$7) -> 3.1 | E22: ='0_AI_to_EV_Bridge'!$C$12 -> 9.1666667 | F22: =$E22*'0_AI_to_EV_Bridge'!$C$11 -> 11000000000
B23: Move one level | C23: ='4d_Metric_Impact'!$C$21+'4d_Metric_Impact'!$D$21*0.46 -> 0.13958682 | D23: =IFERROR(INDEX($C$7:$C$10,MATCH($C23,$D$7:$D$10,1)+1),$C$7) -> 3.1 | E23: =$E$22*$D23/$D$22+($C23-$C$22)*10*$C$13 -> 9.2865019 | F23: =$E23*'0_AI_to_EV_Bridge'!$C$11 -> 1.1143802e+10
B24: Move two levels | C24: ='4d_Metric_Impact'!$C$21+'4d_Metric_Impact'!$D$21*0.93 -> 0.14938205 | D24: =IFERROR(INDEX($C$7:$C$10,MATCH($C24,$D$7:$D$10,1)+1),$C$7) -> 3.1 | E24: =$E$22*$D24/$D$22+($C24-$C$22)*10*$C$13 -> 9.4089422 | F24: =$E24*'0_AI_to_EV_Bridge'!$C$11 -> 1.1290731e+10
B25: At the frontier | C25: ='4d_Metric_Impact'!$C$21+'4d_Metric_Impact'!$D$21*1 -> 0.15084091 | D25: =IFERROR(INDEX($C$7:$C$10,MATCH($C25,$D$7:$D$10,1)+1),$C$7) -> 3.1 | E25: =$E$22*$D25/$D$22+($C25-$C$22)*10*$C$13 -> 9.427178 | F25: =$E25*'0_AI_to_EV_Bridge'!$C$11 -> 1.1312614e+10
B27: VALUE FROM THE MULTIPLE, ABOVE TODAY | F27: ENTERPRISE VALUE
B28: moving one level | F28: =$F23-$F$22 -> 1.4380228e+08
B29: moving two levels | F29: =$F24-$F$22 -> 2.9073069e+08
B30: moving as far as the pools reach | F30: =$F25-$F$22 -> 3.1261364e+08
B33: SOURCES AND LIMITS
B34: 1. Cohort medians are observed, not modelled. SaaS Capital Index constituents at 30 June 2026: 5.5x for 20–30% growers (n=11), 3.1x for 10–20% (n=23), 1.9x for under 10% (n=18). 58 constituents in total; only 6 grew faster than 30%.
B35: 2. Revenue scale is not the screen. Dispersion in that set runs 0.1x to 63x and trailing growth explains most of it — a sub-10% grower trades near 1.9x whether it books $200M or $2B.
B36: 3. Within-band movement uses the published coefficient of roughly +1.0x to +1.5x per 10 points of growth. Midpoint used.
B37: 4. ARR growth on 4d is new logo growth plus expansion from NRR above 100%, so all ten value levers reach the multiple.
B38: 5. Today’s multiple is the enterprise value on tab 0 divided by the metric set by the basis at entry. It is not predicted.
B39: 6. Growth here comes only from the value pools. There is no assumed path to a frontier growth rate — no published data maps a capability level to a growth rate, so any such path would be invented.
B40: 7. CONTEXT WORTH CHECKING: Contoso at 13% growth sits at the market median, but its 9.17x is roughly three times the 3.1x cohort median. A comparable PE take-private priced at 7.7x on 17% growth. The enterprise value input on tab 0 has not been tested against comparables.

Sheet 5_Implementation_Feasibility
B1: Implementation feasibility
B2: Will this company execute? Three factors multiply the value pool once, for the whole company. Two more shift when value arrives rather than how much survives. Anchors are written for vertical SaaS.
B4: INPUTS
B5: Industry vertical | C5: ='4b_Value_Pools_by_Capability'!$D$4 -> Vertical SaaS | D5: ='4b_Value_Pools_by_Capability'!$D$4 -> Vertical SaaS
B6: Capturable pool, before feasibility | D6: ='4b_Value_Pools_by_Capability'!$E$29 -> 49628021
B8: A. FACTORS THAT MULTIPLY THE POOL
B9: FACTOR | C9: WEIGHT | D9: YOUR ANSWER | E9: VALUE | F9: 1 Weakest | G9: 2 | H9: 3 | I9: 4 | J9: 5 Strongest
B10: Vendor / technology risk | C10: 0.35 | D10: 5 | E10: =IFERROR(INDEX($F$26:$J$30,1,$D10),"") -> 1 | F10: Core product capability rests on one vendor's roadmap; multi-year lock-in with no alternative | G10: Deep coupling to one provider's proprietary features; migration would be a project | H10: Single provider, standard commercial terms, no deep coupling | I10: Primary provider with a tested fallback and an abstraction layer in place | J10: Model-agnostic; multiple providers hedged; core capability built in-house. Switching measured in weeks
B11: Competitive response speed | C11: 0.35 | D11: 3 | E11: =IFERROR(INDEX($F$26:$J$30,2,$D11),"") -> 0.85 | F11: Category-wide commoditisation; AI capability is table stakes and undifferentiated | G11: Competitors ship equivalent features within a release cycle | H11: Competitive parity; advantage measured in quarters | I11: Meaningful lead; switching costs and integration depth slow competitor gains | J11: Data moat competitors cannot replicate without equivalent proprietary data
B12: Regulatory exposure | C12: 0.3 | D12: 4 | E12: =IFERROR(INDEX($F$26:$J$30,3,$D12),"") -> 0.89 | F12: Active regulatory uncertainty on the core AI use case; risk of prohibition or material cost in the hold | G12: Concentrated in health, finance or defence with binding AI use restrictions | H12: Some regulated customers imposing contractual AI restrictions | I12: Light obligations (SOC 2, GDPR) with an established compliance posture | J12: No regulated customer verticals; no restrictions on AI in product or operations
B13: IFS residual multiplier | E13: =$E10^$C10*$E11^$C11*$E12^$C12 -> 0.91224948 | F13: VTR^0.35 x CRS^0.35 x REG^0.30, per Barr Table 7.
B14: Pool after feasibility | E14: =$D$6*$E$13 -> 45273137
B15: Feasibility haircut | E15: =$E$13-1 -> -0.087750517
B17: B. FACTORS THAT SHIFT WHEN VALUE ARRIVES
B18: FACTOR | D18: YOUR ANSWER | E18: VALUE | F18: 1 Weakest | G18: 2 | H18: 3 | I18: 4 | J18: 5 Strongest
B19: Organisational change capacity | D19: 3 | E19: =IFERROR(INDEX($F$26:$J$30,4,$D19),"") -> 0.75 | F19: Fragmented organisation, no change track record, prior initiatives rejected by staff | G19: No named sponsor; prior rollouts partially abandoned | H19: Sponsor exists, adoption uneven, past changes landed late | I19: Strong sponsor and a good adoption record, with some functional resistance | J19: Documented prior transformation delivered on schedule; voluntary tool adoption at scale; funded sponsor
B20: Data readiness | D20: =ROUND('2_Capability_Assessment'!$C$80/2,0) -> 3 | E20: =IFERROR(INDEX($F$26:$J$30,5,$D20),"") -> 0.75 | F20: Siloed operational databases; no analytical platform | G20: Reporting layer only; no analytical store; frequent disputes over numbers | H20: Warehouse exists; identity resolution partly manual; gaps in newer modules | I20: Warehouse with good coverage; some manual reconciliation | J20: Governed warehouse, resolved identity, contract-tested schemas, production model access
B21: Implied delay factor | E21: =1/(MAX($E19,0.1)^'7_Value_Timing'!$C$15*MAX($E20,0.1)^'7_Value_Timing'!$D$15) -> 1.3333333 | F21: Mirrors the formula tab 7 actually uses: 1 / (change capacity^0.40 x data readiness^0.60). It previously showed 1 / change capacity only, which disagreed with the ramp midpoint on tab 7.
B22: Data foundation cross-check | E22: =MIN(1,'2_Capability_Assessment'!$C$80/7) -> 0.95238095
B25: SCORE LIBRARY — vertical SaaS | F25: 1 | G25: 2 | H25: 3 | I25: 4 | J25: 5
B26: Vendor / technology risk | C26: Residual | F26: 0.75 | G26: 0.81 | H26: 0.88 | I26: 0.94 | J26: 1
B27: Competitive response speed | C27: Residual | F27: 0.7 | G27: 0.78 | H27: 0.85 | I27: 0.93 | J27: 1
B28: Regulatory exposure | C28: Residual | F28: 0.55 | G28: 0.66 | H28: 0.78 | I28: 0.89 | J28: 1
B29: Organisational change capacity | C29: Trajectory | F29: 0.5 | G29: 0.63 | H29: 0.75 | I29: 0.88 | J29: 1
B30: Data readiness | C30: Trajectory | F30: 0.5 | G30: 0.63 | H30: 0.75 | I30: 0.88 | J30: 1
B32: Only vertical SaaS anchors are carried. The IT managed services and cybersecurity libraries have been removed.

Sheet 6_Implementation_Cost
A1: Implementation cost — one-time, built bottom up
A2: Three workstreams you pay for once, plus the annual run rate. Scoped to the value pool the model sizes — see section C for the current figure. A programme costing materially more than the pool cannot be justified by the pool alone.
A4: Context — pulled from other tabs
B5: Industry vertical | C5: ='4b_Value_Pools_by_Capability'!$D$4 -> Vertical SaaS | G5: Set on 4_Value_Pools.
B6: Company revenue | C6: ='4b_Value_Pools_by_Capability'!$D$6 -> 1500000000 | G6: Set on 4_Value_Pools.
B7: Data readiness | C7: ='5_Implementation_Feasibility'!$E$20 -> 0.75 | G7: ="Guidance only — no longer multiplies anything. A score of "&TEXT(C7,"0.00")&" means messier data, so scope more remediation months in Section A rather than applying a formula." -> Guidance only — no longer multiplies anything. A score of 0.75 means messier data, so scope more remediation months in Section A rather than applying a formula.
B8: Organisational change capacity | C8: ='5_Implementation_Feasibility'!$E$19 -> 0.75 | G8: ="Guidance only — no longer multiplies anything. A score of "&TEXT(C8,"0.00")&" means a harder rollout, so raise the change management cost per user in Section A." -> Guidance only — no longer multiplies anything. A score of 0.75 means a harder rollout, so raise the change management cost per user in Section A.
B10: A. INPUTS — the one-time cost is built from these
B11: Input | C11: Value | H11: Note
B12: Total headcount | C12: 2700 | H12: Company headcount. Context only — does not drive cost.
B13: Users whose workflow changes | C13: 3000 | H13: Everyone whose way of working changes. Drives the change workstream.
B14: Loaded cost per FTE-month | C14: 15000 | H14: Fully burdened: salary, benefits, tax, tools.
B15: Data engineers on remediation | C15: 16 | H15: Headcount on the data workstream.
B16: Remediation duration (months) | C16: 11 | H16: Runs in parallel with the build.
B17: Engineers on build and integration | C17: 14 | H17: Headcount on the build workstream.
B18: Build duration (months) | C18: 12
B19: Tooling and licences during build | C19: 1140000 | H19: Non-people cost across both engineering workstreams.
B20: Change cost per affected user | C20: 400 | H20: Training, enablement, comms, productivity dip, value instrumentation.
B22: B. ONE-TIME COST
B23: Workstream | C23: Cost | D23: Share | E23: People | F23: Non-people | H23: How this number is built
B24: Data remediation | C24: =$E24+$F24 -> 3223255.8 | D24: =IFERROR($C24/$C$27,0) -> 0.42976744 | E24: =$C$15*$C$16*$C$14 -> 2640000 | F24: =$C$19*($E24/($E24+$E25)) -> 583255.81 | H24: Engineers x months x loaded cost, plus a share of tooling. Data preparation is where most AI programmes overrun.
B25: Build and integration | C25: =$E25+$F25 -> 3076744.2 | D25: =IFERROR($C25/$C$27,0) -> 0.41023256 | E25: =$C$17*$C$18*$C$14 -> 2520000 | F25: =$C$19*($E25/($E24+$E25)) -> 556744.19 | H25: Engineers x months x loaded cost, plus a share of tooling. Integration across ten levers and 36 capabilities.
B26: Change and value instrumentation | C26: =$E26+$F26 -> 1200000 | D26: =IFERROR($C26/$C$27,0) -> 0.16 | E26: =$C$13*$C$20 -> 1200000 | F26: 0 | H26: Affected users x cost per user. Includes the instrumentation that lifts Budget Displaced from L2 to L3.
B27: TOTAL one-time implementation cost | C27: =SUM(C24:C26) -> 7500000 | D27: =SUM(D24:D26) -> 1 | E27: =SUM(E24:E26) -> 6360000 | F27: =SUM(F24:F26) -> 1140000
B28: As a percentage of revenue | C28: =$C$27/$C$6 -> 0.005
B29: Cost per affected user, all-in | C29: =$C$27/$C$13 -> 2500
B30: Programme duration (longest workstream) | C30: =MAX($C$16,$C$18) -> 12
B32: C. BENCHMARK CHECKS
B33: Check | C33: This model | E33: Published range | H33: Verdict
B34: Data remediation as a share of one-time cost | C34: =$D$24 -> 0.42976744 | E34: 30% to 50% | H34: =IF(AND($C$34>=0.3,$C$34<=0.5),"IN RANGE","OUTSIDE RANGE")&" — data preparation is consistently the largest workstream." -> IN RANGE — data preparation is consistently the largest workstream.
B35: People as a share of one-time cost | C35: =$E$27/$C$27 -> 0.848 | E35: 40% to 60% | H35: =IF(AND($C$35>=0.4,$C$35<=0.6),"IN RANGE","OUTSIDE RANGE")&" — a people-heavy build is expected where the work is remediation rather than licence purchase." -> OUTSIDE RANGE — a people-heavy build is expected where the work is remediation rather than licence purchase.
B36: Value pool after feasibility, for reference | E36: ='5_Implementation_Feasibility'!$E$14 -> 45273137 | G36: NOT netted here. The pool is an annual run rate of $42.1M after feasibility; annual operating cost is $2.5M. Net operating benefit is roughly $39.6M a year against a $7.5M one-time build — payback inside the first year. The re-rating case is argued separately and is not funded by this program.
A38: Method: cost structure follows Barr, D. (2026), arXiv:2603.13278, Eq. 26, which splits capitalisable implementation cost from period expense. This tab covers the one-time leg only. The link from data readiness to remediation cost and from organisational change capacity to enablement cost is ours, not his — the code applies no such link. Component shares cross-checked against independent 2026 AI implementation cost studies.
B40: D. ANNUAL OPERATING COST — the run-rate half of Barr Eq. 26
A41: Barr splits cost into capitalisable implementation (C_cap, Section B above) and period expense (C_opex: SaaS fees, training, ongoing inference, monitoring). Sections A-C priced only C_cap. These four lines are annual and recur every year of the hold. NO SOURCED BENCHMARK EXISTS for any of them - the amber cells are zero until you set them from the client's own run-rate estimates. Under US GAAP training and ongoing compute are expensed; under IFRS SaaS fees are generally service expenses.
B43: Operating cost line | C43: Annual cost | D43: % of revenue | G43: What it covers
B44: Inference and compute | C44: 1300000 | D44: =IF($C$6=0,0,C44/$C$6) -> 0.00086666667 | G44: Variable cost of running models in production at agentic volume across the installed base.
B45: Licensing and platform fees | C45: 700000 | D45: =IF($C$6=0,0,C45/$C$6) -> 0.00046666667 | G45: Model access, vendor subscriptions, tooling. Recurring, not one-time.
B46: Monitoring and support | C46: 350000 | D46: =IF($C$6=0,0,C46/$C$6) -> 0.00023333333 | G46: Reliability, evaluation, incident response, safety review. Roughly 40 FTE.
B47: Maintenance and retraining | C47: 150000 | D47: =IF($C$6=0,0,C47/$C$6) -> 0.0001 | G47: Model drift, re-tuning, pipeline upkeep, prompt and eval maintenance.
B48: TOTAL annual operating cost | C48: =SUM(C44:C47) -> 2500000 | D48: =IF($C$6=0,0,C48/$C$6) -> 0.0016666667 | G48: Recurs every year. $2.5M against a $7.5M build is 33% — slightly above the published 15-30% benchmark, which is expected for an agentic platform with production inference volume.
B49: Operating cost as a share of one-time cost | C49: =IF($C$26=0,0,C48/$C$26) -> 2.0833333 | G49: 30.0% — top of the published 15-30% range.
B50: Flag | C50: =IF(C48=0,"NOT SET — the cost model is incomplete and tab 8 understates cost","Set") -> Set
B52: E. NPV OF TOTAL COST OVER THE HOLD — Barr Eq. 26
A53: NPV(Cost) = SUM over t of (C_cap,t + C_opex,t) / (1 + WACC)^t. Capitalisable build is placed in year 1; operating cost recurs across every year of the hold. This NPV is what Eq. 31 subtracts from enterprise value created - not the raw one-time figure the workbook used before.
B55: Hold period (years) | C55: 5 | G55: Matches the value window on 7_Value_Timing (60 months = 5 years). Keep the two aligned.
B56: WACC | C56: 0.1 | G56: PLACEHOLDER. Barr applies WACC as the risk-appropriate discount rate. Use the sponsor's own, not a default.
B58: Year | C58: C_cap (build) | D58: C_opex (run rate) | E58: Total | F58: Discounted
B59: 1 | C59: =IF(B59<=ROUNDUP($C$30/12,0),$C$27/ROUNDUP($C$30/12,0),0) -> 7500000 | D59: =IF(1<=$C$55,$C$48,0) -> 2500000 | E59: =C59+D59 -> 10000000 | F59: =E59/(1+$C$56)^1 -> 9090909.1
B60: 2 | C60: =IF(B60<=ROUNDUP($C$30/12,0),$C$27/ROUNDUP($C$30/12,0),0) -> 0 | D60: =IF(2<=$C$55,$C$48,0) -> 2500000 | E60: =C60+D60 -> 2500000 | F60: =E60/(1+$C$56)^2 -> 2066115.7
B61: 3 | C61: =IF(B61<=ROUNDUP($C$30/12,0),$C$27/ROUNDUP($C$30/12,0),0) -> 0 | D61: =IF(3<=$C$55,$C$48,0) -> 2500000 | E61: =C61+D61 -> 2500000 | F61: =E61/(1+$C$56)^3 -> 1878287
B62: 4 | C62: =IF(B62<=ROUNDUP($C$30/12,0),$C$27/ROUNDUP($C$30/12,0),0) -> 0 | D62: =IF(4<=$C$55,$C$48,0) -> 2500000 | E62: =C62+D62 -> 2500000 | F62: =E62/(1+$C$56)^4 -> 1707533.6
B63: 5 | C63: =IF(B63<=ROUNDUP($C$30/12,0),$C$27/ROUNDUP($C$30/12,0),0) -> 0 | D63: =IF(5<=$C$55,$C$48,0) -> 2500000 | E63: =C63+D63 -> 2500000 | F63: =E63/(1+$C$56)^5 -> 1552303.3
B64: NPV(Cost) | C64: =SUM(F59:F63) -> 16295149 | G64: Read by 8_Enterprise_Value C36 and C40. Replaces the raw one-time figure.
B65: Undiscounted total cost over the hold | C65: =SUM(E59:E63) -> 20000000 | G65: Cash out over five years, before discounting.
B67: F. CROSS-CHECK AGAINST BARR’S SIMPLIFICATION
B68: Barr's cross-industry rate: revenue x 1.2% | C68: =$C$6*0.012 -> 18000000 | G68: Barr, Table 22: a uniform 1.2% of revenue implementation rate, adopted for tractability. Published variation: financial services 1.2-1.6%, retail about 3.3%, discrete manufacturing 0.4-0.8%. Compare against C65. If the bottom-up build is far below this, the effort inputs in Section A are almost certainly too small.
B69: This model, undiscounted, versus that rate | C69: =IF(C68=0,0,C65/C68) -> 1.1111111 | G69: Barr’s 1.2% cross-industry rate implies $18.0M of one-time cost. This build is $7.5M, or 0.42x — light against that mark and worth a second look before IC.
B71: Note on Sobol sensitivity | C71: Barr's first-order decomposition finds implementation cost explains only about 1% of value-density variance; exit multiple explains 50% and capture rate 44%. So cost error does not reorder companies - but Barr still requires cost assumptions to be explicitly stated and challenged in any investment decision context.
B74: G. COST BY VALUE LEVER
B75: The one-time build and the annual operating cost allocated across the ten levers. Default allocation follows each lever’s share of the timed value pool — cost follows value. Override the share column where a lever is known to be cheaper or dearer than its pool implies.
B77: VALUE LEVER | C77: CAPS | D77: SHARE | E77: BUILD one-time | F77: OPERATING per year | G77: FIVE-YEAR CASH | H77: ANNUAL POOL after timing | I77: NET per year | J77: PAYBACK years | K77: VERDICT
B78: Product and services differentiation | C78: =COUNTIF('2_Capability_Assessment'!$B$6:$B$41,$B78) -> 5 | D78: =IFERROR('4b_Value_Pools_by_Capability'!$AB$15/SUM('4b_Value_Pools_by_Capability'!$AB$15:$AB$24),0) -> 0.44114592 | E78: =$C$27*$D78 -> 3308594.4 | F78: =$C$48*$D78 -> 1102864.8 | G78: =$E78+$F78*$C$55 -> 8822918.4 | H78: ='4b_Value_Pools_by_Capability'!$AB$15 -> 19168732 | I78: =$H78-$F78 -> 18065867 | J78: =IFERROR(IF($I78<=0,"never",$E78/$I78),"") -> 0.18314064 | K78: =IF($H78=0,"no pool — not funded",IF($I78<=0,"operating cost exceeds the pool",IF($E78/$I78<=1,"pays back inside a year",IF($E78/$I78<=3,"pays back inside the hold","does not pay back in the hold")))) -> pays back inside a year
B79: Pricing and packaging | C79: =COUNTIF('2_Capability_Assessment'!$B$6:$B$41,$B79) -> 2 | D79: =IFERROR('4b_Value_Pools_by_Capability'!$AB$16/SUM('4b_Value_Pools_by_Capability'!$AB$15:$AB$24),0) -> 0.14247014 | E79: =$C$27*$D79 -> 1068526 | F79: =$C$48*$D79 -> 356175.34 | G79: =$E79+$F79*$C$55 -> 2849402.7 | H79: ='4b_Value_Pools_by_Capability'!$AB$16 -> 6190631.4 | I79: =$H79-$F79 -> 5834456.1 | J79: =IFERROR(IF($I79<=0,"never",$E79/$I79),"") -> 0.18314064 | K79: =IF($H79=0,"no pool — not funded",IF($I79<=0,"operating cost exceeds the pool",IF($E79/$I79<=1,"pays back inside a year",IF($E79/$I79<=3,"pays back inside the hold","does not pay back in the hold")))) -> pays back inside a year
B80: Sales effectiveness | C80: =COUNTIF('2_Capability_Assessment'!$B$6:$B$41,$B80) -> 5 | D80: =IFERROR('4b_Value_Pools_by_Capability'!$AB$17/SUM('4b_Value_Pools_by_Capability'!$AB$15:$AB$24),0) -> 0.078863609 | E80: =$C$27*$D80 -> 591477.07 | F80: =$C$48*$D80 -> 197159.02 | G80: =$E80+$F80*$C$55 -> 1577272.2 | H80: ='4b_Value_Pools_by_Capability'!$AB$17 -> 3426792.1 | I80: =$H80-$F80 -> 3229633.1 | J80: =IFERROR(IF($I80<=0,"never",$E80/$I80),"") -> 0.18314064 | K80: =IF($H80=0,"no pool — not funded",IF($I80<=0,"operating cost exceeds the pool",IF($E80/$I80<=1,"pays back inside a year",IF($E80/$I80<=3,"pays back inside the hold","does not pay back in the hold")))) -> pays back inside a year
B81: Customer retention and expansion | C81: =COUNTIF('2_Capability_Assessment'!$B$6:$B$41,$B81) -> 4 | D81: =IFERROR('4b_Value_Pools_by_Capability'!$AB$18/SUM('4b_Value_Pools_by_Capability'!$AB$15:$AB$24),0) -> 0.052338645 | E81: =$C$27*$D81 -> 392539.84 | F81: =$C$48*$D81 -> 130846.61 | G81: =$E81+$F81*$C$55 -> 1046772.9 | H81: ='4b_Value_Pools_by_Capability'!$AB$18 -> 2274225.8 | I81: =$H81-$F81 -> 2143379.2 | J81: =IFERROR(IF($I81<=0,"never",$E81/$I81),"") -> 0.18314064 | K81: =IF($H81=0,"no pool — not funded",IF($I81<=0,"operating cost exceeds the pool",IF($E81/$I81<=1,"pays back inside a year",IF($E81/$I81<=3,"pays back inside the hold","does not pay back in the hold")))) -> pays back inside a year
B82: Ecosystem strategy | C82: =COUNTIF('2_Capability_Assessment'!$B$6:$B$41,$B82) -> 3 | D82: =IFERROR('4b_Value_Pools_by_Capability'!$AB$19/SUM('4b_Value_Pools_by_Capability'!$AB$15:$AB$24),0) -> 0.010693077 | E82: =$C$27*$D82 -> 80198.079 | F82: =$C$48*$D82 -> 26732.693 | G82: =$E82+$F82*$C$55 -> 213861.54 | H82: ='4b_Value_Pools_by_Capability'!$AB$19 -> 464637.02 | I82: =$H82-$F82 -> 437904.33 | J82: =IFERROR(IF($I82<=0,"never",$E82/$I82),"") -> 0.18314064 | K82: =IF($H82=0,"no pool — not funded",IF($I82<=0,"operating cost exceeds the pool",IF($E82/$I82<=1,"pays back inside a year",IF($E82/$I82<=3,"pays back inside the hold","does not pay back in the hold")))) -> pays back inside a year
B83: Product engineering | C83: =COUNTIF('2_Capability_Assessment'!$B$6:$B$41,$B83) -> 4 | D83: =IFERROR('4b_Value_Pools_by_Capability'!$AB$20/SUM('4b_Value_Pools_by_Capability'!$AB$15:$AB$24),0) -> 0.20714228 | E83: =$C$27*$D83 -> 1553567.1 | F83: =$C$48*$D83 -> 517855.7 | G83: =$E83+$F83*$C$55 -> 4142845.6 | H83: ='4b_Value_Pools_by_Capability'!$AB$20 -> 9000774.2 | I83: =$H83-$F83 -> 8482918.5 | J83: =IFERROR(IF($I83<=0,"never",$E83/$I83),"") -> 0.18314064 | K83: =IF($H83=0,"no pool — not funded",IF($I83<=0,"operating cost exceeds the pool",IF($E83/$I83<=1,"pays back inside a year",IF($E83/$I83<=3,"pays back inside the hold","does not pay back in the hold")))) -> pays back inside a year
B84: Revenue operations | C84: =COUNTIF('2_Capability_Assessment'!$B$6:$B$41,$B84) -> 3 | D84: =IFERROR('4b_Value_Pools_by_Capability'!$AB$21/SUM('4b_Value_Pools_by_Capability'!$AB$15:$AB$24),0) -> 0.021382615 | E84: =$C$27*$D84 -> 160369.61 | F84: =$C$48*$D84 -> 53456.537 | G84: =$E84+$F84*$C$55 -> 427652.29 | H84: ='4b_Value_Pools_by_Capability'!$AB$21 -> 929120.23 | I84: =$H84-$F84 -> 875663.7 | J84: =IFERROR(IF($I84<=0,"never",$E84/$I84),"") -> 0.18314064 | K84: =IF($H84=0,"no pool — not funded",IF($I84<=0,"operating cost exceeds the pool",IF($E84/$I84<=1,"pays back inside a year",IF($E84/$I84<=3,"pays back inside the hold","does not pay back in the hold")))) -> pays back inside a year
B85: Supplier and infrastructure cost | C85: =COUNTIF('2_Capability_Assessment'!$B$6:$B$41,$B85) -> 3 | D85: =IFERROR('4b_Value_Pools_by_Capability'!$AB$22/SUM('4b_Value_Pools_by_Capability'!$AB$15:$AB$24),0) -> 0.0056726503 | E85: =$C$27*$D85 -> 42544.877 | F85: =$C$48*$D85 -> 14181.626 | G85: =$E85+$F85*$C$55 -> 113453.01 | H85: ='4b_Value_Pools_by_Capability'!$AB$22 -> 246488.76 | I85: =$H85-$F85 -> 232307.13 | J85: =IFERROR(IF($I85<=0,"never",$E85/$I85),"") -> 0.18314064 | K85: =IF($H85=0,"no pool — not funded",IF($I85<=0,"operating cost exceeds the pool",IF($E85/$I85<=1,"pays back inside a year",IF($E85/$I85<=3,"pays back inside the hold","does not pay back in the hold")))) -> pays back inside a year
B86: Employee experience | C86: =COUNTIF('2_Capability_Assessment'!$B$6:$B$41,$B86) -> 4 | D86: =IFERROR('4b_Value_Pools_by_Capability'!$AB$23/SUM('4b_Value_Pools_by_Capability'!$AB$15:$AB$24),0) -> 0.040291067 | E86: =$C$27*$D86 -> 302183 | F86: =$C$48*$D86 -> 100727.67 | G86: =$E86+$F86*$C$55 -> 805821.33 | H86: ='4b_Value_Pools_by_Capability'!$AB$23 -> 1750732.8 | I86: =$H86-$F86 -> 1650005.2 | J86: =IFERROR(IF($I86<=0,"never",$E86/$I86),"") -> 0.18314064 | K86: =IF($H86=0,"no pool — not funded",IF($I86<=0,"operating cost exceeds the pool",IF($E86/$I86<=1,"pays back inside a year",IF($E86/$I86<=3,"pays back inside the hold","does not pay back in the hold")))) -> pays back inside a year
B87: Capital efficiency | C87: =COUNTIF('2_Capability_Assessment'!$B$6:$B$41,$B87) -> 3 | D87: =IFERROR('4b_Value_Pools_by_Capability'!$AB$24/SUM('4b_Value_Pools_by_Capability'!$AB$15:$AB$24),0) -> 0 | E87: =$C$27*$D87 -> 0 | F87: =$C$48*$D87 -> 0 | G87: =$E87+$F87*$C$55 -> 0 | H87: ='4b_Value_Pools_by_Capability'!$AB$24 -> 0 | I87: =$H87-$F87 -> 0 | J87: =IFERROR(IF($I87<=0,"never",$E87/$I87),"") -> never | K87: =IF($H87=0,"no pool — not funded",IF($I87<=0,"operating cost exceeds the pool",IF($E87/$I87<=1,"pays back inside a year",IF($E87/$I87<=3,"pays back inside the hold","does not pay back in the hold")))) -> no pool — not funded
B88: TOTAL | C88: =SUM(C78:C87) -> 36 | D88: =SUM(D78:D87) -> 1 | E88: =SUM(E78:E87) -> 7500000 | F88: =SUM(F78:F87) -> 2500000 | G88: =SUM(G78:G87) -> 20000000 | H88: =SUM(H78:H87) -> 43452134 | I88: =SUM(I78:I87) -> 40952134 | J88: =IFERROR($E88/$I88,"") -> 0.18314064
B90: NOTES
B91: 1. Allocation follows each lever’s share of the timed pool. It is a default, not an observation — replace column D with a bottom-up estimate where you have one.
B92: 2. Capital efficiency carries no pool, so it draws no cost. Nothing is funded against it.
B93: 3. Payback is one-time build divided by net annual value. Operating cost is already netted out of the annual figure.
B94: 4. Five-year cash is build plus operating across the hold, undiscounted. The NPV block above discounts the total at the WACC in C56.
B95: 5. A lever whose operating cost exceeds its pool is flagged. That is a real result, not a modelling error — some levers cost more to run than they return.

Sheet 7_Value_Timing
A2: Value timing — how much of the pool lands inside the window
A3: The value pool is an annual run rate once fully ramped. It does not arrive on day one. How fast it arrives is set entirely by two scores from 5_Implementation_Feasibility — organisational change capacity and data readiness. Everything else here is a parameter you can see and change.
A5: Context — pulled from 5_Implementation_Feasibility
B6: Organisational change capacity | C6: ='5_Implementation_Feasibility'!$E$19 -> 0.75 | F6: Weighted at 0.40 in the delay formula.
B7: Data readiness | C7: ='5_Implementation_Feasibility'!$E$20 -> 0.75 | F7: Weighted at 0.60 in the delay formula — Barr Eq. 35. Data readiness is the MORE binding constraint on adoption speed (Bloom et al. 2016; Brynjolfsson & Hitt 2000). It is no longer applied as a capture gate on the value pools tab, so it belongs here.
B8: Value pool after feasibility (annual run rate) | C8: ='5_Implementation_Feasibility'!$E$14 -> 45273137 | F8: The fully-ramped annual figure. This tab works out how much of it lands in the window.
A10: A. Ramp parameters
B11: Parameter | C11: Value | F11: Note
B12: Value window (months) | C12: 60 | F12: Set to the remaining hold, not the original hold — a sponsor three years into a five-year hold has 24 months left, not 60. This is the most sensitive input on the tab.
B13: Base ramp midpoint (months) | C13: 18 | F13: Where a perfectly prepared company reaches half its run rate. Calibrated so the ramp is 96% complete at 36 months.
B14: Base ramp steepness (k_base) | C14: 0.18 | F14: Barr's k_base. This is now flexed down for unprepared firms in Section B, per Eq. 33.
B15: Delay exponents: change capacity / data readiness | C15: 0.4 | D15: 0.6 | F15: Barr Eq. 35 exponents. They sum to 1.00. Data carries the heavier weight because it binds harder.
A16: B. Firm-specific timing — Barr Eq. 33, 34 and 35
B17: Step | C17: Value | F17: How this number is built
B18: Delay factor | C18: =1/(MAX($C$6,0.1)^$C$15*MAX($C$7,0.1)^$D$15) -> 1.3333333 | F18: Barr Eq. 35: 1 / (change capacity^0.40 x data readiness^0.60), with a 0.10 floor on each to prevent division by zero. Previously this used change capacity alone, which left data readiness affecting nothing anywhere in the workbook.
B19: This company's ramp midpoint (months) | C19: =$C$13*C18 -> 24 | F19: ="Base "&TEXT($C$13,"0")&" months x delay "&TEXT(C18,"0.00")&" = "&TEXT(C19,"0.0")&" months to reach half the run rate." -> Base 18 months x delay 1.33 = 24.0 months to reach half the run rate.
B20: Change-capacity steepness factor | C20: =0.55+0.45*$C$6 -> 0.8875 | F20: Barr Eq. 34: 0.55 + 0.45 x change capacity.
B21: Data-readiness steepness factor | C21: =0.5+0.5*$C$7 -> 0.875 | F21: Barr Eq. 34: 0.50 + 0.50 x data readiness.
B22: This company's ramp steepness (k_f) | C22: =$C$14*C20*C21 -> 0.13978125 | F22: ="Base "&TEXT($C$14,"0.00")&" x "&TEXT(C20,"0.000")&" x "&TEXT(C21,"0.000")&" = "&TEXT(C22,"0.000")&". A flatter curve, not just a later one — this is where most of Barrs value loss comes from." -> Base 0.18 x 0.888 x 0.875 = 0.140. A flatter curve, not just a later one — this is where most of Barrs value loss comes from.
B23: Realised at the start of the window | C23: =1/(1+EXP(-$C$22*(0-$C$19))) -> 0.033739963 | F23: Value already flowing when the program starts. Near zero on a fresh program.
B24: Realised at the end of the window | C24: =1/(1+EXP(-$C$22*($C$12-$C$19))) -> 0.99351737 | F24: ="The pool is "&TEXT($C$8,"#,##0")&" but only "&TEXT(C23,"#,##0")&" arrives inside the window. Raising the organisation's capacity to absorb change is what recovers the difference." -> The pool is 45,273,137 but only 0 arrives inside the window. Raising the organisation's capacity to absorb change is what recovers the difference.
B25: Share of the pool captured in the window | C25: =C24-C23 -> 0.95977741 | F25: ="End of window "&TEXT(C24,"0.0%")&" minus start "&TEXT(C23,"0.0%")&" = "&TEXT(C25,"0.0%")&". Barr Eq. 27: only the increment counts — value already flowing at the start is in the price you paid." -> End of window 99.4% minus start 3.4% = 96.0%. Barr Eq. 27: only the increment counts — value already flowing at the start is in the price you paid.
A26: C. Ramp curve | B26: Value realised in the window (annual run rate) | C26: =$C$8*C25 -> 43452134 | F26: ="Pool "&TEXT($C$8,"#,##0")&" x "&TEXT(C25,"0.0%")&" = "&TEXT(C26,"#,##0")&" per year." -> Pool 45,273,137 x 96.0% = 43,452,134 per year.
B27: Value lost to slow adoption | C27: =$C$8-C26 -> 1821003 | D27: Well-prepared benchmark | F27: ="The pool is "&TEXT($C$8,"#,##0")&" but only "&TEXT(C26,"#,##0")&" arrives inside the window. Raising data readiness moves this more than raising change capacity, because it carries the heavier exponent." -> The pool is 45,273,137 but only 43,452,134 arrives inside the window. Raising data readiness moves this more than raising change capacity, because it carries the heavier exponent.
B28: 0 | C28: =1/(1+EXP(-$C$14*(B28-$C$19))) -> 0.013125318 | D28: =1/(1+EXP(-$C$14*(B28-$C$13))) -> 0.037687891
A29: C. Ramp curve | B29: 3 | C29: =1/(1+EXP(-$C$14*(B29-$C$19))) -> 0.022313439 | D29: =1/(1+EXP(-$C$14*(B29-$C$13))) -> 0.062973356
B30: Month | C30: This company | D30: Well-prepared benchmark
B31: 0 | C31: =1/(1+EXP(-$C$22*(B31-$C$19))) -> 0.033739963 | D31: =1/(1+EXP(-$C$14*(B31-$C$13))) -> 0.037687891
B32: 3 | C32: =1/(1+EXP(-$C$22*(B32-$C$19))) -> 0.050430803 | D32: =1/(1+EXP(-$C$14*(B32-$C$13))) -> 0.062973356
B33: 6 | C33: =1/(1+EXP(-$C$22*(B33-$C$19))) -> 0.074739783 | D33: =1/(1+EXP(-$C$14*(B33-$C$13))) -> 0.10340045
B34: 9 | C34: =1/(1+EXP(-$C$22*(B34-$C$19))) -> 0.10941615 | D34: =1/(1+EXP(-$C$14*(B34-$C$13))) -> 0.16520487
B35: 12 | C35: =1/(1+EXP(-$C$22*(B35-$C$19))) -> 0.15744338 | D35: =1/(1+EXP(-$C$14*(B35-$C$13))) -> 0.25350602
B36: 15 | C36: =1/(1+EXP(-$C$22*(B36-$C$19))) -> 0.22131299 | D36: =1/(1+EXP(-$C$14*(B36-$C$13))) -> 0.36818758
B37: 18 | C37: =1/(1+EXP(-$C$22*(B37-$C$19))) -> 0.30181128 | D37: =1/(1+EXP(-$C$14*(B37-$C$13))) -> 0.5
B38: 21 | C38: =1/(1+EXP(-$C$22*(B38-$C$19))) -> 0.3966738 | D38: =1/(1+EXP(-$C$14*(B38-$C$13))) -> 0.63181242
B39: 24 | C39: =1/(1+EXP(-$C$22*(B39-$C$19))) -> 0.5 | D39: =1/(1+EXP(-$C$14*(B39-$C$13))) -> 0.74649398
B40: 27 | C40: =1/(1+EXP(-$C$22*(B40-$C$19))) -> 0.6033262 | D40: =1/(1+EXP(-$C$14*(B40-$C$13))) -> 0.83479513
B41: 30 | C41: =1/(1+EXP(-$C$22*(B41-$C$19))) -> 0.69818872 | D41: =1/(1+EXP(-$C$14*(B41-$C$13))) -> 0.89659955
B42: 33 | C42: =1/(1+EXP(-$C$22*(B42-$C$19))) -> 0.77868701 | D42: =1/(1+EXP(-$C$14*(B42-$C$13))) -> 0.93702664
... B49: 54 | C49: =1/(1+EXP(-$C$22*(B49-$C$19))) -> 0.98513014 | D49: =1/(1+EXP(-$C$14*(B49-$C$13))) -> 0.99846854
A50: Method: logistic value ramp R(t) = 1 / (1 + exp(-k(t - t50))), with the firm-specific midpoint t50 set by the delay factor 1 / (OCC^0.40 x DR^0.60), per Barr, D. (2026), arXiv:2603.13278, Eq. 35. Only the increment over the window is counted, per his Eq. 27 — using the end-of-window figure alone overstates by 2x to 25x depending on where the firm starts. Departure from the paper: Barr scales the base midpoint from 18 to 60 months with AITG; we fix it at 18 so the ramp is essentially complete at 36 months, which is the window a sponsor actually underwrites. Change the base midpoint in Section A to restore his calibration. | B50: 57 | C50: =1/(1+EXP(-$C$22*(B50-$C$19))) -> 0.99017334 | D50: =1/(1+EXP(-$C$14*(B50-$C$13))) -> 0.99910697
B51: 60 | C51: =1/(1+EXP(-$C$22*(B51-$C$19))) -> 0.99351737 | D51: =1/(1+EXP(-$C$14*(B51-$C$13))) -> 0.9994794
A53: Method: logistic value ramp R(t) = 1 / (1 + exp(-k_f (t - t50,f))). Both the midpoint and the steepness are firm-specific, per Barr Eq. 33-35. The midpoint shifts right by 1 / (OCC^0.40 x DR^0.60); the steepness flattens by (0.55 + 0.45 OCC)(0.50 + 0.50 DR). Barr's point is that an unprepared firm does not take a flat haircut — it starts later AND climbs more slowly, and the two compound. Only the increment between the start and end of the window is counted (Eq. 27), because value already flowing at acquisition is priced into the entry multiple. The benchmark column holds both parameters at their base values.
A57: D. Timing basis by capability
A58: Not every capability is gated by the same thing. Barr's three-wave cascade (Table 4) times capabilities whose constraint is technology diffusion. A capability whose technology is already in production is not waiting on a wave — it is waiting on something commercial, usually contract renewal. Set the basis per capability in column Y of 4b_Value_Pools_by_Capability.
B60: Basis | C60: Steepness (base) | D60: Midpoint (base, months) | E60: What it describes
B61: Wave 1 | C61: 0.38 | D61: 18 | E61: Foundation AI. Supervised ML, RPA, structured analytics, BI automation.
B62: Wave 2 | C62: 0.42 | D62: 36 | E62: Generative and agentic AI. LLM workflows, copilots, RAG pipelines, agentic task execution.
B63: Wave 3 | C63: 0.32 | D63: 60 | E63: Autonomous AI. Multi-agent orchestration, self-improving systems, AI-native products.
B64: Renewal | E64: Retained for cases where a commercial mechanism genuinely gates delivery. Not used for Contoso — the use cases are gated by build and rollout, which is a Wave 2 problem.
B65: Immediate | E65: No adoption gate. Value is available now. Used rarely — needs justifying.
B67: Contract turnover (months) | C67: 36 | E67: Full book turnover for the Renewal basis. Three-year terms, evenly staggered, means 36. A concentrated renewal cliff behaves very differently — set this from the client's actual contract schedule.
B68: Firm delay factor applied to wave midpoints | C68: =$C$18 -> 1.3333333 | E68: Barr: t0,w,f = t0,w,base x (t50,f / t50,base). The same delay shifts every wave.
B69: Months already on the curve (per capability, column AC on 4b) | E69: Barr Eq. 27: the ramp starts from where the firm already is, not from zero. Delta R = R(t+window) - R(t). Value already flowing is in the baseline and must not be counted twice. Set 0 for work not yet started.

Sheet 8_Enterprise_Value
A1: Enterprise value created
A2: Every step from the whole theoretical prize down to the number a sponsor can underwrite. Each line pulls from the tab that produced it, so nothing is retyped. The only input on this tab is the exit multiple — and it is the single largest source of variance in the entire model.
A4: A. The chain, step by step
B5: Step | C5: Value | D5: Retained | E5: Where it comes from and what it removes
B6: Total possible pool (annual) | C6: ='4b_Value_Pools_by_Capability'!$E$28 -> 484890000 | D6: =IF($C$6=0,0,C6/$C$6) -> 1 | E6: 4b_Value_Pools_by_Capability. Revenue x each capability's base and uplift. The whole prize before any haircut.
B7: Capturable at current capability | C7: ='4b_Value_Pools_by_Capability'!$E$29 -> 49628021 | D7: =IF($C$6=0,0,C7/$C$6) -> 0.10234903 | E7: 4b_Value_Pools_by_Capability. After the capture ceiling, reachability from each capability's own distance, and readiness from its score over its ceiling.
B8: After implementation feasibility | C8: ='5_Implementation_Feasibility'!$E$14 -> 45273137 | D8: =IF($C$6=0,0,C8/$C$6) -> 0.09336785 | E8: 5_Implementation_Feasibility. Removes vendor risk, competitive response speed and regulatory exposure, combined as a geometric multiplier.
B9: After timing | C9: ='4b_Value_Pools_by_Capability'!$E$38 -> 43452134 | D9: =IF($C$6=0,0,C9/$C$6) -> 0.089612353 | E9: Per-capability timing on 4b. Each capability uses the mechanism that actually gates it — a Barr wave where technology adoption is the constraint, contract turnover where it is not.
B10: Annual run-rate uplift the sponsor can underwrite | C10: =C9 -> 43452134 | E10: This is an annual figure. It becomes enterprise value only when capitalised at an exit multiple.
A12: B. Split the pool: revenue drivers and EBITDA drivers
A13: A dollar of recurring revenue and a dollar of cost saved are not worth the same. Revenue carries the ARR multiple; cost saved drops fully to EBITDA and carries the EBITDA multiple. The two shares come from the revenue-share column on 4b, and feasibility and timing are applied to each proportionally.
B15: Revenue effect, after feasibility and timing | C15: ='4b_Value_Pools_by_Capability'!$E$40 -> 25959292 | E15: 4b column Q. New or retained revenue.
B16: Cash EBITDA effect, after feasibility and timing | C16: ='4b_Value_Pools_by_Capability'!$E$41 -> 17492842 | E16: 4b column W. Cost effect after cash conversion. Capacity that never reaches EBITDA is excluded.
B17: Combined, after feasibility and timing | C17: =C15+C16 -> 43452134 | E17: Lower than the adjusted pool at C7 because unconverted capacity is dropped here.
A18: C. Capitalise — the multiple is set by distance to the AI-native frontier | B18: Feasibility x timing retention | C18: 1 | E18: Set to 1 deliberately. C15 and C16 read from 4b rows 50-51, which already multiply by the feasibility factor and by each capability's share landing in the window — they are fully timed. Applying a retention factor here would count feasibility and timing twice. C17 therefore equals C9, the after-timing pool.
B19: Revenue effect, underwritable | C19: =C15*$C$18 -> 25959292
B20: Cash EBITDA effect, underwritable | C20: =C16*$C$18 -> 17492842
B22: C. ENTERPRISE VALUE
B23: One chain. Closing the capability gap captures the value pool. The pool does two things at once: its revenue half adds to ARR, and the whole of it improves growth, which moves the multiple. Enterprise value is the new ARR times the new multiple. The pool is never capitalised separately — that would count it twice.
B25: ARR today | C25: ='0_AI_to_EV_Bridge'!$C$8 -> 1200000000 | E25: Set on tab 0.
B26: Multiple today | C26: ='0_AI_to_EV_Bridge'!$C$12 -> 9.1666667 | E26: Enterprise value divided by the metric set by the basis at entry.
B27: Enterprise value today | C27: ='0_AI_to_EV_Bridge'!$C$7 -> 11000000000 | E27: Set on tab 0.
B28: Revenue effect in the pool | C28: =$C$19 -> 25959292 | E28: The part of the pool that adds to ARR, after feasibility and timing.
B29: NPV of programme cost | C29: ='6_Implementation_Cost'!$C$64 -> 16295149 | E29: Barr Eq. 26.
B32: CAPABILITY POSITION | C32: ARR | D32: MULTIPLE | E32: ENTERPRISE VALUE | F32: ΔEV | G32: ΔEV NET OF COST
B33: Stay where you are | C33: =$C$25+$C$28*0 -> 1200000000 | D33: ='4m_Exit_Multiple'!$E$22 -> 9.1666667 | E33: =$C33*$D33 -> 11000000000 | F33: =$E33-$C$27 -> 0 | G33: =$F33-$C$29 -> -16295149
B34: Move one level | C34: =$C$25+$C$28*0.46 -> 1.2119413e+09 | D34: ='4m_Exit_Multiple'!$E$23 -> 9.2865019 | E34: =$C34*$D34 -> 1.1254695e+10 | F34: =$E34-$C$27 -> 2.5469494e+08 | G34: =$F34-$C$29 -> 2.3839979e+08
B35: Move two levels | C35: =$C$25+$C$28*0.93 -> 1.2241421e+09 | D35: ='4m_Exit_Multiple'!$E$24 -> 9.4089422 | E35: =$C35*$D35 -> 1.1517883e+10 | F35: =$E35-$C$27 -> 5.1788271e+08 | G35: =$F35-$C$29 -> 5.0158756e+08
B36: Close the gap entirely | C36: =$C$25+$C$28*1 -> 1.2259593e+09 | D36: ='4m_Exit_Multiple'!$E$25 -> 9.427178 | E36: =$C36*$D36 -> 1.1557337e+10 | F36: =$E36-$C$27 -> 5.5733651e+08 | G36: =$F36-$C$29 -> 5.4104136e+08
B38: Value density (ΔEV net of cost, per unit of cost) | C38: =IFERROR($G35/$C$29,0) -> 30.781404 | E38: At two levels. Barr Def. 7.1: 2.0x or better is Tier 1, invest.
B41: HOW TO READ IT
B42: 1. Standing still creates nothing and still costs the NPV of the programme.
B43: 2. ARR rises by the revenue half of the pool. The cost half does not add to ARR but does improve margin, which feeds the multiple.
B44: 3. The multiple comes from 4m_Exit_Multiple, driven by ARR growth on 4d, which is new logo growth plus expansion. All ten value levers reach it.
B45: 4. The pool is not capitalised anywhere. Capitalising it and also letting it move the multiple would count the same money twice.
B46: 5. Scale factors of 0.46 and 0.93 for one and two levels come from the maturity term on tab 2. No published data maps a capability level to a growth rate, so this is the weakest link in the chain.
B47: 6. The enterprise value on tab 0 has not been tested against comparables. Contoso at 13% growth sits in a cohort with a 3.1x median; its 9.17x is roughly three times that.
B50: D. DISCOUNTED CASH FLOW — intrinsic value of the programme
B51: The incremental cash the programme throws off, discounted at WACC. Independent of any multiple, so it is a cross-check on the comps answer above. Cash in each year is the pool times the share of the ramp realised by then, less operating cost, less the build in year one.
B53: YEAR | C53: RAMP REALISED | D53: GROSS CASH | E53: LESS OPEX | F53: LESS BUILD | G53: NET CASH | H53: DISCOUNTED
B54: 1 | C54: 0.12888761 | D54: =$C$9*$C54 -> 5600441.5 | E54: -2500000 | F54: -7500000 | G54: =$D54+$E54+$F54 -> -4399558.5 | H54: =$G54/(1+'6_Implementation_Cost'!$C$56)^1 -> -3999598.6
B55: 2 | C55: 0.48580018 | D55: =$C$9*$C55 -> 21109054 | E55: -2500000 | F55: 0 | G55: =$D55+$E55+$F55 -> 18609054 | H55: =$G55/(1+'6_Implementation_Cost'!$C$56)^2 -> 15379384
B56: 3 | C56: 0.84271276 | D56: =$C$9*$C56 -> 36617667 | E56: -2500000 | F56: 0 | G56: =$D56+$E56+$F56 -> 34117667 | H56: =$G56/(1+'6_Implementation_Cost'!$C$56)^3 -> 25633109
B57: 4 | C57: 0.97160036 | D57: =$C$9*$C57 -> 42218109 | E57: -2500000 | F57: 0 | G57: =$D57+$E57+$F57 -> 39718109 | H57: =$G57/(1+'6_Implementation_Cost'!$C$56)^4 -> 27128003
B58: 5 | C58: 1 | D58: =$C$9*$C58 -> 43452134 | E58: -2500000 | F58: 0 | G58: =$D58+$E58+$F58 -> 40952134 | H58: =$G58/(1+'6_Implementation_Cost'!$C$56)^5 -> 25428053
B59: NPV of the explicit five years | C59: =SUM($H$54:$H$58) -> 89568950 | E59: Sum of the discounted column.
B60: Terminal value at the exit multiple | C60: =$C$9*'4m_Exit_Multiple'!$E$24/(1+'6_Implementation_Cost'!$C$56)^5 -> 2.5385662e+08 | E60: Run-rate pool at the two-level multiple, discounted back five years.
B61: DCF value of the programme | C61: =$C$59+$C$60 -> 3.4342557e+08 | E61: Explicit period plus terminal value. Compare against the comps answer on row 35.
B64: E. LBO FLOOR — what a sponsor could pay
B65: Solves for the entry price at which a sponsor still clears its target return, given the exit multiple the model predicts and the EBITDA the programme creates. Not a view of worth — a floor. Where it sits above the market price, the asset is cheap to a financial buyer.
B67: ENTER: target gross MOIC | C67: 2.5 | E67: Money multiple a sponsor underwrites over the hold. 2.5x on five years is roughly a 20% IRR.
B68: ENTER: hold period (years) | C68: 5 | E68: Matches the value window on tab 7.
B69: ENTER: leverage at entry | C69: 0.5 | E69: Debt as a share of enterprise value.
B70: ARR at exit, two levels | C70: =$C$35 -> 1.2241421e+09 | E70: From the chain above.
B71: Exit multiple, two levels | C71: ='4m_Exit_Multiple'!$E$24 -> 9.4089422 | E71: From 4m_Exit_Multiple.
B72: Exit enterprise value | C72: =$C$35*$D$35 -> 1.1517883e+10 | E72: ARR at exit times the exit multiple.
B73: Equity at exit | C73: =$C$72*(1-$C$69) -> 5.7589414e+09 | E73: Assumes debt is repaid in line with entry leverage.
B74: Maximum equity at entry | C74: =IFERROR($C$73/$C$67,0) -> 2.3035765e+09 | E74: Exit equity divided by the target money multiple.
B75: MAXIMUM ENTRY PRICE | C75: =IFERROR($C$74/(1-$C$69),0) -> 4.6071531e+09 | E75: Grossed back up for leverage. The floor.
B76: Against the enterprise value on tab 0 | C76: =IFERROR($C$75/$C$27-1,0) -> -0.5811679 | E76: Positive means a sponsor could pay more than the current mark. Negative means the asset is priced above what the return requirement supports.
B79: F. THE RANGE — what each method says
B80: No single method is the answer. Where they overlap is the zone a deal gets done.
B81: METHOD | C81: ENTERPRISE VALUE | E81: WHAT IT ANSWERS
B82: Trading comps, two levels | C82: =$E$35 -> 1.1517883e+10 | E82: How the market prices peers at that growth rate. Minority value, no control premium.
B83: DCF | C83: =$C$27+$C$61 -> 1.1343426e+10 | E83: Intrinsic value of the cash the programme produces, independent of any multiple.
B84: LBO floor | C84: =$C$75 -> 4.6071531e+09 | E84: What a sponsor could pay and still clear its return. A floor, not a view of worth.
B85: Precedent transaction | C85: =$C$25*18.1 -> 21720000000 | E85: Anaplan at 18.1x revenue, March 2022. Embeds a control premium and predates the derating.
B86: Current mark, tab 0 | C86: =$C$27 -> 11000000000 | E86: The figure entered. Untested against any of the above.
